Workbook

Sheet Read me
A2: IBCS® notation on The Progressive Corporation's reported figures
A4: One sheet per template. Each sheet has two zones: the source data on the left, the charts to its right. They never overlap.
A6: The workbook is live. On any template sheet the two shaded columns are typed inputs - the reference scenario and the measure. Everything from the variance columns rightwards is a formula, so retyping a figure recalculates the variances and redraws the chart, including changing a bar's colour if the variance changes sign.
A8: The columns to the right of the variances feed the charts. They are derived, not data: Excel colours a whole series rather than a point, so a variance that must be green when positive and red when negative is plotted as two mutually exclusive series.
A10: The words are live too. The shaded cells at the top of each sheet hold the entity, measure, unit, period, reference scenario and message; the greyed lines under them - the subject line and each tier caption - are built from those cells, and the text on the charts is linked to them. Retype the unit once and every caption follows. Nothing a chart says is typed into the chart itself.
A12: Charts follow IBCS® notation: fill encodes how a number came to exist (solid dark actual, solid light prior year, outlined plan, hatched forecast), and variance colour encodes impact rather than sign.
A14: IBCS® does not prescribe colour codes (rule UN 4.1). The palette here is a house choice sampled to match the published reference renders.
A16: A third shade. Cells shaded blue are typed like the others, but hold figures the entity never published - a plan or forecast constructed here on a basis stated under the data and on the Sources sheet. Everything else shaded is as reported. Replace either and the charts follow. Scenarios constructed this way: FC, PL.
A18: Figures are from public filings: SEC EDGAR CIK 0000080661, 10-K Exhibit 13 state tables; SEC EDGAR CIK 0000080661, 10-K and monthly 8-K exhibits; SEC EDGAR CIK 0000080661, 10-Q and 10-K reserve roll-forward; SEC EDGAR CIK 0000080661, XBRL companyfacts; SEC EDGAR CIK 0000080661, monthly 8-K exhibits; SEC EDGAR CIK 0000080661, monthly 8-K exhibits and 10-K; SEC EDGAR CIK 0000080661, monthly 8-K exhibits and XBRL. Every figure is either read from a filing or derived from ones that were, and the Sources sheet says which.
A20: Drawn in IBCS® notation from publicly reported figures. IBCS® is a registered trademark of the IBCS Association; this is not an IBCS Institute publication and is not endorsed by, affiliated with, or produced in cooperation with it.
A22: Not affiliated with, endorsed by, or produced in cooperation with The Progressive Corporation. This workbook is an independent presentation of figures that company published; it is not that company's reporting.

Sheet Sources
A1: Where the figures come from
A3: Sheet | B3: Scenario | C3: Basis | D3: Detail
A4: C01A | B4: AC | C4: filed | D4: Segment premium from the year-to-date block of each December monthly release; state premium from the 10-K annual-report exhibit. Both reconcile to the same companywide total.
A5: C02A | B5: AC | C5: filed | D5: Full-year 2025 segment earned premium and the loss and expense ratios, from the year-to-date block of the December monthly release. Losses and expenses are those ratios applied to earned premium; the underwriting result is what remains.
A6: C03A | B6: AC | C6: filed | D6: Monthly net premiums written, Exhibit 99 to the monthly 8-K. Twelve months reconcile to the 10-K annual figure.
A7: C03A | B7: PY | C7: filed | D7: The same series for 2025.
A8: C03A | B8: FC | C8: assumed | D8: Progressive publishes no forecast. Remaining months are prior-year months grown at the year-to-date pace through Jul (+5.7%).
A9: C04A | B9: AC | C9: filed | D9: Monthly net premiums earned and combined ratio from the 2023 monthly 8-K exhibits; the underwriting result is premium times (100 - combined ratio).
A10: C04A | B10: PL | C10: assumed | D10: Progressive publishes no monthly plan. The target it does publish is a 96 combined ratio - a 4% underwriting margin - applied here to each month's earned premium.
A11: C05X | B11: AC | C11: derived | D11: Earned premium times (100 - combined ratio), both from the monthly 8-K exhibit. The same series C07C draws.
A12: C05X | B12: PY | C12: derived | D12: The same calculation over the twelve months of 2025.
A13: C05X | B13: PL | C13: assumed | D13: The 96 combined ratio target applied to the premium each month actually earned. The target is filed; using it as a monthly plan is this workbook's construction, and it is a floor the company aims to beat rather than a forecast.
A14: C05X | B14: FC | C14: assumed | D14: Remaining months are the prior year's at the year-to-date pace, earning the year-to-date margin - the basis C07C states and the same numbers.
... A42: T04A | B42: PL | C42: assumed | D42: The 96 combined ratio target with the expense ratio held where it actually landed, so the whole of the target falls on losses. The target is filed; resolving it into a statement line is this workbook's construction.
A44: filed = the figure appears in a filing. derived = computed from filed figures by the rule stated beside it. assumed = a modelling choice the entity never published; shaded on its own sheet so it cannot be mistaken for something reported.

Sheet C01A
A1: Entity | B1: The Progressive Corporation
A2: Measure | B2: Net premiums written
A3: Unit | B3: $m
A4: Period | B4: 2021..2025
A5: Reference | B5: PL
A6: Message | B6: Direct auto has grown from 18,911 to 39,631 $m since 2021, +110%, and now writes 48% of premium; Texas and Florida together account for 25% of the 2025 book
A7: Subject | B7: =B2&IF(B3="",""," in "&B3) -> Net premiums written in $m
A9: By segment | B9: 2021 AC | C9: 2022 AC | D9: 2023 AC | E9: 2024 AC | F9: 2025 AC
A10: Agency auto | B10: 17258 | C10: 18334 | D10: 22278 | E10: 26967 | F10: 29825
A11: Direct auto | B11: 18911 | C11: 20944 | D11: 26303 | E11: 33432 | F11: 39631
A12: Property | B12: 2216 | C12: 2402 | D12: 2831 | E12: 3071 | F12: 3102
A13: Commercial | B13: 8016 | C13: 9399 | D13: 10138 | E13: 10953 | F13: 10613
A14: Other | B14: 4 | C14: 2 | D14: 0 | E14: 1 | F14: 3
A15: Total | B15: =SUM(B10:B14) -> 46405 | C15: =SUM(C10:C14) -> 51081 | D15: =SUM(D10:D14) -> 61550 | E15: =SUM(E10:E14) -> 74424 | F15: =SUM(F10:F14) -> 83174
A17: By state | B17: 2025 AC
A18: Texas | B18: 10315
A19: Florida | B19: 10261
A20: California | B20: 4777
A21: Georgia | B21: 4084
A22: New York | B22: 3359
A23: All other | B23: 50378
A24: Total | B24: =SUM(B18:B23) -> 83174
A26: span | B26: =MAX(_xlfn.AGGREGATE(4,6,B15:F15,B24:B24),0.000000001) -> 83174
B38: =IF(ISBLANK(B10),NA(),B10/$B$26) -> 0.20749273 | C38: =IF(ISBLANK(C10),NA(),C10/$B$26) -> 0.22042946 | D38: =IF(ISBLANK(D10),NA(),D10/$B$26) -> 0.26784813 | E38: =IF(ISBLANK(E10),NA(),E10/$B$26) -> 0.32422392 | F38: =IF(ISBLANK(F10),NA(),F10/$B$26) -> 0.35858562
B39: =IF(ISBLANK(B11),NA(),B11/$B$26) -> 0.22736673 | C39: =IF(ISBLANK(C11),NA(),C11/$B$26) -> 0.25180946 | D39: =IF(ISBLANK(D11),NA(),D11/$B$26) -> 0.31624065 | E39: =IF(ISBLANK(E11),NA(),E11/$B$26) -> 0.40195253 | F39: =IF(ISBLANK(F11),NA(),F11/$B$26) -> 0.47648304
B40: =IF(ISBLANK(B12),NA(),B12/$B$26) -> 0.026642941 | C40: =IF(ISBLANK(C12),NA(),C12/$B$26) -> 0.028879217 | D40: =IF(ISBLANK(D12),NA(),D12/$B$26) -> 0.034037079 | E40: =IF(ISBLANK(E12),NA(),E12/$B$26) -> 0.036922596 | F40: =IF(ISBLANK(F12),NA(),F12/$B$26) -> 0.037295309
B41: =IF(ISBLANK(B13),NA(),B13/$B$26) -> 0.096376271 | C41: =IF(ISBLANK(C13),NA(),C13/$B$26) -> 0.11300406 | D41: =IF(ISBLANK(D13),NA(),D13/$B$26) -> 0.12188905 | E41: =IF(ISBLANK(E13),NA(),E13/$B$26) -> 0.13168779 | F41: =IF(ISBLANK(F13),NA(),F13/$B$26) -> 0.12759997
B42: =IF(ISBLANK(B14),NA(),B14/$B$26) -> 4.8091952e-05 | C42: =IF(ISBLANK(C14),NA(),C14/$B$26) -> 2.4045976e-05 | D42: =IF(ISBLANK(D14),NA(),D14/$B$26) -> 0 | E42: =IF(ISBLANK(E14),NA(),E14/$B$26) -> 1.2022988e-05 | F42: =IF(ISBLANK(F14),NA(),F14/$B$26) -> 3.6068964e-05
B43: =IF(ISBLANK(B15),NA(),B15/$B$26) -> 0.55792676 | C43: =IF(ISBLANK(C15),NA(),C15/$B$26) -> 0.61414625 | D43: =IF(ISBLANK(D15),NA(),D15/$B$26) -> 0.74001491 | E43: =IF(ISBLANK(E15),NA(),E15/$B$26) -> 0.89479886 | F43: =IF(ISBLANK(F15),NA(),F15/$B$26) -> 1
B46: =IF(ISBLANK(B18),NA(),B18/$B$26) -> 0.12401712
B47: =IF(ISBLANK(B19),NA(),B19/$B$26) -> 0.12336788
B48: =IF(ISBLANK(B20),NA(),B20/$B$26) -> 0.057433813
B49: =IF(ISBLANK(B21),NA(),B21/$B$26) -> 0.049101883
B50: =IF(ISBLANK(B22),NA(),B22/$B$26) -> 0.040385217
B51: =IF(ISBLANK(B23),NA(),B23/$B$26) -> 0.60569409
B52: =IF(ISBLANK(B24),NA(),B24/$B$26) -> 1
B66: =IF(ISBLANK(B10),"",IF(B10/83180*264<(LEN(TEXT(B10,"# ##0")))*5,"",TEXT(B10,"# ##0"))) -> 17 258 | C66: =IF(ISBLANK(C10),"",IF(C10/83180*264<(LEN(TEXT(C10,"# ##0")))*5,"",TEXT(C10,"# ##0"))) -> 18 334 | D66: =IF(ISBLANK(D10),"",IF(D10/83180*264<(LEN(TEXT(D10,"# ##0")))*5,"",TEXT(D10,"# ##0"))) -> 22 278 | E66: =IF(ISBLANK(E10),"",IF(E10/83180*264<(LEN(TEXT(E10,"# ##0")))*5,"",TEXT(E10,"# ##0"))) -> 26 967 | F66: =IF(ISBLANK(F10),"",IF(F10/83180*264<(LEN(TEXT(F10,"# ##0")))*5,"",TEXT(F10,"# ##0"))) -> 29 825
B67: =IF(ISBLANK(B11),"",IF(B11/83180*264<(LEN(TEXT(B11,"# ##0")))*5,"",TEXT(B11,"# ##0"))) -> 18 911 | C67: =IF(ISBLANK(C11),"",IF(C11/83180*264<(LEN(TEXT(C11,"# ##0")))*5,"",TEXT(C11,"# ##0"))) -> 20 944 | D67: =IF(ISBLANK(D11),"",IF(D11/83180*264<(LEN(TEXT(D11,"# ##0")))*5,"",TEXT(D11,"# ##0"))) -> 26 303 | E67: =IF(ISBLANK(E11),"",IF(E11/83180*264<(LEN(TEXT(E11,"# ##0")))*5,"",TEXT(E11,"# ##0"))) -> 33 432 | F67: =IF(ISBLANK(F11),"",IF(F11/83180*264<(LEN(TEXT(F11,"# ##0")))*5,"",TEXT(F11,"# ##0"))) -> 39 631
B68: =IF(ISBLANK(B12),"",IF(B12/83180*264<(LEN(TEXT(B12,"# ##0")))*5,"",TEXT(B12,"# ##0"))) | C68: =IF(ISBLANK(C12),"",IF(C12/83180*264<(LEN(TEXT(C12,"# ##0")))*5,"",TEXT(C12,"# ##0"))) | D68: =IF(ISBLANK(D12),"",IF(D12/83180*264<(LEN(TEXT(D12,"# ##0")))*5,"",TEXT(D12,"# ##0"))) | E68: =IF(ISBLANK(E12),"",IF(E12/83180*264<(LEN(TEXT(E12,"# ##0")))*5,"",TEXT(E12,"# ##0"))) | F68: =IF(ISBLANK(F12),"",IF(F12/83180*264<(LEN(TEXT(F12,"# ##0")))*5,"",TEXT(F12,"# ##0")))
B69: =IF(ISBLANK(B13),"",IF(B13/83180*264<(LEN(TEXT(B13,"# ##0")))*5,"",TEXT(B13,"# ##0"))) -> 8 016 | C69: =IF(ISBLANK(C13),"",IF(C13/83180*264<(LEN(TEXT(C13,"# ##0")))*5,"",TEXT(C13,"# ##0"))) -> 9 399 | D69: =IF(ISBLANK(D13),"",IF(D13/83180*264<(LEN(TEXT(D13,"# ##0")))*5,"",TEXT(D13,"# ##0"))) -> 10 138 | E69: =IF(ISBLANK(E13),"",IF(E13/83180*264<(LEN(TEXT(E13,"# ##0")))*5,"",TEXT(E13,"# ##0"))) -> 10 953 | F69: =IF(ISBLANK(F13),"",IF(F13/83180*264<(LEN(TEXT(F13,"# ##0")))*5,"",TEXT(F13,"# ##0"))) -> 10 613
B70: =IF(ISBLANK(B14),"",IF(B14/83180*264<(LEN(TEXT(B14,"# ##0"))+LEN(TEXT(B15,"# ##0")))*5,"",TEXT(B14,"# ##0"))) | C70: =IF(ISBLANK(C14),"",IF(C14/83180*264<(LEN(TEXT(C14,"# ##0"))+LEN(TEXT(C15,"# ##0")))*5,"",TEXT(C14,"# ##0"))) | D70: =IF(ISBLANK(D14),"",IF(D14/83180*264<(LEN(TEXT(D14,"# ##0"))+LEN(TEXT(D15,"# ##0")))*5,"",TEXT(D14,"# ##0"))) | E70: =IF(ISBLANK(E14),"",IF(E14/83180*264<(LEN(TEXT(E14,"# ##0"))+LEN(TEXT(E15,"# ##0")))*5,"",TEXT(E14,"# ##0"))) | F70: =IF(ISBLANK(F14),"",IF(F14/83180*264<(LEN(TEXT(F14,"# ##0"))+LEN(TEXT(F15,"# ##0")))*5,"",TEXT(F14,"# ##0")))
B71: =IF(ISBLANK(B15),"",IF(B15/83180*264<(LEN(TEXT(B15,"# ##0")))*5,"",TEXT(B15,"# ##0"))) -> 46 405 | C71: =IF(ISBLANK(C15),"",IF(C15/83180*264<(LEN(TEXT(C15,"# ##0")))*5,"",TEXT(C15,"# ##0"))) -> 51 081 | D71: =IF(ISBLANK(D15),"",IF(D15/83180*264<(LEN(TEXT(D15,"# ##0")))*5,"",TEXT(D15,"# ##0"))) -> 61 550 | E71: =IF(ISBLANK(E15),"",IF(E15/83180*264<(LEN(TEXT(E15,"# ##0")))*5,"",TEXT(E15,"# ##0"))) -> 74 424 | F71: =IF(ISBLANK(F15),"",IF(F15/83180*264<(LEN(TEXT(F15,"# ##0")))*5,"",TEXT(F15,"# ##0"))) -> 83 174
B74: =IF(ISBLANK(B18),"",IF(B18/83180*264<(LEN(TEXT(B18,"# ##0")))*5,"",TEXT(B18,"# ##0"))) -> 10 315
B75: =IF(ISBLANK(B19),"",IF(B19/83180*264<(LEN(TEXT(B19,"# ##0")))*5,"",TEXT(B19,"# ##0"))) -> 10 261
B76: =IF(ISBLANK(B20),"",IF(B20/83180*264<(LEN(TEXT(B20,"# ##0")))*5,"",TEXT(B20,"# ##0")))
B77: =IF(ISBLANK(B21),"",IF(B21/83180*264<(LEN(TEXT(B21,"# ##0")))*5,"",TEXT(B21,"# ##0")))
B78: =IF(ISBLANK(B22),"",IF(B22/83180*264<(LEN(TEXT(B22,"# ##0")))*5,"",TEXT(B22,"# ##0")))
B79: =IF(ISBLANK(B23),"",IF(B23/83180*264<(LEN(TEXT(B23,"# ##0"))+LEN(TEXT(B24,"# ##0")))*5,"",TEXT(B23,"# ##0"))) -> 50 378
B80: =IF(ISBLANK(B24),"",IF(B24/83180*264<(LEN(TEXT(B24,"# ##0")))*5,"",TEXT(B24,"# ##0"))) -> 83 174

Sheet C02A
A1: Entity | B1: The Progressive Corporation
A2: Measure | B2: Net premiums earned
A3: Unit | B3: $m
A4: Period | B4: 2025
A5: Reference | B5: PL
A6: Message | B6: Of 81,659 $m earned in 2025, 53,866 went to losses and 17,523 to expenses, leaving an underwriting result of 10,270 $m (12.6%); Property keeps the largest share of its premium at 24.9% and Direct auto the smallest at 9.9%
A7: Subject | B7: =B2&IF(B3="",""," in "&B3) -> Net premiums earned in $m
A9: C02A | B9: Agency auto | C9: Direct auto | D9: Property | E9: Personal Lines | F9: Commercial | G9: Companywide
A10: Losses and LAE | B10: 19186 | C10: 26030 | D10: 1424 | E10: =SUM(B10:D10) -> 46640 | F10: 7225 | G10: =SUM(B10:D10)+F10 -> 53865
A11: Expenses | B11: 5906 | C11: 8460 | D11: 916 | E11: =SUM(B11:D11) -> 15282 | F11: 2241 | G11: =SUM(B11:D11)+F11 -> 17523
A12: Underwriting result | B12: 4290 | C12: 3790 | D12: 776 | E12: =SUM(B12:D12) -> 8856 | F12: 1415 | G12: =SUM(B12:D12)+F12 -> 10271
A13: Total | B13: =SUM(B10:B12) -> 29382 | C13: =SUM(C10:C12) -> 38280 | D13: =SUM(D10:D12) -> 3116 | E13: =SUM(E10:E12) -> 70778 | F13: =SUM(F10:F12) -> 10881 | G13: =SUM(G10:G12) -> 81659
A15: span | B15: =MAX(_xlfn.AGGREGATE(4,6,$B$13:$D$13,$F$13:$F$13),0.000000001) -> 38280
B27: =IF(ISBLANK(B10),NA(),B10/$B$15) -> 0.50120167 | C27: =IF(ISBLANK(C10),NA(),C10/$B$15) -> 0.67998955 | D27: =IF(ISBLANK(D10),NA(),D10/$B$15) -> 0.037199582 | E27: =IF(ISBLANK(E10),NA(),E10/$B$15) -> 1.2183908 | F27: =IF(ISBLANK(F10),NA(),F10/$B$15) -> 0.18874086 | G27: =IF(ISBLANK(G10),NA(),G10/$B$15) -> 1.4071317
B28: =IF(ISBLANK(B11),NA(),B11/$B$15) -> 0.15428422 | C28: =IF(ISBLANK(C11),NA(),C11/$B$15) -> 0.22100313 | D28: =IF(ISBLANK(D11),NA(),D11/$B$15) -> 0.023928945 | E28: =IF(ISBLANK(E11),NA(),E11/$B$15) -> 0.3992163 | F28: =IF(ISBLANK(F11),NA(),F11/$B$15) -> 0.05854232 | G28: =IF(ISBLANK(G11),NA(),G11/$B$15) -> 0.45775862
B29: =IF(ISBLANK(B12),NA(),B12/$B$15) -> 0.11206897 | C29: =IF(ISBLANK(C12),NA(),C12/$B$15) -> 0.099007315 | D29: =IF(ISBLANK(D12),NA(),D12/$B$15) -> 0.020271682 | E29: =IF(ISBLANK(E12),NA(),E12/$B$15) -> 0.23134796 | F29: =IF(ISBLANK(F12),NA(),F12/$B$15) -> 0.036964472 | G29: =IF(ISBLANK(G12),NA(),G12/$B$15) -> 0.26831243
B30: =IF(ISBLANK(B13),NA(),B13/$B$15) -> 0.76755486 | C30: =IF(ISBLANK(C13),NA(),C13/$B$15) -> 1 | D30: =IF(ISBLANK(D13),NA(),D13/$B$15) -> 0.081400209 | E30: =IF(ISBLANK(E13),NA(),E13/$B$15) -> 1.8489551 | F30: =IF(ISBLANK(F13),NA(),F13/$B$15) -> 0.28424765 | G30: =IF(ISBLANK(G13),NA(),G13/$B$15) -> 2.1332027
B44: =IF(ISBLANK(B10),"",IF(B10/38300*492.8<(LEN(TEXT(B10,"# ##0")))*5,"",TEXT(B10,"# ##0"))) -> 19 186 | C44: =IF(ISBLANK(C10),"",IF(C10/38300*492.8<(LEN(TEXT(C10,"# ##0")))*5,"",TEXT(C10,"# ##0"))) -> 26 030 | D44: =IF(ISBLANK(D10),"",IF(D10/38300*492.8<(LEN(TEXT(D10,"# ##0")))*5,"",TEXT(D10,"# ##0"))) | E44: =IF(ISBLANK(E10),"",IF(E10/38300*492.8<(LEN(TEXT(E10,"# ##0")))*5,"",TEXT(E10,"# ##0"))) -> 46 640 | F44: =IF(ISBLANK(F10),"",IF(F10/38300*492.8<(LEN(TEXT(F10,"# ##0")))*5,"",TEXT(F10,"# ##0"))) -> 7 225 | G44: =IF(ISBLANK(G10),"",IF(G10/38300*492.8<(LEN(TEXT(G10,"# ##0")))*5,"",TEXT(G10,"# ##0"))) -> 53 865
B45: =IF(ISBLANK(B11),"",IF(B11/38300*492.8<(LEN(TEXT(B11,"# ##0")))*5,"",TEXT(B11,"# ##0"))) -> 5 906 | C45: =IF(ISBLANK(C11),"",IF(C11/38300*492.8<(LEN(TEXT(C11,"# ##0")))*5,"",TEXT(C11,"# ##0"))) -> 8 460 | D45: =IF(ISBLANK(D11),"",IF(D11/38300*492.8<(LEN(TEXT(D11,"# ##0")))*5,"",TEXT(D11,"# ##0"))) | E45: =IF(ISBLANK(E11),"",IF(E11/38300*492.8<(LEN(TEXT(E11,"# ##0")))*5,"",TEXT(E11,"# ##0"))) -> 15 282 | F45: =IF(ISBLANK(F11),"",IF(F11/38300*492.8<(LEN(TEXT(F11,"# ##0")))*5,"",TEXT(F11,"# ##0"))) -> 2 241 | G45: =IF(ISBLANK(G11),"",IF(G11/38300*492.8<(LEN(TEXT(G11,"# ##0")))*5,"",TEXT(G11,"# ##0"))) -> 17 523
B46: =IF(ISBLANK(B12),"",IF(B12/38300*492.8<(LEN(TEXT(B12,"# ##0"))+LEN(TEXT(B13,"# ##0")))*5,"",TEXT(B12,"# ##0"))) -> 4 290 | C46: =IF(ISBLANK(C12),"",IF(C12/38300*492.8<(LEN(TEXT(C12,"# ##0"))+LEN(TEXT(C13,"# ##0")))*5,"",TEXT(C12,"# ##0"))) | D46: =IF(ISBLANK(D12),"",IF(D12/38300*492.8<(LEN(TEXT(D12,"# ##0"))+LEN(TEXT(D13,"# ##0")))*5,"",TEXT(D12,"# ##0"))) | E46: =IF(ISBLANK(E12),"",IF(E12/38300*492.8<(LEN(TEXT(E12,"# ##0"))+LEN(TEXT(E13,"# ##0")))*5,"",TEXT(E12,"# ##0"))) -> 8 856 | F46: =IF(ISBLANK(F12),"",IF(F12/38300*492.8<(LEN(TEXT(F12,"# ##0"))+LEN(TEXT(F13,"# ##0")))*5,"",TEXT(F12,"# ##0"))) | G46: =IF(ISBLANK(G12),"",IF(G12/38300*492.8<(LEN(TEXT(G12,"# ##0"))+LEN(TEXT(G13,"# ##0")))*5,"",TEXT(G12,"# ##0"))) -> 10 271
B47: =IF(ISBLANK(B13),"",IF(B13/38300*492.8<(LEN(TEXT(B13,"# ##0")))*5,"",TEXT(B13,"# ##0"))) -> 29 382 | C47: =IF(ISBLANK(C13),"",IF(C13/38300*492.8<(LEN(TEXT(C13,"# ##0")))*5,"",TEXT(C13,"# ##0"))) -> 38 280 | D47: =IF(ISBLANK(D13),"",IF(D13/38300*492.8<(LEN(TEXT(D13,"# ##0")))*5,"",TEXT(D13,"# ##0"))) -> 3 116 | E47: =IF(ISBLANK(E13),"",IF(E13/38300*492.8<(LEN(TEXT(E13,"# ##0")))*5,"",TEXT(E13,"# ##0"))) -> 70 778 | F47: =IF(ISBLANK(F13),"",IF(F13/38300*492.8<(LEN(TEXT(F13,"# ##0")))*5,"",TEXT(F13,"# ##0"))) -> 10 881 | G47: =IF(ISBLANK(G13),"",IF(G13/38300*492.8<(LEN(TEXT(G13,"# ##0")))*5,"",TEXT(G13,"# ##0"))) -> 81 659

Sheet C03A
A1: Entity | B1: The Progressive Corporation
A2: Measure | B2: Net premiums written
A3: Unit | B3: $m
A4: Period | B4: 2026
A5: Reference | B5: PY
A6: Message | B6: Net premiums written are running +2.5% to +9.6% above prior year through Jul; on that pace the year closes +4,753 $m (+5.7%) above 2025
A7: Subject | B7: =B2&" in "&B3 -> Net premiums written in $m
A9: var_rel caption | B9: ="Δ"&$B$5&"%" -> ΔPY%
A10: var_abs caption | B10: ="Δ"&$B$5&" "&$B$3 -> ΔPY $m
A12: Period | B12: Scenario | C12: PY | D12: Measure | E12: ΔPY | F12: ΔPY% | G12: Measure AC | H12: Measure FC | I12: ΔPY up | J12: ΔPY down | K12: ΔPY% up | L12: ΔPY% down | M12: up length | N12: down length | O12: span unit | P12: span rel | Q12: ref scaled | R12: measure scaled | S12: measure text | T12: var_abs scaled | U12: var_abs text | V12: abs_up scaled | W12: abs_dn scaled | X12: rel_up scaled | Y12: rel_up text | Z12: rel_dn scaled | AA12: rel_dn text | AB12: rel_up_len scaled | AC12: rel_dn_len scaled
A13: Jan | B13: AC | C13: 6481 | D13: 6735 | E13: =D13-C13 -> 254 | F13: =IF(C13<=0,NA(),(D13-C13)/C13*100) -> 3.9191483 | G13: =IF($B13="AC",$D13,NA()) -> 6735 | H13: =IF($B13="AC",NA(),$D13) -> #N/A | I13: =IF($E13>0,$E13,NA()) -> 254 | J13: =IF($E13<0,$E13,NA()) -> #N/A | K13: =IF($F13>0,$F13,NA()) -> 3.9191483 | L13: =IF($F13<0,$F13,NA()) -> #N/A | M13: =IF($F13>0,$F13,0) -> 3.9191483 | N13: =IF($F13<0,-$F13,0) -> 0 | O13: =MAX(_xlfn.AGGREGATE(4,6,C13:C24,D13:D24,E13:E24,I13:I24,J13:J24),-_xlfn.AGGREGATE(5,6,C13:C24,D13:D24,E13:E24,I13:I24,J13:J24),0.000000001) -> 9911 | P13: =MAX(_xlfn.AGGREGATE(4,6,K13:K24,L13:L24,M13:M24,N13:N24),-_xlfn.AGGREGATE(5,6,K13:K24,L13:L24,M13:M24,N13:N24),0.000000001) -> 9.6228293 | Q13: =C13/$O$13 -> 0.65391989 | R13: =D13/$O$13 -> 0.67954798 | S13: =IF(ISNA(D13),"",TEXT(D13,"0")) -> 6735 | T13: =E13/$O$13 -> 0.02562809 | U13: =IF(ISNA(E13),"",TEXT(E13,"+0;-0")) -> +254 | V13: =I13/$O$13 -> 0.02562809 | W13: =J13/$O$13 -> #N/A | X13: =K13/$P$13 -> 0.40727609 | Y13: =IF(ISNA(K13),"",TEXT(K13,"+0.0;-0.0")) -> +3.9 | Z13: =L13/$P$13 -> #N/A | AA13: =IF(ISNA(L13),"",TEXT(L13,"+0.0;-0.0")) | AB13: =M13/$P$13 -> 0.40727609 | AC13: =N13/$P$13 -> 0
A14: Feb | B14: AC | C14: 6684 | D14: 6995 | E14: =D14-C14 -> 311 | F14: =IF(C14<=0,NA(),(D14-C14)/C14*100) -> 4.6529025 | G14: =IF($B14="AC",$D14,NA()) -> 6995 | H14: =IF($B14="AC",NA(),$D14) -> #N/A | I14: =IF($E14>0,$E14,NA()) -> 311 | J14: =IF($E14<0,$E14,NA()) -> #N/A | K14: =IF($F14>0,$F14,NA()) -> 4.6529025 | L14: =IF($F14<0,$F14,NA()) -> #N/A | M14: =IF($F14>0,$F14,0) -> 4.6529025 | N14: =IF($F14<0,-$F14,0) -> 0 | Q14: =C14/$O$13 -> 0.67440218 | R14: =D14/$O$13 -> 0.70578145 | S14: =IF(ISNA(D14),"",TEXT(D14,"0")) -> 6995 | T14: =E14/$O$13 -> 0.031379276 | U14: =IF(ISNA(E14),"",TEXT(E14,"+0;-0")) -> +311 | V14: =I14/$O$13 -> 0.031379276 | W14: =J14/$O$13 -> #N/A | X14: =K14/$P$13 -> 0.48352748 | Y14: =IF(ISNA(K14),"",TEXT(K14,"+0.0;-0.0")) -> +4.7 | Z14: =L14/$P$13 -> #N/A | AA14: =IF(ISNA(L14),"",TEXT(L14,"+0.0;-0.0")) | AB14: =M14/$P$13 -> 0.48352748 | AC14: =N14/$P$13 -> 0
A15: Mar | B15: AC | C15: 9041 | D15: 9911 | E15: =D15-C15 -> 870 | F15: =IF(C15<=0,NA(),(D15-C15)/C15*100) -> 9.6228293 | G15: =IF($B15="AC",$D15,NA()) -> 9911 | H15: =IF($B15="AC",NA(),$D15) -> #N/A | I15: =IF($E15>0,$E15,NA()) -> 870 | J15: =IF($E15<0,$E15,NA()) -> #N/A | K15: =IF($F15>0,$F15,NA()) -> 9.6228293 | L15: =IF($F15<0,$F15,NA()) -> #N/A | M15: =IF($F15>0,$F15,0) -> 9.6228293 | N15: =IF($F15<0,-$F15,0) -> 0 | Q15: =C15/$O$13 -> 0.91221875 | R15: =D15/$O$13 -> 1 | S15: =IF(ISNA(D15),"",TEXT(D15,"0")) -> 9911 | T15: =E15/$O$13 -> 0.087781253 | U15: =IF(ISNA(E15),"",TEXT(E15,"+0;-0")) -> +870 | V15: =I15/$O$13 -> 0.087781253 | W15: =J15/$O$13 -> #N/A | X15: =K15/$P$13 -> 1 | Y15: =IF(ISNA(K15),"",TEXT(K15,"+0.0;-0.0")) -> +9.6 | Z15: =L15/$P$13 -> #N/A | AA15: =IF(ISNA(L15),"",TEXT(L15,"+0.0;-0.0")) | AB15: =M15/$P$13 -> 1 | AC15: =N15/$P$13 -> 0
A16: Apr | B16: AC | C16: 6837 | D16: 7278 | E16: =D16-C16 -> 441 | F16: =IF(C16<=0,NA(),(D16-C16)/C16*100) -> 6.4501975 | G16: =IF($B16="AC",$D16,NA()) -> 7278 | H16: =IF($B16="AC",NA(),$D16) -> #N/A | I16: =IF($E16>0,$E16,NA()) -> 441 | J16: =IF($E16<0,$E16,NA()) -> #N/A | K16: =IF($F16>0,$F16,NA()) -> 6.4501975 | L16: =IF($F16<0,$F16,NA()) -> #N/A | M16: =IF($F16>0,$F16,0) -> 6.4501975 | N16: =IF($F16<0,-$F16,0) -> 0 | Q16: =C16/$O$13 -> 0.68983957 | R16: =D16/$O$13 -> 0.73433559 | S16: =IF(ISNA(D16),"",TEXT(D16,"0")) -> 7278 | T16: =E16/$O$13 -> 0.044496015 | U16: =IF(ISNA(E16),"",TEXT(E16,"+0;-0")) -> +441 | V16: =I16/$O$13 -> 0.044496015 | W16: =J16/$O$13 -> #N/A | X16: =K16/$P$13 -> 0.67030155 | Y16: =IF(ISNA(K16),"",TEXT(K16,"+0.0;-0.0")) -> +6.5 | Z16: =L16/$P$13 -> #N/A | AA16: =IF(ISNA(L16),"",TEXT(L16,"+0.0;-0.0")) | AB16: =M16/$P$13 -> 0.67030155 | AC16: =N16/$P$13 -> 0
A17: May | B17: AC | C17: 6634 | D17: 7027 | E17: =D17-C17 -> 393 | F17: =IF(C17<=0,NA(),(D17-C17)/C17*100) -> 5.9240277 | G17: =IF($B17="AC",$D17,NA()) -> 7027 | H17: =IF($B17="AC",NA(),$D17) -> #N/A | I17: =IF($E17>0,$E17,NA()) -> 393 | J17: =IF($E17<0,$E17,NA()) -> #N/A | K17: =IF($F17>0,$F17,NA()) -> 5.9240277 | L17: =IF($F17<0,$F17,NA()) -> #N/A | M17: =IF($F17>0,$F17,0) -> 5.9240277 | N17: =IF($F17<0,-$F17,0) -> 0 | Q17: =C17/$O$13 -> 0.66935728 | R17: =D17/$O$13 -> 0.70901019 | S17: =IF(ISNA(D17),"",TEXT(D17,"0")) -> 7027 | T17: =E17/$O$13 -> 0.039652911 | U17: =IF(ISNA(E17),"",TEXT(E17,"+0;-0")) -> +393 | V17: =I17/$O$13 -> 0.039652911 | W17: =J17/$O$13 -> #N/A | X17: =K17/$P$13 -> 0.61562224 | Y17: =IF(ISNA(K17),"",TEXT(K17,"+0.0;-0.0")) -> +5.9 | Z17: =L17/$P$13 -> #N/A | AA17: =IF(ISNA(L17),"",TEXT(L17,"+0.0;-0.0")) | AB17: =M17/$P$13 -> 0.61562224 | AC17: =N17/$P$13 -> 0
A18: Jun | B18: AC | C18: 6605 | D18: 6772 | E18: =D18-C18 -> 167 | F18: =IF(C18<=0,NA(),(D18-C18)/C18*100) -> 2.5283876 | G18: =IF($B18="AC",$D18,NA()) -> 6772 | H18: =IF($B18="AC",NA(),$D18) -> #N/A | I18: =IF($E18>0,$E18,NA()) -> 167 | J18: =IF($E18<0,$E18,NA()) -> #N/A | K18: =IF($F18>0,$F18,NA()) -> 2.5283876 | L18: =IF($F18<0,$F18,NA()) -> #N/A | M18: =IF($F18>0,$F18,0) -> 2.5283876 | N18: =IF($F18<0,-$F18,0) -> 0 | Q18: =C18/$O$13 -> 0.66643124 | R18: =D18/$O$13 -> 0.6832812 | S18: =IF(ISNA(D18),"",TEXT(D18,"0")) -> 6772 | T18: =E18/$O$13 -> 0.016849965 | U18: =IF(ISNA(E18),"",TEXT(E18,"+0;-0")) -> +167 | V18: =I18/$O$13 -> 0.016849965 | W18: =J18/$O$13 -> #N/A | X18: =K18/$P$13 -> 0.26274888 | Y18: =IF(ISNA(K18),"",TEXT(K18,"+0.0;-0.0")) -> +2.5 | Z18: =L18/$P$13 -> #N/A | AA18: =IF(ISNA(L18),"",TEXT(L18,"+0.0;-0.0")) | AB18: =M18/$P$13 -> 0.26274888 | AC18: =N18/$P$13 -> 0
A19: Jul | B19: AC | C19: 7057 | D19: 7441 | E19: =D19-C19 -> 384 | F19: =IF(C19<=0,NA(),(D19-C19)/C19*100) -> 5.4414057 | G19: =IF($B19="AC",$D19,NA()) -> 7441 | H19: =IF($B19="AC",NA(),$D19) -> #N/A | I19: =IF($E19>0,$E19,NA()) -> 384 | J19: =IF($E19<0,$E19,NA()) -> #N/A | K19: =IF($F19>0,$F19,NA()) -> 5.4414057 | L19: =IF($F19<0,$F19,NA()) -> #N/A | M19: =IF($F19>0,$F19,0) -> 5.4414057 | N19: =IF($F19<0,-$F19,0) -> 0 | Q19: =C19/$O$13 -> 0.71203713 | R19: =D19/$O$13 -> 0.75078196 | S19: =IF(ISNA(D19),"",TEXT(D19,"0")) -> 7441 | T19: =E19/$O$13 -> 0.038744829 | U19: =IF(ISNA(E19),"",TEXT(E19,"+0;-0")) -> +384 | V19: =I19/$O$13 -> 0.038744829 | W19: =J19/$O$13 -> #N/A | X19: =K19/$P$13 -> 0.56546838 | Y19: =IF(ISNA(K19),"",TEXT(K19,"+0.0;-0.0")) -> +5.4 | Z19: =L19/$P$13 -> #N/A | AA19: =IF(ISNA(L19),"",TEXT(L19,"+0.0;-0.0")) | AB19: =M19/$P$13 -> 0.56546838 | AC19: =N19/$P$13 -> 0
A20: Aug | B20: FC | C20: 7199 | D20: 7610 | E20: =D20-C20 -> 411 | F20: =IF(C20<=0,NA(),(D20-C20)/C20*100) -> 5.7091263 | G20: =IF($B20="AC",$D20,NA()) -> #N/A | H20: =IF($B20="AC",NA(),$D20) -> 7610 | I20: =IF($E20>0,$E20,NA()) -> 411 | J20: =IF($E20<0,$E20,NA()) -> #N/A | K20: =IF($F20>0,$F20,NA()) -> 5.7091263 | L20: =IF($F20<0,$F20,NA()) -> #N/A | M20: =IF($F20>0,$F20,0) -> 5.7091263 | N20: =IF($F20<0,-$F20,0) -> 0 | Q20: =C20/$O$13 -> 0.72636465 | R20: =D20/$O$13 -> 0.76783372 | S20: =IF(ISNA(D20),"",TEXT(D20,"0")) -> 7610 | T20: =E20/$O$13 -> 0.041469075 | U20: =IF(ISNA(E20),"",TEXT(E20,"+0;-0")) -> +411 | V20: =I20/$O$13 -> 0.041469075 | W20: =J20/$O$13 -> #N/A | X20: =K20/$P$13 -> 0.59328978 | Y20: =IF(ISNA(K20),"",TEXT(K20,"+0.0;-0.0")) -> +5.7 | Z20: =L20/$P$13 -> #N/A | AA20: =IF(ISNA(L20),"",TEXT(L20,"+0.0;-0.0")) | AB20: =M20/$P$13 -> 0.59328978 | AC20: =N20/$P$13 -> 0
A21: Sep | B21: FC | C21: 7128 | D21: 7535 | E21: =D21-C21 -> 407 | F21: =IF(C21<=0,NA(),(D21-C21)/C21*100) -> 5.7098765 | G21: =IF($B21="AC",$D21,NA()) -> #N/A | H21: =IF($B21="AC",NA(),$D21) -> 7535 | I21: =IF($E21>0,$E21,NA()) -> 407 | J21: =IF($E21<0,$E21,NA()) -> #N/A | K21: =IF($F21>0,$F21,NA()) -> 5.7098765 | L21: =IF($F21<0,$F21,NA()) -> #N/A | M21: =IF($F21>0,$F21,0) -> 5.7098765 | N21: =IF($F21<0,-$F21,0) -> 0 | Q21: =C21/$O$13 -> 0.71920089 | R21: =D21/$O$13 -> 0.76026637 | S21: =IF(ISNA(D21),"",TEXT(D21,"0")) -> 7535 | T21: =E21/$O$13 -> 0.041065483 | U21: =IF(ISNA(E21),"",TEXT(E21,"+0;-0")) -> +407 | V21: =I21/$O$13 -> 0.041065483 | W21: =J21/$O$13 -> #N/A | X21: =K21/$P$13 -> 0.59336775 | Y21: =IF(ISNA(K21),"",TEXT(K21,"+0.0;-0.0")) -> +5.7 | Z21: =L21/$P$13 -> #N/A | AA21: =IF(ISNA(L21),"",TEXT(L21,"+0.0;-0.0")) | AB21: =M21/$P$13 -> 0.59336775 | AC21: =N21/$P$13 -> 0
A22: Oct | B22: FC | C22: 7002 | D22: 7402 | E22: =D22-C22 -> 400 | F22: =IF(C22<=0,NA(),(D22-C22)/C22*100) -> 5.7126535 | G22: =IF($B22="AC",$D22,NA()) -> #N/A | H22: =IF($B22="AC",NA(),$D22) -> 7402 | I22: =IF($E22>0,$E22,NA()) -> 400 | J22: =IF($E22<0,$E22,NA()) -> #N/A | K22: =IF($F22>0,$F22,NA()) -> 5.7126535 | L22: =IF($F22<0,$F22,NA()) -> #N/A | M22: =IF($F22>0,$F22,0) -> 5.7126535 | N22: =IF($F22<0,-$F22,0) -> 0 | Q22: =C22/$O$13 -> 0.70648774 | R22: =D22/$O$13 -> 0.74684694 | S22: =IF(ISNA(D22),"",TEXT(D22,"0")) -> 7402 | T22: =E22/$O$13 -> 0.040359197 | U22: =IF(ISNA(E22),"",TEXT(E22,"+0;-0")) -> +400 | V22: =I22/$O$13 -> 0.040359197 | W22: =J22/$O$13 -> #N/A | X22: =K22/$P$13 -> 0.59365633 | Y22: =IF(ISNA(K22),"",TEXT(K22,"+0.0;-0.0")) -> +5.7 | Z22: =L22/$P$13 -> #N/A | AA22: =IF(ISNA(L22),"",TEXT(L22,"+0.0;-0.0")) | AB22: =M22/$P$13 -> 0.59365633 | AC22: =N22/$P$13 -> 0
A23: Nov | B23: FC | C23: 6193 | D23: 6547 | E23: =D23-C23 -> 354 | F23: =IF(C23<=0,NA(),(D23-C23)/C23*100) -> 5.7161311 | G23: =IF($B23="AC",$D23,NA()) -> #N/A | H23: =IF($B23="AC",NA(),$D23) -> 6547 | I23: =IF($E23>0,$E23,NA()) -> 354 | J23: =IF($E23<0,$E23,NA()) -> #N/A | K23: =IF($F23>0,$F23,NA()) -> 5.7161311 | L23: =IF($F23<0,$F23,NA()) -> #N/A | M23: =IF($F23>0,$F23,0) -> 5.7161311 | N23: =IF($F23<0,-$F23,0) -> 0 | Q23: =C23/$O$13 -> 0.62486127 | R23: =D23/$O$13 -> 0.66057915 | S23: =IF(ISNA(D23),"",TEXT(D23,"0")) -> 6547 | T23: =E23/$O$13 -> 0.035717889 | U23: =IF(ISNA(E23),"",TEXT(E23,"+0;-0")) -> +354 | V23: =I23/$O$13 -> 0.035717889 | W23: =J23/$O$13 -> #N/A | X23: =K23/$P$13 -> 0.59401772 | Y23: =IF(ISNA(K23),"",TEXT(K23,"+0.0;-0.0")) -> +5.7 | Z23: =L23/$P$13 -> #N/A | AA23: =IF(ISNA(L23),"",TEXT(L23,"+0.0;-0.0")) | AB23: =M23/$P$13 -> 0.59401772 | AC23: =N23/$P$13 -> 0
A24: Dec | B24: FC | C24: 6313 | D24: 6674 | E24: =D24-C24 -> 361 | F24: =IF(C24<=0,NA(),(D24-C24)/C24*100) -> 5.7183589 | G24: =IF($B24="AC",$D24,NA()) -> #N/A | H24: =IF($B24="AC",NA(),$D24) -> 6674 | I24: =IF($E24>0,$E24,NA()) -> 361 | J24: =IF($E24<0,$E24,NA()) -> #N/A | K24: =IF($F24>0,$F24,NA()) -> 5.7183589 | L24: =IF($F24<0,$F24,NA()) -> #N/A | M24: =IF($F24>0,$F24,0) -> 5.7183589 | N24: =IF($F24<0,-$F24,0) -> 0 | Q24: =C24/$O$13 -> 0.63696902 | R24: =D24/$O$13 -> 0.6733932 | S24: =IF(ISNA(D24),"",TEXT(D24,"0")) -> 6674 | T24: =E24/$O$13 -> 0.036424175 | U24: =IF(ISNA(E24),"",TEXT(E24,"+0;-0")) -> +361 | V24: =I24/$O$13 -> 0.036424175 | W24: =J24/$O$13 -> #N/A | X24: =K24/$P$13 -> 0.59424923 | Y24: =IF(ISNA(K24),"",TEXT(K24,"+0.0;-0.0")) -> +5.7 | Z24: =L24/$P$13 -> #N/A | AA24: =IF(ISNA(L24),"",TEXT(L24,"+0.0;-0.0")) | AB24: =M24/$P$13 -> 0.59424923 | AC24: =N24/$P$13 -> 0
A26: FC is not reported by the entity. Progressive publishes no forecast. Remaining months are prior-year months grown at the year-to-date pace through Jul (+5.7%). Replace these cells with your own figures and every chart on this sheet follows.

Sheet C04A
A1: Entity | B1: The Progressive Corporation
A2: Measure | B2: Underwriting result
A3: Unit | B3: $m
A4: Period | B4: 2023
A5: Reference | B5: PL
A6: Message | B6: 6 of 12 months beat the 96 combined ratio target in 2023; Dec by +670 $m and Mar missed it by 441 $m, a spread of 1,111 $m across the year
A7: Subject | B7: =B2&" in "&B3 -> Underwriting result in $m
A9: var_abs caption | B9: ="Δ"&$B$5&" "&$B$3 -> ΔPL $m
A10: var_rel caption | B10: ="Δ"&$B$5&"%" -> ΔPL%
A12: State | B12: Scenario | C12: Measure | D12: ΔPL | E12: PL | F12: ΔPL% | G12: ΔPL up | H12: ΔPL down | I12: ΔPL% up | J12: ΔPL% down | K12: up length | L12: down length | M12: span unit | N12: span rel | O12: ref scaled | P12: measure scaled | Q12: measure text | R12: var_abs scaled | S12: var_abs text | T12: abs_up scaled | U12: abs_dn scaled | V12: var_rel scaled | W12: var_rel text | X12: rel_up scaled | Y12: rel_dn scaled
A13: Dec | B13: AC | C13: 882 | D13: 670 | E13: =C13-D13 -> 212 | F13: =IF(E13<=0,NA(),D13/E13*100) -> 316.03774 | G13: =IF($D13>0,$D13,NA()) -> 670 | H13: =IF($D13<0,$D13,NA()) -> #N/A | I13: =IF($F13>0,$F13,NA()) -> 316.03774 | J13: =IF($F13<0,$F13,NA()) -> #N/A | K13: =IF($F13>0,$F13,0) -> 316.03774 | L13: =IF($F13<0,-$F13,0) -> 0 | M13: =MAX(_xlfn.AGGREGATE(4,6,E13:E31,C13:C31,D13:D31,G13:G31,H13:H31),-_xlfn.AGGREGATE(5,6,E13:E31,C13:C31,D13:D31,G13:G31,H13:H31),0.000000001) -> 882 | N13: =MAX(_xlfn.AGGREGATE(4,6,F13:F31,I13:I31,J13:J31),-_xlfn.AGGREGATE(5,6,F13:F31,I13:I31,J13:J31),0.000000001) -> 316.03774 | O13: =E13/$M$13 -> 0.24036281 | P13: =C13/$M$13 -> 1 | Q13: =IF(ISNA(C13),"",TEXT(C13,"0")) -> 882 | R13: =D13/$M$13 -> 0.75963719 | S13: =IF(ISNA(D13),"",TEXT(D13,"+0;-0")) -> +670 | T13: =G13/$M$13 -> 0.75963719 | U13: =H13/$M$13 -> #N/A | V13: =F13/$N$13 -> 1 | W13: =IF(ISNA(F13),"",TEXT(F13,"+0;-0")) -> +316 | X13: =I13/$N$13 -> 1 | Y13: =J13/$N$13 -> #N/A
A14: Nov | B14: AC | C14: 528 | D14: 325 | E14: =C14-D14 -> 203 | F14: =IF(E14<=0,NA(),D14/E14*100) -> 160.09852 | G14: =IF($D14>0,$D14,NA()) -> 325 | H14: =IF($D14<0,$D14,NA()) -> #N/A | I14: =IF($F14>0,$F14,NA()) -> 160.09852 | J14: =IF($F14<0,$F14,NA()) -> #N/A | K14: =IF($F14>0,$F14,0) -> 160.09852 | L14: =IF($F14<0,-$F14,0) -> 0 | O14: =E14/$M$13 -> 0.23015873 | P14: =C14/$M$13 -> 0.59863946 | Q14: =IF(ISNA(C14),"",TEXT(C14,"0")) -> 528 | R14: =D14/$M$13 -> 0.36848073 | S14: =IF(ISNA(D14),"",TEXT(D14,"+0;-0")) -> +325 | T14: =G14/$M$13 -> 0.36848073 | U14: =H14/$M$13 -> #N/A | V14: =F14/$N$13 -> 0.5065804 | W14: =IF(ISNA(F14),"",TEXT(F14,"+0;-0")) -> +160 | X14: =I14/$N$13 -> 0.5065804 | Y14: =J14/$N$13 -> #N/A
A15: Jul | B15: AC | C15: 531 | D15: 305 | E15: =C15-D15 -> 226 | F15: =IF(E15<=0,NA(),D15/E15*100) -> 134.95575 | G15: =IF($D15>0,$D15,NA()) -> 305 | H15: =IF($D15<0,$D15,NA()) -> #N/A | I15: =IF($F15>0,$F15,NA()) -> 134.95575 | J15: =IF($F15<0,$F15,NA()) -> #N/A | K15: =IF($F15>0,$F15,0) -> 134.95575 | L15: =IF($F15<0,-$F15,0) -> 0 | O15: =E15/$M$13 -> 0.25623583 | P15: =C15/$M$13 -> 0.60204082 | Q15: =IF(ISNA(C15),"",TEXT(C15,"0")) -> 531 | R15: =D15/$M$13 -> 0.34580499 | S15: =IF(ISNA(D15),"",TEXT(D15,"+0;-0")) -> +305 | T15: =G15/$M$13 -> 0.34580499 | U15: =H15/$M$13 -> #N/A | V15: =F15/$N$13 -> 0.42702417 | W15: =IF(ISNA(F15),"",TEXT(F15,"+0;-0")) -> +135 | X15: =I15/$N$13 -> 0.42702417 | Y15: =J15/$N$13 -> #N/A
A16: Sep | B16: AC | C16: 479 | D16: 293 | E16: =C16-D16 -> 186 | F16: =IF(E16<=0,NA(),D16/E16*100) -> 157.52688 | G16: =IF($D16>0,$D16,NA()) -> 293 | H16: =IF($D16<0,$D16,NA()) -> #N/A | I16: =IF($F16>0,$F16,NA()) -> 157.52688 | J16: =IF($F16<0,$F16,NA()) -> #N/A | K16: =IF($F16>0,$F16,0) -> 157.52688 | L16: =IF($F16<0,-$F16,0) -> 0 | O16: =E16/$M$13 -> 0.21088435 | P16: =C16/$M$13 -> 0.5430839 | Q16: =IF(ISNA(C16),"",TEXT(C16,"0")) -> 479 | R16: =D16/$M$13 -> 0.33219955 | S16: =IF(ISNA(D16),"",TEXT(D16,"+0;-0")) -> +293 | T16: =G16/$M$13 -> 0.33219955 | U16: =H16/$M$13 -> #N/A | V16: =F16/$N$13 -> 0.49844327 | W16: =IF(ISNA(F16),"",TEXT(F16,"+0;-0")) -> +158 | X16: =I16/$N$13 -> 0.49844327 | Y16: =J16/$N$13 -> #N/A
A17: Oct | B17: AC | C17: 323 | D17: 108 | E17: =C17-D17 -> 215 | F17: =IF(E17<=0,NA(),D17/E17*100) -> 50.232558 | G17: =IF($D17>0,$D17,NA()) -> 108 | H17: =IF($D17<0,$D17,NA()) -> #N/A | I17: =IF($F17>0,$F17,NA()) -> 50.232558 | J17: =IF($F17<0,$F17,NA()) -> #N/A | K17: =IF($F17>0,$F17,0) -> 50.232558 | L17: =IF($F17<0,-$F17,0) -> 0 | O17: =E17/$M$13 -> 0.24376417 | P17: =C17/$M$13 -> 0.36621315 | Q17: =IF(ISNA(C17),"",TEXT(C17,"0")) -> 323 | R17: =D17/$M$13 -> 0.12244898 | S17: =IF(ISNA(D17),"",TEXT(D17,"+0;-0")) -> +108 | T17: =G17/$M$13 -> 0.12244898 | U17: =H17/$M$13 -> #N/A | V17: =F17/$N$13 -> 0.15894481 | W17: =IF(ISNA(F17),"",TEXT(F17,"+0;-0")) -> +50 | X17: =I17/$N$13 -> 0.15894481 | Y17: =J17/$N$13 -> #N/A
A18: Feb | B18: AC | C18: 204 | D18: 37 | E18: =C18-D18 -> 167 | F18: =IF(E18<=0,NA(),D18/E18*100) -> 22.155689 | G18: =IF($D18>0,$D18,NA()) -> 37 | H18: =IF($D18<0,$D18,NA()) -> #N/A | I18: =IF($F18>0,$F18,NA()) -> 22.155689 | J18: =IF($F18<0,$F18,NA()) -> #N/A | K18: =IF($F18>0,$F18,0) -> 22.155689 | L18: =IF($F18<0,-$F18,0) -> 0 | O18: =E18/$M$13 -> 0.1893424 | P18: =C18/$M$13 -> 0.23129252 | Q18: =IF(ISNA(C18),"",TEXT(C18,"0")) -> 204 | R18: =D18/$M$13 -> 0.041950113 | S18: =IF(ISNA(D18),"",TEXT(D18,"+0;-0")) -> +37 | T18: =G18/$M$13 -> 0.041950113 | U18: =H18/$M$13 -> #N/A | V18: =F18/$N$13 -> 0.070104567 | W18: =IF(ISNA(F18),"",TEXT(F18,"+0;-0")) -> +22 | X18: =I18/$N$13 -> 0.070104567 | Y18: =J18/$N$13 -> #N/A
A19: Jan | B19: AC | C19: 202 | D19: 0 | E19: =C19-D19 -> 202 | F19: =IF(E19<=0,NA(),D19/E19*100) -> 0 | G19: =IF($D19>0,$D19,NA()) -> #N/A | H19: =IF($D19<0,$D19,NA()) -> #N/A | I19: =IF($F19>0,$F19,NA()) -> #N/A | J19: =IF($F19<0,$F19,NA()) -> #N/A | K19: =IF($F19>0,$F19,0) -> 0 | L19: =IF($F19<0,-$F19,0) -> 0 | O19: =E19/$M$13 -> 0.22902494 | P19: =C19/$M$13 -> 0.22902494 | Q19: =IF(ISNA(C19),"",TEXT(C19,"0")) -> 202 | R19: =D19/$M$13 -> 0 | S19: =IF(ISNA(D19),"",TEXT(D19,"+0;-0")) -> +0 | T19: =G19/$M$13 -> #N/A | U19: =H19/$M$13 -> #N/A | V19: =F19/$N$13 -> 0 | W19: =IF(ISNA(F19),"",TEXT(F19,"+0;-0")) -> +0 | X19: =I19/$N$13 -> #N/A | Y19: =J19/$N$13 -> #N/A
A20: Aug | B20: AC | C20: 129 | D20: -55 | E20: =C20-D20 -> 184 | F20: =IF(E20<=0,NA(),D20/E20*100) -> -29.891304 | G20: =IF($D20>0,$D20,NA()) -> #N/A | H20: =IF($D20<0,$D20,NA()) -> -55 | I20: =IF($F20>0,$F20,NA()) -> #N/A | J20: =IF($F20<0,$F20,NA()) -> -29.891304 | K20: =IF($F20>0,$F20,0) -> 0 | L20: =IF($F20<0,-$F20,0) -> 29.891304 | O20: =E20/$M$13 -> 0.20861678 | P20: =C20/$M$13 -> 0.1462585 | Q20: =IF(ISNA(C20),"",TEXT(C20,"0")) -> 129 | R20: =D20/$M$13 -> -0.062358277 | S20: =IF(ISNA(D20),"",TEXT(D20,"+0;-0")) -> -55 | T20: =G20/$M$13 -> #N/A | U20: =H20/$M$13 -> -0.062358277 | V20: =F20/$N$13 -> -0.094581441 | W20: =IF(ISNA(F20),"",TEXT(F20,"+0;-0")) -> -30 | X20: =I20/$N$13 -> #N/A | Y20: =J20/$N$13 -> -0.094581441
A21: Apr | B21: AC | C21: 115 | D21: -103 | E21: =C21-D21 -> 218 | F21: =IF(E21<=0,NA(),D21/E21*100) -> -47.247706 | G21: =IF($D21>0,$D21,NA()) -> #N/A | H21: =IF($D21<0,$D21,NA()) -> -103 | I21: =IF($F21>0,$F21,NA()) -> #N/A | J21: =IF($F21<0,$F21,NA()) -> -47.247706 | K21: =IF($F21>0,$F21,0) -> 0 | L21: =IF($F21<0,-$F21,0) -> 47.247706 | O21: =E21/$M$13 -> 0.24716553 | P21: =C21/$M$13 -> 0.13038549 | Q21: =IF(ISNA(C21),"",TEXT(C21,"0")) -> 115 | R21: =D21/$M$13 -> -0.11678005 | S21: =IF(ISNA(D21),"",TEXT(D21,"+0;-0")) -> -103 | T21: =G21/$M$13 -> #N/A | U21: =H21/$M$13 -> -0.11678005 | V21: =F21/$N$13 -> -0.14950021 | W21: =IF(ISNA(F21),"",TEXT(F21,"+0;-0")) -> -47 | X21: =I21/$N$13 -> #N/A | Y21: =J21/$N$13 -> -0.14950021
A22: May | B22: AC | C22: 45 | D22: -135 | E22: =C22-D22 -> 180 | F22: =IF(E22<=0,NA(),D22/E22*100) -> -75 | G22: =IF($D22>0,$D22,NA()) -> #N/A | H22: =IF($D22<0,$D22,NA()) -> -135 | I22: =IF($F22>0,$F22,NA()) -> #N/A | J22: =IF($F22<0,$F22,NA()) -> -75 | K22: =IF($F22>0,$F22,0) -> 0 | L22: =IF($F22<0,-$F22,0) -> 75 | O22: =E22/$M$13 -> 0.20408163 | P22: =C22/$M$13 -> 0.051020408 | Q22: =IF(ISNA(C22),"",TEXT(C22,"0")) -> 45 | R22: =D22/$M$13 -> -0.15306122 | S22: =IF(ISNA(D22),"",TEXT(D22,"+0;-0")) -> -135 | T22: =G22/$M$13 -> #N/A | U22: =H22/$M$13 -> -0.15306122 | V22: =F22/$N$13 -> -0.23731343 | W22: =IF(ISNA(F22),"",TEXT(F22,"+0;-0")) -> -75 | X22: =I22/$N$13 -> #N/A | Y22: =J22/$N$13 -> -0.23731343
A23: Jun | B23: AC | C23: -221 | D23: -402 | E23: =C23-D23 -> 181 | F23: =IF(E23<=0,NA(),D23/E23*100) -> -222.09945 | G23: =IF($D23>0,$D23,NA()) -> #N/A | H23: =IF($D23<0,$D23,NA()) -> -402 | I23: =IF($F23>0,$F23,NA()) -> #N/A | J23: =IF($F23<0,$F23,NA()) -> -222.09945 | K23: =IF($F23>0,$F23,0) -> 0 | L23: =IF($F23<0,-$F23,0) -> 222.09945 | O23: =E23/$M$13 -> 0.20521542 | P23: =C23/$M$13 -> -0.25056689 | Q23: =IF(ISNA(C23),"",TEXT(C23,"0")) -> -221 | R23: =D23/$M$13 -> -0.45578231 | S23: =IF(ISNA(D23),"",TEXT(D23,"+0;-0")) -> -402 | T23: =G23/$M$13 -> #N/A | U23: =H23/$M$13 -> -0.45578231 | V23: =F23/$N$13 -> -0.70276243 | W23: =IF(ISNA(F23),"",TEXT(F23,"+0;-0")) -> -222 | X23: =I23/$N$13 -> #N/A | Y23: =J23/$N$13 -> -0.70276243
A24: Mar | B24: AC | C24: -268 | D24: -441 | E24: =C24-D24 -> 173 | F24: =IF(E24<=0,NA(),D24/E24*100) -> -254.91329 | G24: =IF($D24>0,$D24,NA()) -> #N/A | H24: =IF($D24<0,$D24,NA()) -> -441 | I24: =IF($F24>0,$F24,NA()) -> #N/A | J24: =IF($F24<0,$F24,NA()) -> -254.91329 | K24: =IF($F24>0,$F24,0) -> 0 | L24: =IF($F24<0,-$F24,0) -> 254.91329 | O24: =E24/$M$13 -> 0.19614512 | P24: =C24/$M$13 -> -0.30385488 | Q24: =IF(ISNA(C24),"",TEXT(C24,"0")) -> -268 | R24: =D24/$M$13 -> -0.5 | S24: =IF(ISNA(D24),"",TEXT(D24,"+0;-0")) -> -441 | T24: =G24/$M$13 -> #N/A | U24: =H24/$M$13 -> -0.5 | V24: =F24/$N$13 -> -0.80659132 | W24: =IF(ISNA(F24),"",TEXT(F24,"+0;-0")) -> -255 | X24: =I24/$N$13 -> #N/A | Y24: =J24/$N$13 -> -0.80659132
A26: PL is not reported by the entity. Progressive publishes no monthly plan. The target it does publish is a 96 combined ratio - a 4% underwriting margin - applied here to each month's earned premium. Replace these cells with your own figures and every chart on this sheet follows.

Sheet C05X
A1: Entity | B1: The Progressive Corporation
A2: Measure | B2: Underwriting result
A3: Unit | B3: $m
A4: Period | B4: 2026
A5: Reference | B5: PY
A6: Message | B6: The underwriting result is running +1,200 $m (+11.7%) ahead of 2025, with 7 of twelve months up and Sep contributing +985 on its own. Both years sit far above the 96 combined ratio target, drawn as the second opening column
A7: Subject | B7: =B2&" in "&B3 -> Underwriting result in $m
A9: var_rel caption | B9: ="Δ"&$B$5&"%" -> ΔPY%
A11: Period | B11: Scenario | C11: Kind | D11: AC/FC | E11: ΔPY | F11: PY | G11: ΔPY% | H11: PY bar | I11: PY bar | J11: AC bar | K11: FC bar | L11: level | M11: from | N11: base | O11: up AC | P11: down AC | Q11: up FC | R11: down FC | S11: ΔPY% up | T11: ΔPY% down | U11: up length | V11: down length | W11: span unit | X11: span rel | Y11: bar_py scaled | Z11: bar_py text | AA11: bar_pl scaled | AB11: bar_pl text | AC11: bar_ac scaled | AD11: bar_ac text | AE11: bar_fc scaled | AF11: bar_fc text | AG11: wf_base scaled | AH11: wf_up_ac scaled | AI11: wf_up_ac text | AJ11: wf_dn_ac scaled | AK11: wf_dn_ac text | AL11: wf_up_fc scaled | AM11: wf_up_fc text | AN11: wf_dn_fc scaled | AO11: wf_dn_fc text | AP11: rel_up scaled | AQ11: rel_up text | AR11: rel_dn scaled | AS11: rel_dn text | AT11: rel_up_len scaled | AU11: rel_dn_len scaled
A12: 2026 PL | B12: PL | C12: total | D12: =SUM(F14:F25) -> 10256 | F12: =0 -> 0 | G12: =NA() -> #N/A | H12: =NA() -> #N/A | I12: =D12 -> 10256 | J12: =NA() -> #N/A | K12: =NA() -> #N/A | L12: =0 -> 0 | M12: =L12 -> 0 | N12: =0 -> 0 | O12: =0 -> 0 | P12: =0 -> 0 | Q12: =0 -> 0 | R12: =0 -> 0 | S12: =NA() -> #N/A | T12: =NA() -> #N/A | U12: =0 -> 0 | V12: =0 -> 0 | W12: =MAX(_xlfn.AGGREGATE(4,6,H12:H28,I12:I28,J12:J28,K12:K28,N12:N28,O12:O28,P12:P28,Q12:Q28,R12:R28),-_xlfn.AGGREGATE(5,6,H12:H28,I12:I28,J12:J28,K12:K28,N12:N28,O12:O28,P12:P28,Q12:Q28,R12:R28),0.000000001) -> 11376 | X12: =MAX(_xlfn.AGGREGATE(4,6,S12:S28,T12:T28,U12:U28,V12:V28),-_xlfn.AGGREGATE(5,6,S12:S28,T12:T28,U12:U28,V12:V28),0.000000001) -> 3648.1481 | Y12: =H12/$W$12 -> #N/A | Z12: =IF(ISNA(H12),"",TEXT(H12,"#,##0")) | AA12: =I12/$W$12 -> 0.90154712 | AB12: =IF(ISNA(I12),"",TEXT(I12,"#,##0")) -> 10,256 | AC12: =J12/$W$12 -> #N/A | AD12: =IF(ISNA(J12),"",TEXT(J12,"#,##0")) | AE12: =K12/$W$12 -> #N/A | AF12: =IF(ISNA(K12),"",TEXT(K12,"#,##0")) | AG12: =N12/$W$12 -> 0 | AH12: =O12/$W$12 -> 0 | AI12: =IF(ISNA(O12),"",TEXT(O12,"+#,##0")) -> +0 | AJ12: =P12/$W$12 -> 0 | AK12: =IF(ISNA(P12),"",TEXT(P12,"""-""#,##0")) -> -0 | AL12: =Q12/$W$12 -> 0 | AM12: =IF(ISNA(Q12),"",TEXT(Q12,"+#,##0")) -> +0 | AN12: =R12/$W$12 -> 0 | AO12: =IF(ISNA(R12),"",TEXT(R12,"""-""#,##0")) -> -0 | AP12: =S12/$X$12 -> #N/A | AQ12: =IF(ISNA(S12),"",TEXT(S12,"+0.0;-0.0")) | AR12: =T12/$X$12 -> #N/A | AS12: =IF(ISNA(T12),"",TEXT(T12,"+0.0;-0.0")) | AT12: =U12/$X$12 -> 0 | AU12: =V12/$X$12 -> 0
A13: 2025 AC | B13: PY | C13: total | D13: 10256 | F13: =0 -> 0 | G13: =NA() -> #N/A | H13: =D13 -> 10256 | I13: =NA() -> #N/A | J13: =NA() -> #N/A | K13: =NA() -> #N/A | L13: =D13 -> 10256 | M13: =L13 -> 10256 | N13: =0 -> 0 | O13: =0 -> 0 | P13: =0 -> 0 | Q13: =0 -> 0 | R13: =0 -> 0 | S13: =NA() -> #N/A | T13: =NA() -> #N/A | U13: =0 -> 0 | V13: =0 -> 0 | Y13: =H13/$W$12 -> 0.90154712 | Z13: =IF(ISNA(H13),"",TEXT(H13,"#,##0")) -> 10,256 | AA13: =I13/$W$12 -> #N/A | AB13: =IF(ISNA(I13),"",TEXT(I13,"#,##0")) | AC13: =J13/$W$12 -> #N/A | AD13: =IF(ISNA(J13),"",TEXT(J13,"#,##0")) | AE13: =K13/$W$12 -> #N/A | AF13: =IF(ISNA(K13),"",TEXT(K13,"#,##0")) | AG13: =N13/$W$12 -> 0 | AH13: =O13/$W$12 -> 0 | AI13: =IF(ISNA(O13),"",TEXT(O13,"+#,##0")) -> +0 | AJ13: =P13/$W$12 -> 0 | AK13: =IF(ISNA(P13),"",TEXT(P13,"""-""#,##0")) -> -0 | AL13: =Q13/$W$12 -> 0 | AM13: =IF(ISNA(Q13),"",TEXT(Q13,"+#,##0")) -> +0 | AN13: =R13/$W$12 -> 0 | AO13: =IF(ISNA(R13),"",TEXT(R13,"""-""#,##0")) -> -0 | AP13: =S13/$X$12 -> #N/A | AQ13: =IF(ISNA(S13),"",TEXT(S13,"+0.0;-0.0")) | AR13: =T13/$X$12 -> #N/A | AS13: =IF(ISNA(T13),"",TEXT(T13,"+0.0;-0.0")) | AT13: =U13/$X$12 -> 0 | AU13: =V13/$X$12 -> 0
A14: Jan | B14: AC | C14: state | D14: 1080 | E14: 33 | F14: =D14-E14 -> 1047 | G14: =IF(F14=0,NA(),E14/F14*100) -> 3.1518625 | H14: =NA() -> #N/A | I14: =F14 -> 1047 | J14: =IF($B14="AC",D14,NA()) -> 1080 | K14: =IF($B14="FC",D14,NA()) -> #N/A | L14: =M14+E14 -> 10289 | M14: =L13 -> 10256 | N14: =MIN(M14,L14) -> 10256 | O14: =IF(AND($B14="AC",E14>0),E14,0) -> 33 | P14: =IF(AND($B14="AC",E14<0),-E14,0) -> 0 | Q14: =IF(AND($B14="FC",E14>0),E14,0) -> 0 | R14: =IF(AND($B14="FC",E14<0),-E14,0) -> 0 | S14: =IF(G14>0,G14,NA()) -> 3.1518625 | T14: =IF(G14<0,G14,NA()) -> #N/A | U14: =IF(G14>0,G14,0) -> 3.1518625 | V14: =IF(G14<0,-G14,0) -> 0 | Y14: =H14/$W$12 -> #N/A | Z14: =IF(ISNA(H14),"",TEXT(H14,"#,##0")) | AA14: =I14/$W$12 -> 0.092035865 | AB14: =IF(ISNA(I14),"",TEXT(I14,"#,##0")) -> 1,047 | AC14: =J14/$W$12 -> 0.094936709 | AD14: =IF(ISNA(J14),"",TEXT(J14,"#,##0")) -> 1,080 | AE14: =K14/$W$12 -> #N/A | AF14: =IF(ISNA(K14),"",TEXT(K14,"#,##0")) | AG14: =N14/$W$12 -> 0.90154712 | AH14: =O14/$W$12 -> 0.0029008439 | AI14: =IF(ISNA(O14),"",TEXT(O14,"+#,##0")) -> +33 | AJ14: =P14/$W$12 -> 0 | AK14: =IF(ISNA(P14),"",TEXT(P14,"""-""#,##0")) -> -0 | AL14: =Q14/$W$12 -> 0 | AM14: =IF(ISNA(Q14),"",TEXT(Q14,"+#,##0")) -> +0 | AN14: =R14/$W$12 -> 0 | AO14: =IF(ISNA(R14),"",TEXT(R14,"""-""#,##0")) -> -0 | AP14: =S14/$X$12 -> 0.0008639623 | AQ14: =IF(ISNA(S14),"",TEXT(S14,"+0.0;-0.0")) -> +3.2 | AR14: =T14/$X$12 -> #N/A | AS14: =IF(ISNA(T14),"",TEXT(T14,"+0.0;-0.0")) | AT14: =U14/$X$12 -> 0.0008639623 | AU14: =V14/$X$12 -> 0
A15: Feb | B15: AC | C15: state | D15: 934 | E15: -116 | F15: =D15-E15 -> 1050 | G15: =IF(F15=0,NA(),E15/F15*100) -> -11.047619 | H15: =NA() -> #N/A | I15: =F15 -> 1050 | J15: =IF($B15="AC",D15,NA()) -> 934 | K15: =IF($B15="FC",D15,NA()) -> #N/A | L15: =M15+E15 -> 10173 | M15: =L14 -> 10289 | N15: =MIN(M15,L15) -> 10173 | O15: =IF(AND($B15="AC",E15>0),E15,0) -> 0 | P15: =IF(AND($B15="AC",E15<0),-E15,0) -> 116 | Q15: =IF(AND($B15="FC",E15>0),E15,0) -> 0 | R15: =IF(AND($B15="FC",E15<0),-E15,0) -> 0 | S15: =IF(G15>0,G15,NA()) -> #N/A | T15: =IF(G15<0,G15,NA()) -> -11.047619 | U15: =IF(G15>0,G15,0) -> 0 | V15: =IF(G15<0,-G15,0) -> 11.047619 | Y15: =H15/$W$12 -> #N/A | Z15: =IF(ISNA(H15),"",TEXT(H15,"#,##0")) | AA15: =I15/$W$12 -> 0.092299578 | AB15: =IF(ISNA(I15),"",TEXT(I15,"#,##0")) -> 1,050 | AC15: =J15/$W$12 -> 0.082102672 | AD15: =IF(ISNA(J15),"",TEXT(J15,"#,##0")) -> 934 | AE15: =K15/$W$12 -> #N/A | AF15: =IF(ISNA(K15),"",TEXT(K15,"#,##0")) | AG15: =N15/$W$12 -> 0.89425105 | AH15: =O15/$W$12 -> 0 | AI15: =IF(ISNA(O15),"",TEXT(O15,"+#,##0")) -> +0 | AJ15: =P15/$W$12 -> 0.010196906 | AK15: =IF(ISNA(P15),"",TEXT(P15,"""-""#,##0")) -> -116 | AL15: =Q15/$W$12 -> 0 | AM15: =IF(ISNA(Q15),"",TEXT(Q15,"+#,##0")) -> +0 | AN15: =R15/$W$12 -> 0 | AO15: =IF(ISNA(R15),"",TEXT(R15,"""-""#,##0")) -> -0 | AP15: =S15/$X$12 -> #N/A | AQ15: =IF(ISNA(S15),"",TEXT(S15,"+0.0;-0.0")) | AR15: =T15/$X$12 -> -0.0030282814 | AS15: =IF(ISNA(T15),"",TEXT(T15,"+0.0;-0.0")) -> -11.0 | AT15: =U15/$X$12 -> 0 | AU15: =V15/$X$12 -> 0.0030282814
A16: Mar | B16: AC | C16: state | D16: 842 | E16: 224 | F16: =D16-E16 -> 618 | G16: =IF(F16=0,NA(),E16/F16*100) -> 36.245955 | H16: =NA() -> #N/A | I16: =F16 -> 618 | J16: =IF($B16="AC",D16,NA()) -> 842 | K16: =IF($B16="FC",D16,NA()) -> #N/A | L16: =M16+E16 -> 10397 | M16: =L15 -> 10173 | N16: =MIN(M16,L16) -> 10173 | O16: =IF(AND($B16="AC",E16>0),E16,0) -> 224 | P16: =IF(AND($B16="AC",E16<0),-E16,0) -> 0 | Q16: =IF(AND($B16="FC",E16>0),E16,0) -> 0 | R16: =IF(AND($B16="FC",E16<0),-E16,0) -> 0 | S16: =IF(G16>0,G16,NA()) -> 36.245955 | T16: =IF(G16<0,G16,NA()) -> #N/A | U16: =IF(G16>0,G16,0) -> 36.245955 | V16: =IF(G16<0,-G16,0) -> 0 | Y16: =H16/$W$12 -> #N/A | Z16: =IF(ISNA(H16),"",TEXT(H16,"#,##0")) | AA16: =I16/$W$12 -> 0.054324895 | AB16: =IF(ISNA(I16),"",TEXT(I16,"#,##0")) -> 618 | AC16: =J16/$W$12 -> 0.074015471 | AD16: =IF(ISNA(J16),"",TEXT(J16,"#,##0")) -> 842 | AE16: =K16/$W$12 -> #N/A | AF16: =IF(ISNA(K16),"",TEXT(K16,"#,##0")) | AG16: =N16/$W$12 -> 0.89425105 | AH16: =O16/$W$12 -> 0.019690577 | AI16: =IF(ISNA(O16),"",TEXT(O16,"+#,##0")) -> +224 | AJ16: =P16/$W$12 -> 0 | AK16: =IF(ISNA(P16),"",TEXT(P16,"""-""#,##0")) -> -0 | AL16: =Q16/$W$12 -> 0 | AM16: =IF(ISNA(Q16),"",TEXT(Q16,"+#,##0")) -> +0 | AN16: =R16/$W$12 -> 0 | AO16: =IF(ISNA(R16),"",TEXT(R16,"""-""#,##0")) -> -0 | AP16: =S16/$X$12 -> 0.0099354394 | AQ16: =IF(ISNA(S16),"",TEXT(S16,"+0.0;-0.0")) -> +36.2 | AR16: =T16/$X$12 -> #N/A | AS16: =IF(ISNA(T16),"",TEXT(T16,"+0.0;-0.0")) | AT16: =U16/$X$12 -> 0.0099354394 | AU16: =V16/$X$12 -> 0
A17: Apr | B17: AC | C17: state | D17: 697 | E17: -306 | F17: =D17-E17 -> 1003 | G17: =IF(F17=0,NA(),E17/F17*100) -> -30.508475 | H17: =NA() -> #N/A | I17: =F17 -> 1003 | J17: =IF($B17="AC",D17,NA()) -> 697 | K17: =IF($B17="FC",D17,NA()) -> #N/A | L17: =M17+E17 -> 10091 | M17: =L16 -> 10397 | N17: =MIN(M17,L17) -> 10091 | O17: =IF(AND($B17="AC",E17>0),E17,0) -> 0 | P17: =IF(AND($B17="AC",E17<0),-E17,0) -> 306 | Q17: =IF(AND($B17="FC",E17>0),E17,0) -> 0 | R17: =IF(AND($B17="FC",E17<0),-E17,0) -> 0 | S17: =IF(G17>0,G17,NA()) -> #N/A | T17: =IF(G17<0,G17,NA()) -> -30.508475 | U17: =IF(G17>0,G17,0) -> 0 | V17: =IF(G17<0,-G17,0) -> 30.508475 | Y17: =H17/$W$12 -> #N/A | Z17: =IF(ISNA(H17),"",TEXT(H17,"#,##0")) | AA17: =I17/$W$12 -> 0.088168073 | AB17: =IF(ISNA(I17),"",TEXT(I17,"#,##0")) -> 1,003 | AC17: =J17/$W$12 -> 0.061269339 | AD17: =IF(ISNA(J17),"",TEXT(J17,"#,##0")) -> 697 | AE17: =K17/$W$12 -> #N/A | AF17: =IF(ISNA(K17),"",TEXT(K17,"#,##0")) | AG17: =N17/$W$12 -> 0.8870429 | AH17: =O17/$W$12 -> 0 | AI17: =IF(ISNA(O17),"",TEXT(O17,"+#,##0")) -> +0 | AJ17: =P17/$W$12 -> 0.026898734 | AK17: =IF(ISNA(P17),"",TEXT(P17,"""-""#,##0")) -> -306 | AL17: =Q17/$W$12 -> 0 | AM17: =IF(ISNA(Q17),"",TEXT(Q17,"+#,##0")) -> +0 | AN17: =R17/$W$12 -> 0 | AO17: =IF(ISNA(R17),"",TEXT(R17,"""-""#,##0")) -> -0 | AP17: =S17/$X$12 -> #N/A | AQ17: =IF(ISNA(S17),"",TEXT(S17,"+0.0;-0.0")) | AR17: =T17/$X$12 -> -0.0083627291 | AS17: =IF(ISNA(T17),"",TEXT(T17,"+0.0;-0.0")) -> -30.5 | AT17: =U17/$X$12 -> 0 | AU17: =V17/$X$12 -> 0.0083627291
A18: May | B18: AC | C18: state | D18: 1318 | E18: 438 | F18: =D18-E18 -> 880 | G18: =IF(F18=0,NA(),E18/F18*100) -> 49.772727 | H18: =NA() -> #N/A | I18: =F18 -> 880 | J18: =IF($B18="AC",D18,NA()) -> 1318 | K18: =IF($B18="FC",D18,NA()) -> #N/A | L18: =M18+E18 -> 10529 | M18: =L17 -> 10091 | N18: =MIN(M18,L18) -> 10091 | O18: =IF(AND($B18="AC",E18>0),E18,0) -> 438 | P18: =IF(AND($B18="AC",E18<0),-E18,0) -> 0 | Q18: =IF(AND($B18="FC",E18>0),E18,0) -> 0 | R18: =IF(AND($B18="FC",E18<0),-E18,0) -> 0 | S18: =IF(G18>0,G18,NA()) -> 49.772727 | T18: =IF(G18<0,G18,NA()) -> #N/A | U18: =IF(G18>0,G18,0) -> 49.772727 | V18: =IF(G18<0,-G18,0) -> 0 | Y18: =H18/$W$12 -> #N/A | Z18: =IF(ISNA(H18),"",TEXT(H18,"#,##0")) | AA18: =I18/$W$12 -> 0.077355837 | AB18: =IF(ISNA(I18),"",TEXT(I18,"#,##0")) -> 880 | AC18: =J18/$W$12 -> 0.11585795 | AD18: =IF(ISNA(J18),"",TEXT(J18,"#,##0")) -> 1,318 | AE18: =K18/$W$12 -> #N/A | AF18: =IF(ISNA(K18),"",TEXT(K18,"#,##0")) | AG18: =N18/$W$12 -> 0.8870429 | AH18: =O18/$W$12 -> 0.03850211 | AI18: =IF(ISNA(O18),"",TEXT(O18,"+#,##0")) -> +438 | AJ18: =P18/$W$12 -> 0 | AK18: =IF(ISNA(P18),"",TEXT(P18,"""-""#,##0")) -> -0 | AL18: =Q18/$W$12 -> 0 | AM18: =IF(ISNA(Q18),"",TEXT(Q18,"+#,##0")) -> +0 | AN18: =R18/$W$12 -> 0 | AO18: =IF(ISNA(R18),"",TEXT(R18,"""-""#,##0")) -> -0 | AP18: =S18/$X$12 -> 0.013643286 | AQ18: =IF(ISNA(S18),"",TEXT(S18,"+0.0;-0.0")) -> +49.8 | AR18: =T18/$X$12 -> #N/A | AS18: =IF(ISNA(T18),"",TEXT(T18,"+0.0;-0.0")) | AT18: =U18/$X$12 -> 0.013643286 | AU18: =V18/$X$12 -> 0
A19: Jun | B19: AC | C19: state | D19: 710 | E19: -222 | F19: =D19-E19 -> 932 | G19: =IF(F19=0,NA(),E19/F19*100) -> -23.819742 | H19: =NA() -> #N/A | I19: =F19 -> 932 | J19: =IF($B19="AC",D19,NA()) -> 710 | K19: =IF($B19="FC",D19,NA()) -> #N/A | L19: =M19+E19 -> 10307 | M19: =L18 -> 10529 | N19: =MIN(M19,L19) -> 10307 | O19: =IF(AND($B19="AC",E19>0),E19,0) -> 0 | P19: =IF(AND($B19="AC",E19<0),-E19,0) -> 222 | Q19: =IF(AND($B19="FC",E19>0),E19,0) -> 0 | R19: =IF(AND($B19="FC",E19<0),-E19,0) -> 0 | S19: =IF(G19>0,G19,NA()) -> #N/A | T19: =IF(G19<0,G19,NA()) -> -23.819742 | U19: =IF(G19>0,G19,0) -> 0 | V19: =IF(G19<0,-G19,0) -> 23.819742 | Y19: =H19/$W$12 -> #N/A | Z19: =IF(ISNA(H19),"",TEXT(H19,"#,##0")) | AA19: =I19/$W$12 -> 0.081926864 | AB19: =IF(ISNA(I19),"",TEXT(I19,"#,##0")) -> 932 | AC19: =J19/$W$12 -> 0.062412096 | AD19: =IF(ISNA(J19),"",TEXT(J19,"#,##0")) -> 710 | AE19: =K19/$W$12 -> #N/A | AF19: =IF(ISNA(K19),"",TEXT(K19,"#,##0")) | AG19: =N19/$W$12 -> 0.90603024 | AH19: =O19/$W$12 -> 0 | AI19: =IF(ISNA(O19),"",TEXT(O19,"+#,##0")) -> +0 | AJ19: =P19/$W$12 -> 0.019514768 | AK19: =IF(ISNA(P19),"",TEXT(P19,"""-""#,##0")) -> -222 | AL19: =Q19/$W$12 -> 0 | AM19: =IF(ISNA(Q19),"",TEXT(Q19,"+#,##0")) -> +0 | AN19: =R19/$W$12 -> 0 | AO19: =IF(ISNA(R19),"",TEXT(R19,"""-""#,##0")) -> -0 | AP19: =S19/$X$12 -> #N/A | AQ19: =IF(ISNA(S19),"",TEXT(S19,"+0.0;-0.0")) | AR19: =T19/$X$12 -> -0.0065292695 | AS19: =IF(ISNA(T19),"",TEXT(T19,"+0.0;-0.0")) -> -23.8 | AT19: =U19/$X$12 -> 0 | AU19: =V19/$X$12 -> 0.0065292695
A20: Jul | B20: AC | C20: state | D20: 971 | E20: -56 | F20: =D20-E20 -> 1027 | G20: =IF(F20=0,NA(),E20/F20*100) -> -5.4527751 | H20: =NA() -> #N/A | I20: =F20 -> 1027 | J20: =IF($B20="AC",D20,NA()) -> 971 | K20: =IF($B20="FC",D20,NA()) -> #N/A | L20: =M20+E20 -> 10251 | M20: =L19 -> 10307 | N20: =MIN(M20,L20) -> 10251 | O20: =IF(AND($B20="AC",E20>0),E20,0) -> 0 | P20: =IF(AND($B20="AC",E20<0),-E20,0) -> 56 | Q20: =IF(AND($B20="FC",E20>0),E20,0) -> 0 | R20: =IF(AND($B20="FC",E20<0),-E20,0) -> 0 | S20: =IF(G20>0,G20,NA()) -> #N/A | T20: =IF(G20<0,G20,NA()) -> -5.4527751 | U20: =IF(G20>0,G20,0) -> 0 | V20: =IF(G20<0,-G20,0) -> 5.4527751 | Y20: =H20/$W$12 -> #N/A | Z20: =IF(ISNA(H20),"",TEXT(H20,"#,##0")) | AA20: =I20/$W$12 -> 0.090277778 | AB20: =IF(ISNA(I20),"",TEXT(I20,"#,##0")) -> 1,027 | AC20: =J20/$W$12 -> 0.085355134 | AD20: =IF(ISNA(J20),"",TEXT(J20,"#,##0")) -> 971 | AE20: =K20/$W$12 -> #N/A | AF20: =IF(ISNA(K20),"",TEXT(K20,"#,##0")) | AG20: =N20/$W$12 -> 0.90110759 | AH20: =O20/$W$12 -> 0 | AI20: =IF(ISNA(O20),"",TEXT(O20,"+#,##0")) -> +0 | AJ20: =P20/$W$12 -> 0.0049226442 | AK20: =IF(ISNA(P20),"",TEXT(P20,"""-""#,##0")) -> -56 | AL20: =Q20/$W$12 -> 0 | AM20: =IF(ISNA(Q20),"",TEXT(Q20,"+#,##0")) -> +0 | AN20: =R20/$W$12 -> 0 | AO20: =IF(ISNA(R20),"",TEXT(R20,"""-""#,##0")) -> -0 | AP20: =S20/$X$12 -> #N/A | AQ20: =IF(ISNA(S20),"",TEXT(S20,"+0.0;-0.0")) | AR20: =T20/$X$12 -> -0.0014946693 | AS20: =IF(ISNA(T20),"",TEXT(T20,"+0.0;-0.0")) -> -5.5 | AT20: =U20/$X$12 -> 0 | AU20: =V20/$X$12 -> 0.0014946693
A21: Aug | B21: FC | C21: state | D21: 987 | E21: -202 | F21: =D21-E21 -> 1189 | G21: =IF(F21=0,NA(),E21/F21*100) -> -16.989066 | H21: =NA() -> #N/A | I21: =F21 -> 1189 | J21: =IF($B21="AC",D21,NA()) -> #N/A | K21: =IF($B21="FC",D21,NA()) -> 987 | L21: =M21+E21 -> 10049 | M21: =L20 -> 10251 | N21: =MIN(M21,L21) -> 10049 | O21: =IF(AND($B21="AC",E21>0),E21,0) -> 0 | P21: =IF(AND($B21="AC",E21<0),-E21,0) -> 0 | Q21: =IF(AND($B21="FC",E21>0),E21,0) -> 0 | R21: =IF(AND($B21="FC",E21<0),-E21,0) -> 202 | S21: =IF(G21>0,G21,NA()) -> #N/A | T21: =IF(G21<0,G21,NA()) -> -16.989066 | U21: =IF(G21>0,G21,0) -> 0 | V21: =IF(G21<0,-G21,0) -> 16.989066 | Y21: =H21/$W$12 -> #N/A | Z21: =IF(ISNA(H21),"",TEXT(H21,"#,##0")) | AA21: =I21/$W$12 -> 0.10451828 | AB21: =IF(ISNA(I21),"",TEXT(I21,"#,##0")) -> 1,189 | AC21: =J21/$W$12 -> #N/A | AD21: =IF(ISNA(J21),"",TEXT(J21,"#,##0")) | AE21: =K21/$W$12 -> 0.086761603 | AF21: =IF(ISNA(K21),"",TEXT(K21,"#,##0")) -> 987 | AG21: =N21/$W$12 -> 0.88335091 | AH21: =O21/$W$12 -> 0 | AI21: =IF(ISNA(O21),"",TEXT(O21,"+#,##0")) -> +0 | AJ21: =P21/$W$12 -> 0 | AK21: =IF(ISNA(P21),"",TEXT(P21,"""-""#,##0")) -> -0 | AL21: =Q21/$W$12 -> 0 | AM21: =IF(ISNA(Q21),"",TEXT(Q21,"+#,##0")) -> +0 | AN21: =R21/$W$12 -> 0.017756681 | AO21: =IF(ISNA(R21),"",TEXT(R21,"""-""#,##0")) -> -202 | AP21: =S21/$X$12 -> #N/A | AQ21: =IF(ISNA(S21),"",TEXT(S21,"+0.0;-0.0")) | AR21: =T21/$X$12 -> -0.0046569015 | AS21: =IF(ISNA(T21),"",TEXT(T21,"+0.0;-0.0")) -> -17.0 | AT21: =U21/$X$12 -> 0 | AU21: =V21/$X$12 -> 0.0046569015
A22: Sep | B22: FC | C22: state | D22: 958 | E22: 985 | F22: =D22-E22 -> -27 | G22: =IF(F22=0,NA(),E22/F22*100) -> -3648.1481 | H22: =NA() -> #N/A | I22: =F22 -> -27 | J22: =IF($B22="AC",D22,NA()) -> #N/A | K22: =IF($B22="FC",D22,NA()) -> 958 | L22: =M22+E22 -> 11034 | M22: =L21 -> 10049 | N22: =MIN(M22,L22) -> 10049 | O22: =IF(AND($B22="AC",E22>0),E22,0) -> 0 | P22: =IF(AND($B22="AC",E22<0),-E22,0) -> 0 | Q22: =IF(AND($B22="FC",E22>0),E22,0) -> 985 | R22: =IF(AND($B22="FC",E22<0),-E22,0) -> 0 | S22: =IF(G22>0,G22,NA()) -> #N/A | T22: =IF(G22<0,G22,NA()) -> -3648.1481 | U22: =IF(G22>0,G22,0) -> 0 | V22: =IF(G22<0,-G22,0) -> 3648.1481 | Y22: =H22/$W$12 -> #N/A | Z22: =IF(ISNA(H22),"",TEXT(H22,"#,##0")) | AA22: =I22/$W$12 -> -0.0023734177 | AB22: =IF(ISNA(I22),"",TEXT(I22,"#,##0")) -> -27 | AC22: =J22/$W$12 -> #N/A | AD22: =IF(ISNA(J22),"",TEXT(J22,"#,##0")) | AE22: =K22/$W$12 -> 0.084212377 | AF22: =IF(ISNA(K22),"",TEXT(K22,"#,##0")) -> 958 | AG22: =N22/$W$12 -> 0.88335091 | AH22: =O22/$W$12 -> 0 | AI22: =IF(ISNA(O22),"",TEXT(O22,"+#,##0")) -> +0 | AJ22: =P22/$W$12 -> 0 | AK22: =IF(ISNA(P22),"",TEXT(P22,"""-""#,##0")) -> -0 | AL22: =Q22/$W$12 -> 0.086585795 | AM22: =IF(ISNA(Q22),"",TEXT(Q22,"+#,##0")) -> +985 | AN22: =R22/$W$12 -> 0 | AO22: =IF(ISNA(R22),"",TEXT(R22,"""-""#,##0")) -> -0 | AP22: =S22/$X$12 -> #N/A | AQ22: =IF(ISNA(S22),"",TEXT(S22,"+0.0;-0.0")) | AR22: =T22/$X$12 -> -1 | AS22: =IF(ISNA(T22),"",TEXT(T22,"+0.0;-0.0")) -> -3648.1 | AT22: =U22/$X$12 -> 0 | AU22: =V22/$X$12 -> 1
A23: Oct | B23: FC | C23: state | D23: 993 | E23: 264 | F23: =D23-E23 -> 729 | G23: =IF(F23=0,NA(),E23/F23*100) -> 36.213992 | H23: =NA() -> #N/A | I23: =F23 -> 729 | J23: =IF($B23="AC",D23,NA()) -> #N/A | K23: =IF($B23="FC",D23,NA()) -> 993 | L23: =M23+E23 -> 11298 | M23: =L22 -> 11034 | N23: =MIN(M23,L23) -> 11034 | O23: =IF(AND($B23="AC",E23>0),E23,0) -> 0 | P23: =IF(AND($B23="AC",E23<0),-E23,0) -> 0 | Q23: =IF(AND($B23="FC",E23>0),E23,0) -> 264 | R23: =IF(AND($B23="FC",E23<0),-E23,0) -> 0 | S23: =IF(G23>0,G23,NA()) -> 36.213992 | T23: =IF(G23<0,G23,NA()) -> #N/A | U23: =IF(G23>0,G23,0) -> 36.213992 | V23: =IF(G23<0,-G23,0) -> 0 | Y23: =H23/$W$12 -> #N/A | Z23: =IF(ISNA(H23),"",TEXT(H23,"#,##0")) | AA23: =I23/$W$12 -> 0.064082278 | AB23: =IF(ISNA(I23),"",TEXT(I23,"#,##0")) -> 729 | AC23: =J23/$W$12 -> #N/A | AD23: =IF(ISNA(J23),"",TEXT(J23,"#,##0")) | AE23: =K23/$W$12 -> 0.08728903 | AF23: =IF(ISNA(K23),"",TEXT(K23,"#,##0")) -> 993 | AG23: =N23/$W$12 -> 0.96993671 | AH23: =O23/$W$12 -> 0 | AI23: =IF(ISNA(O23),"",TEXT(O23,"+#,##0")) -> +0 | AJ23: =P23/$W$12 -> 0 | AK23: =IF(ISNA(P23),"",TEXT(P23,"""-""#,##0")) -> -0 | AL23: =Q23/$W$12 -> 0.023206751 | AM23: =IF(ISNA(Q23),"",TEXT(Q23,"+#,##0")) -> +264 | AN23: =R23/$W$12 -> 0 | AO23: =IF(ISNA(R23),"",TEXT(R23,"""-""#,##0")) -> -0 | AP23: =S23/$X$12 -> 0.0099266779 | AQ23: =IF(ISNA(S23),"",TEXT(S23,"+0.0;-0.0")) -> +36.2 | AR23: =T23/$X$12 -> #N/A | AS23: =IF(ISNA(T23),"",TEXT(T23,"+0.0;-0.0")) | AT23: =U23/$X$12 -> 0.0099266779 | AU23: =V23/$X$12 -> 0
A24: Nov | B24: FC | C24: state | D24: 967 | E24: 78 | F24: =D24-E24 -> 889 | G24: =IF(F24=0,NA(),E24/F24*100) -> 8.7739033 | H24: =NA() -> #N/A | I24: =F24 -> 889 | J24: =IF($B24="AC",D24,NA()) -> #N/A | K24: =IF($B24="FC",D24,NA()) -> 967 | L24: =M24+E24 -> 11376 | M24: =L23 -> 11298 | N24: =MIN(M24,L24) -> 11298 | O24: =IF(AND($B24="AC",E24>0),E24,0) -> 0 | P24: =IF(AND($B24="AC",E24<0),-E24,0) -> 0 | Q24: =IF(AND($B24="FC",E24>0),E24,0) -> 78 | R24: =IF(AND($B24="FC",E24<0),-E24,0) -> 0 | S24: =IF(G24>0,G24,NA()) -> 8.7739033 | T24: =IF(G24<0,G24,NA()) -> #N/A | U24: =IF(G24>0,G24,0) -> 8.7739033 | V24: =IF(G24<0,-G24,0) -> 0 | Y24: =H24/$W$12 -> #N/A | Z24: =IF(ISNA(H24),"",TEXT(H24,"#,##0")) | AA24: =I24/$W$12 -> 0.078146976 | AB24: =IF(ISNA(I24),"",TEXT(I24,"#,##0")) -> 889 | AC24: =J24/$W$12 -> #N/A | AD24: =IF(ISNA(J24),"",TEXT(J24,"#,##0")) | AE24: =K24/$W$12 -> 0.085003516 | AF24: =IF(ISNA(K24),"",TEXT(K24,"#,##0")) -> 967 | AG24: =N24/$W$12 -> 0.99314346 | AH24: =O24/$W$12 -> 0 | AI24: =IF(ISNA(O24),"",TEXT(O24,"+#,##0")) -> +0 | AJ24: =P24/$W$12 -> 0 | AK24: =IF(ISNA(P24),"",TEXT(P24,"""-""#,##0")) -> -0 | AL24: =Q24/$W$12 -> 0.0068565401 | AM24: =IF(ISNA(Q24),"",TEXT(Q24,"+#,##0")) -> +78 | AN24: =R24/$W$12 -> 0 | AO24: =IF(ISNA(R24),"",TEXT(R24,"""-""#,##0")) -> -0 | AP24: =S24/$X$12 -> 0.0024050293 | AQ24: =IF(ISNA(S24),"",TEXT(S24,"+0.0;-0.0")) -> +8.8 | AR24: =T24/$X$12 -> #N/A | AS24: =IF(ISNA(T24),"",TEXT(T24,"+0.0;-0.0")) | AT24: =U24/$X$12 -> 0.0024050293 | AU24: =V24/$X$12 -> 0
A25: Dec | B25: FC | C25: state | D25: 999 | E25: 80 | F25: =D25-E25 -> 919 | G25: =IF(F25=0,NA(),E25/F25*100) -> 8.7051143 | H25: =NA() -> #N/A | I25: =F25 -> 919 | J25: =IF($B25="AC",D25,NA()) -> #N/A | K25: =IF($B25="FC",D25,NA()) -> 999 | L25: =M25+E25 -> 11456 | M25: =L24 -> 11376 | N25: =MIN(M25,L25) -> 11376 | O25: =IF(AND($B25="AC",E25>0),E25,0) -> 0 | P25: =IF(AND($B25="AC",E25<0),-E25,0) -> 0 | Q25: =IF(AND($B25="FC",E25>0),E25,0) -> 80 | R25: =IF(AND($B25="FC",E25<0),-E25,0) -> 0 | S25: =IF(G25>0,G25,NA()) -> 8.7051143 | T25: =IF(G25<0,G25,NA()) -> #N/A | U25: =IF(G25>0,G25,0) -> 8.7051143 | V25: =IF(G25<0,-G25,0) -> 0 | Y25: =H25/$W$12 -> #N/A | Z25: =IF(ISNA(H25),"",TEXT(H25,"#,##0")) | AA25: =I25/$W$12 -> 0.080784107 | AB25: =IF(ISNA(I25),"",TEXT(I25,"#,##0")) -> 919 | AC25: =J25/$W$12 -> #N/A | AD25: =IF(ISNA(J25),"",TEXT(J25,"#,##0")) | AE25: =K25/$W$12 -> 0.087816456 | AF25: =IF(ISNA(K25),"",TEXT(K25,"#,##0")) -> 999 | AG25: =N25/$W$12 -> 1 | AH25: =O25/$W$12 -> 0 | AI25: =IF(ISNA(O25),"",TEXT(O25,"+#,##0")) -> +0 | AJ25: =P25/$W$12 -> 0 | AK25: =IF(ISNA(P25),"",TEXT(P25,"""-""#,##0")) -> -0 | AL25: =Q25/$W$12 -> 0.0070323488 | AM25: =IF(ISNA(Q25),"",TEXT(Q25,"+#,##0")) -> +80 | AN25: =R25/$W$12 -> 0 | AO25: =IF(ISNA(R25),"",TEXT(R25,"""-""#,##0")) -> -0 | AP25: =S25/$X$12 -> 0.0023861735 | AQ25: =IF(ISNA(S25),"",TEXT(S25,"+0.0;-0.0")) -> +8.7 | AR25: =T25/$X$12 -> #N/A | AS25: =IF(ISNA(T25),"",TEXT(T25,"+0.0;-0.0")) | AT25: =U25/$X$12 -> 0.0023861735 | AU25: =V25/$X$12 -> 0
A26: 2026 AC+FC | B26: AC | C26: total | D26: =SUM(D14:D25) -> 11456 | E26: =D26-$D$13 -> 1200 | F26: =0 -> 0 | G26: =IF($D$13<=0,NA(),E26/$D$13*100) -> 11.700468 | H26: =NA() -> #N/A | I26: =NA() -> #N/A | J26: =SUMIF($B$14:$B$25,"AC",$D$14:$D$25) -> 6552 | K26: =SUMIF($B$14:$B$25,"FC",$D$14:$D$25) -> 4904 | L26: =L25 -> 11456 | M26: =L26 -> 11456 | N26: =0 -> 0 | O26: =0 -> 0 | P26: =0 -> 0 | Q26: =0 -> 0 | R26: =0 -> 0 | S26: =IF(G26>0,G26,NA()) -> 11.700468 | T26: =IF(G26<0,G26,NA()) -> #N/A | U26: =IF(G26>0,G26,0) -> 11.700468 | V26: =IF(G26<0,-G26,0) -> 0 | Y26: =H26/$W$12 -> #N/A | Z26: =IF(ISNA(H26),"",TEXT(H26,"#,##0")) | AA26: =I26/$W$12 -> #N/A | AB26: =IF(ISNA(I26),"",TEXT(I26,"#,##0")) | AC26: =J26/$W$12 -> 0.57594937 | AD26: =IF(ISNA(J26),"",TEXT(J26,"#,##0")) -> 6,552 | AE26: =K26/$W$12 -> 0.43108298 | AF26: =IF(ISNA(K26),"",TEXT(K26,"#,##0")) -> 4,904 | AG26: =N26/$W$12 -> 0 | AH26: =O26/$W$12 -> 0 | AI26: =IF(ISNA(O26),"",TEXT(O26,"+#,##0")) -> +0 | AJ26: =P26/$W$12 -> 0 | AK26: =IF(ISNA(P26),"",TEXT(P26,"""-""#,##0")) -> -0 | AL26: =Q26/$W$12 -> 0 | AM26: =IF(ISNA(Q26),"",TEXT(Q26,"+#,##0")) -> +0 | AN26: =R26/$W$12 -> 0 | AO26: =IF(ISNA(R26),"",TEXT(R26,"""-""#,##0")) -> -0 | AP26: =S26/$X$12 -> 0.0032072349 | AQ26: =IF(ISNA(S26),"",TEXT(S26,"+0.0;-0.0")) -> +11.7 | AR26: =T26/$X$12 -> #N/A | AS26: =IF(ISNA(T26),"",TEXT(T26,"+0.0;-0.0")) | AT26: =U26/$X$12 -> 0.0032072349 | AU26: =V26/$X$12 -> 0
A27: vs PY | C27: variance | E27: =$D$26-$D$13 -> 1200 | F27: =0 -> 0 | G27: =NA() -> #N/A | H27: =NA() -> #N/A | I27: =NA() -> #N/A | J27: =NA() -> #N/A | K27: =NA() -> #N/A | L27: =$D$26 -> 11456 | M27: =$D$13 -> 10256 | N27: =MIN($D$13,$D$26) -> 10256 | O27: =IF(E27>0,E27,0) -> 1200 | P27: =IF(E27<0,-E27,0) -> 0 | Q27: =0 -> 0 | R27: =0 -> 0 | S27: =NA() -> #N/A | T27: =NA() -> #N/A | U27: =0 -> 0 | V27: =0 -> 0 | Y27: =H27/$W$12 -> #N/A | Z27: =IF(ISNA(H27),"",TEXT(H27,"#,##0")) | AA27: =I27/$W$12 -> #N/A | AB27: =IF(ISNA(I27),"",TEXT(I27,"#,##0")) | AC27: =J27/$W$12 -> #N/A | AD27: =IF(ISNA(J27),"",TEXT(J27,"#,##0")) | AE27: =K27/$W$12 -> #N/A | AF27: =IF(ISNA(K27),"",TEXT(K27,"#,##0")) | AG27: =N27/$W$12 -> 0.90154712 | AH27: =O27/$W$12 -> 0.10548523 | AI27: =IF(ISNA(O27),"",TEXT(O27,"+#,##0")) -> +1,200 | AJ27: =P27/$W$12 -> 0 | AK27: =IF(ISNA(P27),"",TEXT(P27,"""-""#,##0")) -> -0 | AL27: =Q27/$W$12 -> 0 | AM27: =IF(ISNA(Q27),"",TEXT(Q27,"+#,##0")) -> +0 | AN27: =R27/$W$12 -> 0 | AO27: =IF(ISNA(R27),"",TEXT(R27,"""-""#,##0")) -> -0 | AP27: =S27/$X$12 -> #N/A | AQ27: =IF(ISNA(S27),"",TEXT(S27,"+0.0;-0.0")) | AR27: =T27/$X$12 -> #N/A | AS27: =IF(ISNA(T27),"",TEXT(T27,"+0.0;-0.0")) | AT27: =U27/$X$12 -> 0 | AU27: =V27/$X$12 -> 0
A28: vs PL | C28: variance | E28: =$D$26-$D$12 -> 1200 | F28: =0 -> 0 | G28: =NA() -> #N/A | H28: =NA() -> #N/A | I28: =NA() -> #N/A | J28: =NA() -> #N/A | K28: =NA() -> #N/A | L28: =$D$26 -> 11456 | M28: =$D$12 -> 10256 | N28: =MIN($D$12,$D$26) -> 10256 | O28: =IF(E28>0,E28,0) -> 1200 | P28: =IF(E28<0,-E28,0) -> 0 | Q28: =0 -> 0 | R28: =0 -> 0 | S28: =NA() -> #N/A | T28: =NA() -> #N/A | U28: =0 -> 0 | V28: =0 -> 0 | Y28: =H28/$W$12 -> #N/A | Z28: =IF(ISNA(H28),"",TEXT(H28,"#,##0")) | AA28: =I28/$W$12 -> #N/A | AB28: =IF(ISNA(I28),"",TEXT(I28,"#,##0")) | AC28: =J28/$W$12 -> #N/A | AD28: =IF(ISNA(J28),"",TEXT(J28,"#,##0")) | AE28: =K28/$W$12 -> #N/A | AF28: =IF(ISNA(K28),"",TEXT(K28,"#,##0")) | AG28: =N28/$W$12 -> 0.90154712 | AH28: =O28/$W$12 -> 0.10548523 | AI28: =IF(ISNA(O28),"",TEXT(O28,"+#,##0")) -> +1,200 | AJ28: =P28/$W$12 -> 0 | AK28: =IF(ISNA(P28),"",TEXT(P28,"""-""#,##0")) -> -0 | AL28: =Q28/$W$12 -> 0 | AM28: =IF(ISNA(Q28),"",TEXT(Q28,"+#,##0")) -> +0 | AN28: =R28/$W$12 -> 0 | AO28: =IF(ISNA(R28),"",TEXT(R28,"""-""#,##0")) -> -0 | AP28: =S28/$X$12 -> #N/A | AQ28: =IF(ISNA(S28),"",TEXT(S28,"+0.0;-0.0")) | AR28: =T28/$X$12 -> #N/A | AS28: =IF(ISNA(T28),"",TEXT(T28,"+0.0;-0.0")) | AT28: =U28/$X$12 -> 0 | AU28: =V28/$X$12 -> 0
A30: PL is not reported by the entity. The 96 combined ratio target applied to the premium each month actually earned. The target is filed; using it as a monthly plan is this workbook's construction, and it is a floor the company aims to beat rather than a forecast. Replace these cells with your own figures and every chart on this sheet follows.
A31: FC is not reported by the entity. Remaining months are the prior year's at the year-to-date pace, earning the year-to-date margin - the basis C07C states and the same numbers. Replace these cells with your own figures and every chart on this sheet follows.

Sheet C06F
A1: Entity | B1: The Progressive Corporation
A2: Measure | B2: Net premiums written
A3: Unit | B3: $m
A4: Period | B4: 2025
A5: Reference | B5: PY
A6: Message | B6: Premium grew +8,750 $m (+11.8%) and every one of the ten largest states grew. But 56% of the increase came from outside the top ten - +4,885 $m against +3,865 from all ten named states put together, Texas included
A7: Subject | B7: =B2&" in "&B3 -> Net premiums written in $m
A9: var_rel caption | B9: ="Δ"&$B$5&"%" -> ΔPY%
A11: Line | B11: Kind | C11: Scenario | D11: AC | E11: ΔPY% | F11: PY | G11: ΔPY | H11: AC bar | I11: PY short | J11: PL bar | K11: PY bar | L11: AC total | M11: level | N11: from | O11: base | P11: step up | Q11: step down | R11: ΔPY% up | S11: ΔPY% down | T11: span unit | U11: span rel | V11: bar_state scaled | W11: bar_state text | X11: bar_short scaled | Y11: bar_pl scaled | Z11: bar_pl text | AA11: bar_py scaled | AB11: bar_py text | AC11: bar_ac scaled | AD11: bar_ac text | AE11: wf_base scaled | AF11: wf_up scaled | AG11: wf_up text | AH11: wf_dn scaled | AI11: wf_dn text | AJ11: var_rel scaled | AK11: var_rel text | AL11: rel_up scaled | AM11: rel_dn scaled
A12: PY | B12: total | C12: PY | D12: =SUM(F13:F23) -> 74424 | F12: =0 -> 0 | H12: =0 -> 0 | I12: =0 -> 0 | J12: =0 -> 0 | K12: =D12 -> 74424 | L12: =0 -> 0 | M12: =D12 -> 74424 | N12: =M12 -> 74424 | O12: =0 -> 0 | P12: =0 -> 0 | Q12: =0 -> 0 | R12: =NA() -> #N/A | S12: =NA() -> #N/A | T12: =MAX(_xlfn.AGGREGATE(4,6,H12:H31,I12:I31,J12:J31,K12:K31,L12:L31,O12:O31,P12:P31,Q12:Q31),-_xlfn.AGGREGATE(5,6,H12:H31,I12:I31,J12:J31,K12:K31,L12:L31,O12:O31,P12:P31,Q12:Q31),0.000000001) -> 83174 | U12: =MAX(_xlfn.AGGREGATE(4,6,E12:E31,R12:R31,S12:S31),-_xlfn.AGGREGATE(5,6,E12:E31,R12:R31,S12:S31),0.000000001) -> 28.286491 | V12: =H12/$T$12 -> 0 | W12: =IF(ISNA(H12),"",TEXT(H12,"#,##0")) -> 0 | X12: =I12/$T$12 -> 0 | Y12: =J12/$T$12 -> 0 | Z12: =IF(ISNA(J12),"",TEXT(J12,"#,##0")) -> 0 | AA12: =K12/$T$12 -> 0.89479886 | AB12: =IF(ISNA(K12),"",TEXT(K12,"#,##0")) -> 74,424 | AC12: =L12/$T$12 -> 0 | AD12: =IF(ISNA(L12),"",TEXT(L12,"#,##0")) -> 0 | AE12: =O12/$T$12 -> 0 | AF12: =P12/$T$12 -> 0 | AG12: =IF(ISNA(P12),"",TEXT(P12,"+#,##0")) -> +0 | AH12: =Q12/$T$12 -> 0 | AI12: =IF(ISNA(Q12),"",TEXT(Q12,"""-""#,##0")) -> -0 | AJ12: =E12/$U$12 -> 0 | AK12: =IF(ISNA(E12),"",TEXT(E12,"+0;-0")) -> +0 | AL12: =R12/$U$12 -> #N/A | AM12: =S12/$U$12 -> #N/A
A13: Texas | B13: state | C13: AC | D13: 10315 | E13: 6.990976 | F13: =IF(E13=-100,NA(),D13/(1+E13/100)) -> 9641 | G13: =D13-F13 -> 674 | H13: =D13 -> 10315 | I13: =MAX(F13-D13,0) -> 0 | J13: =0 -> 0 | K13: =0 -> 0 | L13: =0 -> 0 | M13: =N13+G13 -> 75098 | N13: =M12 -> 74424 | O13: =MIN(N13,M13) -> 74424 | P13: =IF(G13>0,G13,0) -> 674 | Q13: =IF(G13<0,-G13,0) -> 0 | R13: =IF(E13>0,E13,NA()) -> 6.990976 | S13: =IF(E13<0,E13,NA()) -> #N/A | V13: =H13/$T$12 -> 0.12401712 | W13: =IF(ISNA(H13),"",TEXT(H13,"#,##0")) -> 10,315 | X13: =I13/$T$12 -> 0 | Y13: =J13/$T$12 -> 0 | Z13: =IF(ISNA(J13),"",TEXT(J13,"#,##0")) -> 0 | AA13: =K13/$T$12 -> 0 | AB13: =IF(ISNA(K13),"",TEXT(K13,"#,##0")) -> 0 | AC13: =L13/$T$12 -> 0 | AD13: =IF(ISNA(L13),"",TEXT(L13,"#,##0")) -> 0 | AE13: =O13/$T$12 -> 0.89479886 | AF13: =P13/$T$12 -> 0.0081034939 | AG13: =IF(ISNA(P13),"",TEXT(P13,"+#,##0")) -> +674 | AH13: =Q13/$T$12 -> 0 | AI13: =IF(ISNA(Q13),"",TEXT(Q13,"""-""#,##0")) -> -0 | AJ13: =E13/$U$12 -> 0.24714893 | AK13: =IF(ISNA(E13),"",TEXT(E13,"+0;-0")) -> +7 | AL13: =R13/$U$12 -> 0.24714893 | AM13: =S13/$U$12 -> #N/A
A14: California | B14: state | C14: AC | D14: 4777 | E14: 15.834142 | F14: =IF(E14=-100,NA(),D14/(1+E14/100)) -> 4124 | G14: =D14-F14 -> 653 | H14: =D14 -> 4777 | I14: =MAX(F14-D14,0) -> 0 | J14: =0 -> 0 | K14: =0 -> 0 | L14: =0 -> 0 | M14: =N14+G14 -> 75751 | N14: =M13 -> 75098 | O14: =MIN(N14,M14) -> 75098 | P14: =IF(G14>0,G14,0) -> 653 | Q14: =IF(G14<0,-G14,0) -> 0 | R14: =IF(E14>0,E14,NA()) -> 15.834142 | S14: =IF(E14<0,E14,NA()) -> #N/A | V14: =H14/$T$12 -> 0.057433813 | W14: =IF(ISNA(H14),"",TEXT(H14,"#,##0")) -> 4,777 | X14: =I14/$T$12 -> 0 | Y14: =J14/$T$12 -> 0 | Z14: =IF(ISNA(J14),"",TEXT(J14,"#,##0")) -> 0 | AA14: =K14/$T$12 -> 0 | AB14: =IF(ISNA(K14),"",TEXT(K14,"#,##0")) -> 0 | AC14: =L14/$T$12 -> 0 | AD14: =IF(ISNA(L14),"",TEXT(L14,"#,##0")) -> 0 | AE14: =O14/$T$12 -> 0.90290235 | AF14: =P14/$T$12 -> 0.0078510111 | AG14: =IF(ISNA(P14),"",TEXT(P14,"+#,##0")) -> +653 | AH14: =Q14/$T$12 -> 0 | AI14: =IF(ISNA(Q14),"",TEXT(Q14,"""-""#,##0")) -> -0 | AJ14: =E14/$U$12 -> 0.55977751 | AK14: =IF(ISNA(E14),"",TEXT(E14,"+0;-0")) -> +16 | AL14: =R14/$U$12 -> 0.55977751 | AM14: =S14/$U$12 -> #N/A
A15: New Jersey | B15: state | C15: AC | D15: 2830 | E15: 28.286491 | F15: =IF(E15=-100,NA(),D15/(1+E15/100)) -> 2206 | G15: =D15-F15 -> 624 | H15: =D15 -> 2830 | I15: =MAX(F15-D15,0) -> 0 | J15: =0 -> 0 | K15: =0 -> 0 | L15: =0 -> 0 | M15: =N15+G15 -> 76375 | N15: =M14 -> 75751 | O15: =MIN(N15,M15) -> 75751 | P15: =IF(G15>0,G15,0) -> 624 | Q15: =IF(G15<0,-G15,0) -> 0 | R15: =IF(E15>0,E15,NA()) -> 28.286491 | S15: =IF(E15<0,E15,NA()) -> #N/A | V15: =H15/$T$12 -> 0.034025056 | W15: =IF(ISNA(H15),"",TEXT(H15,"#,##0")) -> 2,830 | X15: =I15/$T$12 -> 0 | Y15: =J15/$T$12 -> 0 | Z15: =IF(ISNA(J15),"",TEXT(J15,"#,##0")) -> 0 | AA15: =K15/$T$12 -> 0 | AB15: =IF(ISNA(K15),"",TEXT(K15,"#,##0")) -> 0 | AC15: =L15/$T$12 -> 0 | AD15: =IF(ISNA(L15),"",TEXT(L15,"#,##0")) -> 0 | AE15: =O15/$T$12 -> 0.91075336 | AF15: =P15/$T$12 -> 0.0075023445 | AG15: =IF(ISNA(P15),"",TEXT(P15,"+#,##0")) -> +624 | AH15: =Q15/$T$12 -> 0 | AI15: =IF(ISNA(Q15),"",TEXT(Q15,"""-""#,##0")) -> -0 | AJ15: =E15/$U$12 -> 1 | AK15: =IF(ISNA(E15),"",TEXT(E15,"+0;-0")) -> +28 | AL15: =R15/$U$12 -> 1 | AM15: =S15/$U$12 -> #N/A
A16: New York | B16: state | C16: AC | D16: 3359 | E16: 18.69258 | F16: =IF(E16=-100,NA(),D16/(1+E16/100)) -> 2830 | G16: =D16-F16 -> 529 | H16: =D16 -> 3359 | I16: =MAX(F16-D16,0) -> 0 | J16: =0 -> 0 | K16: =0 -> 0 | L16: =0 -> 0 | M16: =N16+G16 -> 76904 | N16: =M15 -> 76375 | O16: =MIN(N16,M16) -> 76375 | P16: =IF(G16>0,G16,0) -> 529 | Q16: =IF(G16<0,-G16,0) -> 0 | R16: =IF(E16>0,E16,NA()) -> 18.69258 | S16: =IF(E16<0,E16,NA()) -> #N/A | V16: =H16/$T$12 -> 0.040385217 | W16: =IF(ISNA(H16),"",TEXT(H16,"#,##0")) -> 3,359 | X16: =I16/$T$12 -> 0 | Y16: =J16/$T$12 -> 0 | Z16: =IF(ISNA(J16),"",TEXT(J16,"#,##0")) -> 0 | AA16: =K16/$T$12 -> 0 | AB16: =IF(ISNA(K16),"",TEXT(K16,"#,##0")) -> 0 | AC16: =L16/$T$12 -> 0 | AD16: =IF(ISNA(L16),"",TEXT(L16,"#,##0")) -> 0 | AE16: =O16/$T$12 -> 0.9182557 | AF16: =P16/$T$12 -> 0.0063601606 | AG16: =IF(ISNA(P16),"",TEXT(P16,"+#,##0")) -> +529 | AH16: =Q16/$T$12 -> 0 | AI16: =IF(ISNA(Q16),"",TEXT(Q16,"""-""#,##0")) -> -0 | AJ16: =E16/$U$12 -> 0.66083062 | AK16: =IF(ISNA(E16),"",TEXT(E16,"+0;-0")) -> +19 | AL16: =R16/$U$12 -> 0.66083062 | AM16: =S16/$U$12 -> #N/A
A17: Georgia | B17: state | C17: AC | D17: 4084 | E17: 12.352132 | F17: =IF(E17=-100,NA(),D17/(1+E17/100)) -> 3635 | G17: =D17-F17 -> 449 | H17: =D17 -> 4084 | I17: =MAX(F17-D17,0) -> 0 | J17: =0 -> 0 | K17: =0 -> 0 | L17: =0 -> 0 | M17: =N17+G17 -> 77353 | N17: =M16 -> 76904 | O17: =MIN(N17,M17) -> 76904 | P17: =IF(G17>0,G17,0) -> 449 | Q17: =IF(G17<0,-G17,0) -> 0 | R17: =IF(E17>0,E17,NA()) -> 12.352132 | S17: =IF(E17<0,E17,NA()) -> #N/A | V17: =H17/$T$12 -> 0.049101883 | W17: =IF(ISNA(H17),"",TEXT(H17,"#,##0")) -> 4,084 | X17: =I17/$T$12 -> 0 | Y17: =J17/$T$12 -> 0 | Z17: =IF(ISNA(J17),"",TEXT(J17,"#,##0")) -> 0 | AA17: =K17/$T$12 -> 0 | AB17: =IF(ISNA(K17),"",TEXT(K17,"#,##0")) -> 0 | AC17: =L17/$T$12 -> 0 | AD17: =IF(ISNA(L17),"",TEXT(L17,"#,##0")) -> 0 | AE17: =O17/$T$12 -> 0.92461587 | AF17: =P17/$T$12 -> 0.0053983216 | AG17: =IF(ISNA(P17),"",TEXT(P17,"+#,##0")) -> +449 | AH17: =Q17/$T$12 -> 0 | AI17: =IF(ISNA(Q17),"",TEXT(Q17,"""-""#,##0")) -> -0 | AJ17: =E17/$U$12 -> 0.43667954 | AK17: =IF(ISNA(E17),"",TEXT(E17,"+0;-0")) -> +12 | AL17: =R17/$U$12 -> 0.43667954 | AM17: =S17/$U$12 -> #N/A
A18: Ohio | B18: state | C18: AC | D18: 2445 | E18: 12.776753 | F18: =IF(E18=-100,NA(),D18/(1+E18/100)) -> 2168 | G18: =D18-F18 -> 277 | H18: =D18 -> 2445 | I18: =MAX(F18-D18,0) -> 0 | J18: =0 -> 0 | K18: =0 -> 0 | L18: =0 -> 0 | M18: =N18+G18 -> 77630 | N18: =M17 -> 77353 | O18: =MIN(N18,M18) -> 77353 | P18: =IF(G18>0,G18,0) -> 277 | Q18: =IF(G18<0,-G18,0) -> 0 | R18: =IF(E18>0,E18,NA()) -> 12.776753 | S18: =IF(E18<0,E18,NA()) -> #N/A | V18: =H18/$T$12 -> 0.029396206 | W18: =IF(ISNA(H18),"",TEXT(H18,"#,##0")) -> 2,445 | X18: =I18/$T$12 -> 0 | Y18: =J18/$T$12 -> 0 | Z18: =IF(ISNA(J18),"",TEXT(J18,"#,##0")) -> 0 | AA18: =K18/$T$12 -> 0 | AB18: =IF(ISNA(K18),"",TEXT(K18,"#,##0")) -> 0 | AC18: =L18/$T$12 -> 0 | AD18: =IF(ISNA(L18),"",TEXT(L18,"#,##0")) -> 0 | AE18: =O18/$T$12 -> 0.93001419 | AF18: =P18/$T$12 -> 0.0033303677 | AG18: =IF(ISNA(P18),"",TEXT(P18,"+#,##0")) -> +277 | AH18: =Q18/$T$12 -> 0 | AI18: =IF(ISNA(Q18),"",TEXT(Q18,"""-""#,##0")) -> -0 | AJ18: =E18/$U$12 -> 0.45169097 | AK18: =IF(ISNA(E18),"",TEXT(E18,"+0;-0")) -> +13 | AL18: =R18/$U$12 -> 0.45169097 | AM18: =S18/$U$12 -> #N/A
A19: Arizona | B19: state | C19: AC | D19: 2240 | E19: 12.619407 | F19: =IF(E19=-100,NA(),D19/(1+E19/100)) -> 1989 | G19: =D19-F19 -> 251 | H19: =D19 -> 2240 | I19: =MAX(F19-D19,0) -> 0 | J19: =0 -> 0 | K19: =0 -> 0 | L19: =0 -> 0 | M19: =N19+G19 -> 77881 | N19: =M18 -> 77630 | O19: =MIN(N19,M19) -> 77630 | P19: =IF(G19>0,G19,0) -> 251 | Q19: =IF(G19<0,-G19,0) -> 0 | R19: =IF(E19>0,E19,NA()) -> 12.619407 | S19: =IF(E19<0,E19,NA()) -> #N/A | V19: =H19/$T$12 -> 0.026931493 | W19: =IF(ISNA(H19),"",TEXT(H19,"#,##0")) -> 2,240 | X19: =I19/$T$12 -> 0 | Y19: =J19/$T$12 -> 0 | Z19: =IF(ISNA(J19),"",TEXT(J19,"#,##0")) -> 0 | AA19: =K19/$T$12 -> 0 | AB19: =IF(ISNA(K19),"",TEXT(K19,"#,##0")) -> 0 | AC19: =L19/$T$12 -> 0 | AD19: =IF(ISNA(L19),"",TEXT(L19,"#,##0")) -> 0 | AE19: =O19/$T$12 -> 0.93334455 | AF19: =P19/$T$12 -> 0.00301777 | AG19: =IF(ISNA(P19),"",TEXT(P19,"+#,##0")) -> +251 | AH19: =Q19/$T$12 -> 0 | AI19: =IF(ISNA(Q19),"",TEXT(Q19,"""-""#,##0")) -> -0 | AJ19: =E19/$U$12 -> 0.44612839 | AK19: =IF(ISNA(E19),"",TEXT(E19,"+0;-0")) -> +13 | AL19: =R19/$U$12 -> 0.44612839 | AM19: =S19/$U$12 -> #N/A
A20: Pennsylvania | B20: state | C20: AC | D20: 2414 | E20: 10.127737 | F20: =IF(E20=-100,NA(),D20/(1+E20/100)) -> 2192 | G20: =D20-F20 -> 222 | H20: =D20 -> 2414 | I20: =MAX(F20-D20,0) -> 0 | J20: =0 -> 0 | K20: =0 -> 0 | L20: =0 -> 0 | M20: =N20+G20 -> 78103 | N20: =M19 -> 77881 | O20: =MIN(N20,M20) -> 77881 | P20: =IF(G20>0,G20,0) -> 222 | Q20: =IF(G20<0,-G20,0) -> 0 | R20: =IF(E20>0,E20,NA()) -> 10.127737 | S20: =IF(E20<0,E20,NA()) -> #N/A | V20: =H20/$T$12 -> 0.029023493 | W20: =IF(ISNA(H20),"",TEXT(H20,"#,##0")) -> 2,414 | X20: =I20/$T$12 -> 0 | Y20: =J20/$T$12 -> 0 | Z20: =IF(ISNA(J20),"",TEXT(J20,"#,##0")) -> 0 | AA20: =K20/$T$12 -> 0 | AB20: =IF(ISNA(K20),"",TEXT(K20,"#,##0")) -> 0 | AC20: =L20/$T$12 -> 0 | AD20: =IF(ISNA(L20),"",TEXT(L20,"#,##0")) -> 0 | AE20: =O20/$T$12 -> 0.93636232 | AF20: =P20/$T$12 -> 0.0026691033 | AG20: =IF(ISNA(P20),"",TEXT(P20,"+#,##0")) -> +222 | AH20: =Q20/$T$12 -> 0 | AI20: =IF(ISNA(Q20),"",TEXT(Q20,"""-""#,##0")) -> -0 | AJ20: =E20/$U$12 -> 0.35804148 | AK20: =IF(ISNA(E20),"",TEXT(E20,"+0;-0")) -> +10 | AL20: =R20/$U$12 -> 0.35804148 | AM20: =S20/$U$12 -> #N/A
A21: Michigan | B21: state | C21: AC | D21: 2775 | E21: 5.5936073 | F21: =IF(E21=-100,NA(),D21/(1+E21/100)) -> 2628 | G21: =D21-F21 -> 147 | H21: =D21 -> 2775 | I21: =MAX(F21-D21,0) -> 0 | J21: =0 -> 0 | K21: =0 -> 0 | L21: =0 -> 0 | M21: =N21+G21 -> 78250 | N21: =M20 -> 78103 | O21: =MIN(N21,M21) -> 78103 | P21: =IF(G21>0,G21,0) -> 147 | Q21: =IF(G21<0,-G21,0) -> 0 | R21: =IF(E21>0,E21,NA()) -> 5.5936073 | S21: =IF(E21<0,E21,NA()) -> #N/A | V21: =H21/$T$12 -> 0.033363792 | W21: =IF(ISNA(H21),"",TEXT(H21,"#,##0")) -> 2,775 | X21: =I21/$T$12 -> 0 | Y21: =J21/$T$12 -> 0 | Z21: =IF(ISNA(J21),"",TEXT(J21,"#,##0")) -> 0 | AA21: =K21/$T$12 -> 0 | AB21: =IF(ISNA(K21),"",TEXT(K21,"#,##0")) -> 0 | AC21: =L21/$T$12 -> 0 | AD21: =IF(ISNA(L21),"",TEXT(L21,"#,##0")) -> 0 | AE21: =O21/$T$12 -> 0.93903143 | AF21: =P21/$T$12 -> 0.0017673792 | AG21: =IF(ISNA(P21),"",TEXT(P21,"+#,##0")) -> +147 | AH21: =Q21/$T$12 -> 0 | AI21: =IF(ISNA(Q21),"",TEXT(Q21,"""-""#,##0")) -> -0 | AJ21: =E21/$U$12 -> 0.19774836 | AK21: =IF(ISNA(E21),"",TEXT(E21,"+0;-0")) -> +6 | AL21: =R21/$U$12 -> 0.19774836 | AM21: =S21/$U$12 -> #N/A
A22: Florida | B22: state | C22: AC | D22: 10261 | E22: 0.38153003 | F22: =IF(E22=-100,NA(),D22/(1+E22/100)) -> 10222 | G22: =D22-F22 -> 39 | H22: =D22 -> 10261 | I22: =MAX(F22-D22,0) -> 0 | J22: =0 -> 0 | K22: =0 -> 0 | L22: =0 -> 0 | M22: =N22+G22 -> 78289 | N22: =M21 -> 78250 | O22: =MIN(N22,M22) -> 78250 | P22: =IF(G22>0,G22,0) -> 39 | Q22: =IF(G22<0,-G22,0) -> 0 | R22: =IF(E22>0,E22,NA()) -> 0.38153003 | S22: =IF(E22<0,E22,NA()) -> #N/A | V22: =H22/$T$12 -> 0.12336788 | W22: =IF(ISNA(H22),"",TEXT(H22,"#,##0")) -> 10,261 | X22: =I22/$T$12 -> 0 | Y22: =J22/$T$12 -> 0 | Z22: =IF(ISNA(J22),"",TEXT(J22,"#,##0")) -> 0 | AA22: =K22/$T$12 -> 0 | AB22: =IF(ISNA(K22),"",TEXT(K22,"#,##0")) -> 0 | AC22: =L22/$T$12 -> 0 | AD22: =IF(ISNA(L22),"",TEXT(L22,"#,##0")) -> 0 | AE22: =O22/$T$12 -> 0.94079881 | AF22: =P22/$T$12 -> 0.00046889653 | AG22: =IF(ISNA(P22),"",TEXT(P22,"+#,##0")) -> +39 | AH22: =Q22/$T$12 -> 0 | AI22: =IF(ISNA(Q22),"",TEXT(Q22,"""-""#,##0")) -> -0 | AJ22: =E22/$U$12 -> 0.013488065 | AK22: =IF(ISNA(E22),"",TEXT(E22,"+0;-0")) -> +0 | AL22: =R22/$U$12 -> 0.013488065 | AM22: =S22/$U$12 -> #N/A
A23: All other | B23: state | C23: AC | D23: 37674 | E23: 14.898289 | F23: =IF(E23=-100,NA(),D23/(1+E23/100)) -> 32789 | G23: =D23-F23 -> 4885 | H23: =D23 -> 37674 | I23: =MAX(F23-D23,0) -> 0 | J23: =0 -> 0 | K23: =0 -> 0 | L23: =0 -> 0 | M23: =N23+G23 -> 83174 | N23: =M22 -> 78289 | O23: =MIN(N23,M23) -> 78289 | P23: =IF(G23>0,G23,0) -> 4885 | Q23: =IF(G23<0,-G23,0) -> 0 | R23: =IF(E23>0,E23,NA()) -> 14.898289 | S23: =IF(E23<0,E23,NA()) -> #N/A | V23: =H23/$T$12 -> 0.45295405 | W23: =IF(ISNA(H23),"",TEXT(H23,"#,##0")) -> 37,674 | X23: =I23/$T$12 -> 0 | Y23: =J23/$T$12 -> 0 | Z23: =IF(ISNA(J23),"",TEXT(J23,"#,##0")) -> 0 | AA23: =K23/$T$12 -> 0 | AB23: =IF(ISNA(K23),"",TEXT(K23,"#,##0")) -> 0 | AC23: =L23/$T$12 -> 0 | AD23: =IF(ISNA(L23),"",TEXT(L23,"#,##0")) -> 0 | AE23: =O23/$T$12 -> 0.9412677 | AF23: =P23/$T$12 -> 0.058732296 | AG23: =IF(ISNA(P23),"",TEXT(P23,"+#,##0")) -> +4,885 | AH23: =Q23/$T$12 -> 0 | AI23: =IF(ISNA(Q23),"",TEXT(Q23,"""-""#,##0")) -> -0 | AJ23: =E23/$U$12 -> 0.52669272 | AK23: =IF(ISNA(E23),"",TEXT(E23,"+0;-0")) -> +15 | AL23: =R23/$U$12 -> 0.52669272 | AM23: =S23/$U$12 -> #N/A
A24: AC | B24: total | C24: AC | D24: =SUM(D13:D23) -> 83174 | E24: 11.8 | F24: =0 -> 0 | G24: =D24-$D$12 -> 8750 | H24: =0 -> 0 | I24: =0 -> 0 | J24: =0 -> 0 | K24: =0 -> 0 | L24: =D24 -> 83174 | M24: =M23 -> 83174 | N24: =M24 -> 83174 | O24: =0 -> 0 | P24: =0 -> 0 | Q24: =0 -> 0 | R24: =IF(E24>0,E24,NA()) -> 11.8 | S24: =IF(E24<0,E24,NA()) -> #N/A | V24: =H24/$T$12 -> 0 | W24: =IF(ISNA(H24),"",TEXT(H24,"#,##0")) -> 0 | X24: =I24/$T$12 -> 0 | Y24: =J24/$T$12 -> 0 | Z24: =IF(ISNA(J24),"",TEXT(J24,"#,##0")) -> 0 | AA24: =K24/$T$12 -> 0 | AB24: =IF(ISNA(K24),"",TEXT(K24,"#,##0")) -> 0 | AC24: =L24/$T$12 -> 1 | AD24: =IF(ISNA(L24),"",TEXT(L24,"#,##0")) -> 83,174 | AE24: =O24/$T$12 -> 0 | AF24: =P24/$T$12 -> 0 | AG24: =IF(ISNA(P24),"",TEXT(P24,"+#,##0")) -> +0 | AH24: =Q24/$T$12 -> 0 | AI24: =IF(ISNA(Q24),"",TEXT(Q24,"""-""#,##0")) -> -0 | AJ24: =E24/$U$12 -> 0.41716026 | AK24: =IF(ISNA(E24),"",TEXT(E24,"+0;-0")) -> +12 | AL24: =R24/$U$12 -> 0.41716026 | AM24: =S24/$U$12 -> #N/A
A25: ΔPY | B25: variance | E25: 11.8 | F25: =0 -> 0 | G25: =$D$24-$D$12 -> 8750 | H25: =0 -> 0 | I25: =0 -> 0 | J25: =0 -> 0 | K25: =0 -> 0 | L25: =0 -> 0 | M25: =$D$24 -> 83174 | N25: =$D$12 -> 74424 | O25: =MIN($D$12,$D$24) -> 74424 | P25: =IF(G25>0,G25,0) -> 8750 | Q25: =IF(G25<0,-G25,0) -> 0 | R25: =NA() -> #N/A | S25: =NA() -> #N/A | V25: =H25/$T$12 -> 0 | W25: =IF(ISNA(H25),"",TEXT(H25,"#,##0")) -> 0 | X25: =I25/$T$12 -> 0 | Y25: =J25/$T$12 -> 0 | Z25: =IF(ISNA(J25),"",TEXT(J25,"#,##0")) -> 0 | AA25: =K25/$T$12 -> 0 | AB25: =IF(ISNA(K25),"",TEXT(K25,"#,##0")) -> 0 | AC25: =L25/$T$12 -> 0 | AD25: =IF(ISNA(L25),"",TEXT(L25,"#,##0")) -> 0 | AE25: =O25/$T$12 -> 0.89479886 | AF25: =P25/$T$12 -> 0.10520114 | AG25: =IF(ISNA(P25),"",TEXT(P25,"+#,##0")) -> +8,750 | AH25: =Q25/$T$12 -> 0 | AI25: =IF(ISNA(Q25),"",TEXT(Q25,"""-""#,##0")) -> -0 | AJ25: =E25/$U$12 -> 0.41716026 | AK25: =IF(ISNA(E25),"",TEXT(E25,"+0;-0")) -> +12 | AL25: =R25/$U$12 -> #N/A | AM25: =S25/$U$12 -> #N/A

Sheet C07C
A1: Entity | B1: The Progressive Corporation
A2: Measure | B2: Underwriting result
A3: Unit | B3: $m
A4: Period | B4: 2026
A5: Reference | B5: PL
A6: Message | B6: Through Jul the underwriting result is +4,557 $m against the 96 combined ratio target - a 13.1% margin where the target implies 4.0%. Holding that margin closes the year +7,967 $m ahead of target, and the moving annual total has stayed above 10,000 $m all year
A7: Subject | B7: =B2&IF(B3="",""," in "&B3) -> Underwriting result in $m
B9: Jan | C9: Feb | D9: Mar | E9: Apr | F9: May | G9: Jun | H9: Jul | I9: Aug | J9: Sep | K9: Oct | L9: Nov | M9: Dec
B10: AC | C10: AC | D10: AC | E10: AC | F10: AC | G10: AC | H10: AC | I10: FC | J10: FC | K10: FC | L10: FC | M10: FC
A11: PL month | B11: 277 | C11: 261 | D11: 301 | E11: 284 | F11: 294 | G11: 284 | H11: 294 | I11: 301 | J11: 292 | K11: 302 | L11: 295 | M11: 304
A12: AC month | B12: 1080 | C12: 934 | D12: 842 | E12: 697 | F12: 1318 | G12: 710 | H12: 971
A13: FC month | I13: 987 | J13: 958 | K13: 993 | L13: 967 | M13: 999
A14: PL cumulative | B14: =SUM(B11:B11) -> 277 | C14: =SUM(B11:C11) -> 538 | D14: =SUM(B11:D11) -> 839 | E14: =SUM(B11:E11) -> 1123 | F14: =SUM(B11:F11) -> 1417 | G14: =SUM(B11:G11) -> 1701 | H14: =SUM(B11:H11) -> 1995 | I14: =SUM(B11:I11) -> 2296 | J14: =SUM(B11:J11) -> 2588 | K14: =SUM(B11:K11) -> 2890 | L14: =SUM(B11:L11) -> 3185 | M14: =SUM(B11:M11) -> 3489
A15: AC cumulative | B15: =SUM(B12:B12) -> 1080 | C15: =SUM(B12:C12) -> 2014 | D15: =SUM(B12:D12) -> 2856 | E15: =SUM(B12:E12) -> 3553 | F15: =SUM(B12:F12) -> 4871 | G15: =SUM(B12:G12) -> 5581 | H15: =SUM(B12:H12) -> 6552
A16: FC cumulative | H16: =SUM(B12:H12)+SUM(B13:H13) -> 6552 | I16: =SUM(B12:I12)+SUM(B13:I13) -> 7539 | J16: =SUM(B12:J12)+SUM(B13:J13) -> 8497 | K16: =SUM(B12:K12)+SUM(B13:K13) -> 9490 | L16: =SUM(B12:L12)+SUM(B13:L13) -> 10457 | M16: =SUM(B12:M12)+SUM(B13:M13) -> 11456
A17: MAT | B17: 10288 | C17: 10172 | D17: 10396 | E17: 10090 | F17: 10529 | G17: 10307 | H17: 10251 | I17: 10049 | J17: 11034 | K17: 11298 | L17: 11376 | M17: 11456
A19: span | B19: =MAX(_xlfn.AGGREGATE(4,6,B11:M11,B12:M12,B13:M13,B14:M14,B15:M15,B16:M16,B17:M17),-_xlfn.AGGREGATE(5,6,B11:M11,B12:M12,B13:M13,B14:M14,B15:M15,B16:M16,B17:M17),0.000000001) -> 11456
A21: PL is not reported by the entity. The 96 combined ratio target is Progressive's own and is stated in every 10-K, so a 4.0% margin is filed. Applying it month by month to produce a plan is this workbook's construction, and the target is a floor the company aims to beat rather than a forecast of what it expects. Replace these cells with your own figures and every chart on this sheet follows.
A22: FC is not reported by the entity. Remaining months are the prior year's months at the year-to-date pace (+6.8%), earning the year-to-date margin (13.1%). Replace these cells with your own figures and every chart on this sheet follows.
A32: PL month scaled | B32: =IF(ISNA(B11),NA(),IF(ISBLANK(B11),NA(),B11/$B$19)) -> 0.024179469 | C32: =IF(ISNA(C11),NA(),IF(ISBLANK(C11),NA(),C11/$B$19)) -> 0.022782821 | D32: =IF(ISNA(D11),NA(),IF(ISBLANK(D11),NA(),D11/$B$19)) -> 0.026274441 | E32: =IF(ISNA(E11),NA(),IF(ISBLANK(E11),NA(),E11/$B$19)) -> 0.024790503 | F32: =IF(ISNA(F11),NA(),IF(ISBLANK(F11),NA(),F11/$B$19)) -> 0.025663408 | G32: =IF(ISNA(G11),NA(),IF(ISBLANK(G11),NA(),G11/$B$19)) -> 0.024790503 | H32: =IF(ISNA(H11),NA(),IF(ISBLANK(H11),NA(),H11/$B$19)) -> 0.025663408 | I32: =IF(ISNA(I11),NA(),IF(ISBLANK(I11),NA(),I11/$B$19)) -> 0.026274441 | ... M32: =IF(ISNA(M11),NA(),IF(ISBLANK(M11),NA(),M11/$B$19)) -> 0.026536313
A33: AC month scaled | B33: =IF(ISNA(B12),NA(),IF(ISBLANK(B12),NA(),B12/$B$19)) -> 0.094273743 | C33: =IF(ISNA(C12),NA(),IF(ISBLANK(C12),NA(),C12/$B$19)) -> 0.08152933 | D33: =IF(ISNA(D12),NA(),IF(ISBLANK(D12),NA(),D12/$B$19)) -> 0.073498603 | E33: =IF(ISNA(E12),NA(),IF(ISBLANK(E12),NA(),E12/$B$19)) -> 0.06084148 | F33: =IF(ISNA(F12),NA(),IF(ISBLANK(F12),NA(),F12/$B$19)) -> 0.11504888 | G33: =IF(ISNA(G12),NA(),IF(ISBLANK(G12),NA(),G12/$B$19)) -> 0.061976257 | H33: =IF(ISNA(H12),NA(),IF(ISBLANK(H12),NA(),H12/$B$19)) -> 0.084759078 | I33: =IF(ISNA(I12),NA(),IF(ISBLANK(I12),NA(),I12/$B$19)) -> #N/A | ... M33: =IF(ISNA(M12),NA(),IF(ISBLANK(M12),NA(),M12/$B$19)) -> #N/A
A34: FC month scaled | B34: =IF(ISNA(B13),NA(),IF(ISBLANK(B13),NA(),B13/$B$19)) -> #N/A | C34: =IF(ISNA(C13),NA(),IF(ISBLANK(C13),NA(),C13/$B$19)) -> #N/A | D34: =IF(ISNA(D13),NA(),IF(ISBLANK(D13),NA(),D13/$B$19)) -> #N/A | E34: =IF(ISNA(E13),NA(),IF(ISBLANK(E13),NA(),E13/$B$19)) -> #N/A | F34: =IF(ISNA(F13),NA(),IF(ISBLANK(F13),NA(),F13/$B$19)) -> #N/A | G34: =IF(ISNA(G13),NA(),IF(ISBLANK(G13),NA(),G13/$B$19)) -> #N/A | H34: =IF(ISNA(H13),NA(),IF(ISBLANK(H13),NA(),H13/$B$19)) -> #N/A | I34: =IF(ISNA(I13),NA(),IF(ISBLANK(I13),NA(),I13/$B$19)) -> 0.086155726 | ... M34: =IF(ISNA(M13),NA(),IF(ISBLANK(M13),NA(),M13/$B$19)) -> 0.087203212
A35: PL cumulative scaled | B35: =IF(ISNA(B14),NA(),IF(ISBLANK(B14),NA(),B14/$B$19)) -> 0.024179469 | C35: =IF(ISNA(C14),NA(),IF(ISBLANK(C14),NA(),C14/$B$19)) -> 0.046962291 | D35: =IF(ISNA(D14),NA(),IF(ISBLANK(D14),NA(),D14/$B$19)) -> 0.073236732 | E35: =IF(ISNA(E14),NA(),IF(ISBLANK(E14),NA(),E14/$B$19)) -> 0.098027235 | F35: =IF(ISNA(F14),NA(),IF(ISBLANK(F14),NA(),F14/$B$19)) -> 0.12369064 | G35: =IF(ISNA(G14),NA(),IF(ISBLANK(G14),NA(),G14/$B$19)) -> 0.14848115 | H35: =IF(ISNA(H14),NA(),IF(ISBLANK(H14),NA(),H14/$B$19)) -> 0.17414455 | I35: =IF(ISNA(I14),NA(),IF(ISBLANK(I14),NA(),I14/$B$19)) -> 0.20041899 | ... M35: =IF(ISNA(M14),NA(),IF(ISBLANK(M14),NA(),M14/$B$19)) -> 0.30455656
A36: AC cumulative scaled | B36: =IF(ISNA(B15),NA(),IF(ISBLANK(B15),NA(),B15/$B$19)) -> 0.094273743 | C36: =IF(ISNA(C15),NA(),IF(ISBLANK(C15),NA(),C15/$B$19)) -> 0.17580307 | D36: =IF(ISNA(D15),NA(),IF(ISBLANK(D15),NA(),D15/$B$19)) -> 0.24930168 | E36: =IF(ISNA(E15),NA(),IF(ISBLANK(E15),NA(),E15/$B$19)) -> 0.31014316 | F36: =IF(ISNA(F15),NA(),IF(ISBLANK(F15),NA(),F15/$B$19)) -> 0.42519204 | G36: =IF(ISNA(G15),NA(),IF(ISBLANK(G15),NA(),G15/$B$19)) -> 0.4871683 | H36: =IF(ISNA(H15),NA(),IF(ISBLANK(H15),NA(),H15/$B$19)) -> 0.57192737 | I36: =IF(ISNA(I15),NA(),IF(ISBLANK(I15),NA(),I15/$B$19)) -> #N/A | ... M36: =IF(ISNA(M15),NA(),IF(ISBLANK(M15),NA(),M15/$B$19)) -> #N/A
A37: FC cumulative scaled | B37: =IF(ISNA(B16),NA(),IF(ISBLANK(B16),NA(),B16/$B$19)) -> #N/A | C37: =IF(ISNA(C16),NA(),IF(ISBLANK(C16),NA(),C16/$B$19)) -> #N/A | D37: =IF(ISNA(D16),NA(),IF(ISBLANK(D16),NA(),D16/$B$19)) -> #N/A | E37: =IF(ISNA(E16),NA(),IF(ISBLANK(E16),NA(),E16/$B$19)) -> #N/A | F37: =IF(ISNA(F16),NA(),IF(ISBLANK(F16),NA(),F16/$B$19)) -> #N/A | G37: =IF(ISNA(G16),NA(),IF(ISBLANK(G16),NA(),G16/$B$19)) -> #N/A | H37: =IF(ISNA(H16),NA(),IF(ISBLANK(H16),NA(),H16/$B$19)) -> 0.57192737 | I37: =IF(ISNA(I16),NA(),IF(ISBLANK(I16),NA(),I16/$B$19)) -> 0.6580831 | ... M37: =IF(ISNA(M16),NA(),IF(ISBLANK(M16),NA(),M16/$B$19)) -> 1
A38: MAT scaled | B38: =IF(ISNA(B17),NA(),IF(ISBLANK(B17),NA(),B17/$B$19)) -> 0.89804469 | C38: =IF(ISNA(C17),NA(),IF(ISBLANK(C17),NA(),C17/$B$19)) -> 0.88791899 | D38: =IF(ISNA(D17),NA(),IF(ISBLANK(D17),NA(),D17/$B$19)) -> 0.90747207 | E38: =IF(ISNA(E17),NA(),IF(ISBLANK(E17),NA(),E17/$B$19)) -> 0.88076117 | F38: =IF(ISNA(F17),NA(),IF(ISBLANK(F17),NA(),F17/$B$19)) -> 0.9190817 | G38: =IF(ISNA(G17),NA(),IF(ISBLANK(G17),NA(),G17/$B$19)) -> 0.89970321 | H38: =IF(ISNA(H17),NA(),IF(ISBLANK(H17),NA(),H17/$B$19)) -> 0.89481494 | I38: =IF(ISNA(I17),NA(),IF(ISBLANK(I17),NA(),I17/$B$19)) -> 0.87718226 | ... M38: =IF(ISNA(M17),NA(),IF(ISBLANK(M17),NA(),M17/$B$19)) -> 1
A54: AC month text | B54: =IF(ISNA(B12),"",IF(ISBLANK(B12),"",TEXT(B12,"#,##0"))) -> 1,080 | C54: =IF(ISNA(C12),"",IF(ISBLANK(C12),"",TEXT(C12,"#,##0"))) -> 934 | D54: =IF(ISNA(D12),"",IF(ISBLANK(D12),"",TEXT(D12,"#,##0"))) -> 842 | E54: =IF(ISNA(E12),"",IF(ISBLANK(E12),"",TEXT(E12,"#,##0"))) -> 697 | F54: =IF(ISNA(F12),"",IF(ISBLANK(F12),"",TEXT(F12,"#,##0"))) -> 1,318 | G54: =IF(ISNA(G12),"",IF(ISBLANK(G12),"",TEXT(G12,"#,##0"))) -> 710 | H54: =IF(ISNA(H12),"",IF(ISBLANK(H12),"",TEXT(H12,"#,##0"))) -> 971 | I54: =IF(ISNA(I12),"",IF(ISBLANK(I12),"",TEXT(I12,"#,##0"))) | ... M54: =IF(ISNA(M12),"",IF(ISBLANK(M12),"",TEXT(M12,"#,##0")))
A55: FC month text | B55: =IF(ISNA(B13),"",IF(ISBLANK(B13),"",TEXT(B13,"#,##0"))) | C55: =IF(ISNA(C13),"",IF(ISBLANK(C13),"",TEXT(C13,"#,##0"))) | D55: =IF(ISNA(D13),"",IF(ISBLANK(D13),"",TEXT(D13,"#,##0"))) | E55: =IF(ISNA(E13),"",IF(ISBLANK(E13),"",TEXT(E13,"#,##0"))) | F55: =IF(ISNA(F13),"",IF(ISBLANK(F13),"",TEXT(F13,"#,##0"))) | G55: =IF(ISNA(G13),"",IF(ISBLANK(G13),"",TEXT(G13,"#,##0"))) | H55: =IF(ISNA(H13),"",IF(ISBLANK(H13),"",TEXT(H13,"#,##0"))) | I55: =IF(ISNA(I13),"",IF(ISBLANK(I13),"",TEXT(I13,"#,##0"))) -> 987 | ... M55: =IF(ISNA(M13),"",IF(ISBLANK(M13),"",TEXT(M13,"#,##0"))) -> 999
A56: PL cumulative text | B56: =IF(ISNA(B14),"",IF(ISBLANK(B14),"",TEXT(B14,"#,##0"))) -> 277 | C56: =IF(ISNA(C14),"",IF(ISBLANK(C14),"",TEXT(C14,"#,##0"))) -> 538 | D56: =IF(ISNA(D14),"",IF(ISBLANK(D14),"",TEXT(D14,"#,##0"))) -> 839 | E56: =IF(ISNA(E14),"",IF(ISBLANK(E14),"",TEXT(E14,"#,##0"))) -> 1,123 | F56: =IF(ISNA(F14),"",IF(ISBLANK(F14),"",TEXT(F14,"#,##0"))) -> 1,417 | G56: =IF(ISNA(G14),"",IF(ISBLANK(G14),"",TEXT(G14,"#,##0"))) -> 1,701 | H56: =IF(ISNA(H14),"",IF(ISBLANK(H14),"",TEXT(H14,"#,##0"))) -> 1,995 | I56: =IF(ISNA(I14),"",IF(ISBLANK(I14),"",TEXT(I14,"#,##0"))) -> 2,296 | ... M56: =IF(ISNA(M14),"",IF(ISBLANK(M14),"",TEXT(M14,"#,##0"))) -> 3,489
A57: AC cumulative text | B57: =IF(ISNA(B15),"",IF(ISBLANK(B15),"",TEXT(B15,"#,##0"))) -> 1,080 | C57: =IF(ISNA(C15),"",IF(ISBLANK(C15),"",TEXT(C15,"#,##0"))) -> 2,014 | D57: =IF(ISNA(D15),"",IF(ISBLANK(D15),"",TEXT(D15,"#,##0"))) -> 2,856 | E57: =IF(ISNA(E15),"",IF(ISBLANK(E15),"",TEXT(E15,"#,##0"))) -> 3,553 | F57: =IF(ISNA(F15),"",IF(ISBLANK(F15),"",TEXT(F15,"#,##0"))) -> 4,871 | G57: =IF(ISNA(G15),"",IF(ISBLANK(G15),"",TEXT(G15,"#,##0"))) -> 5,581 | H57: =IF(ISNA(H15),"",IF(ISBLANK(H15),"",TEXT(H15,"#,##0"))) -> 6,552 | I57: =IF(ISNA(I15),"",IF(ISBLANK(I15),"",TEXT(I15,"#,##0"))) | ... M57: =IF(ISNA(M15),"",IF(ISBLANK(M15),"",TEXT(M15,"#,##0")))
A58: FC cumulative text | B58: =IF(ISNA(B16),"",IF(ISBLANK(B16),"",TEXT(B16,"#,##0"))) | C58: =IF(ISNA(C16),"",IF(ISBLANK(C16),"",TEXT(C16,"#,##0"))) | D58: =IF(ISNA(D16),"",IF(ISBLANK(D16),"",TEXT(D16,"#,##0"))) | E58: =IF(ISNA(E16),"",IF(ISBLANK(E16),"",TEXT(E16,"#,##0"))) | F58: =IF(ISNA(F16),"",IF(ISBLANK(F16),"",TEXT(F16,"#,##0"))) | G58: =IF(ISNA(G16),"",IF(ISBLANK(G16),"",TEXT(G16,"#,##0"))) | H58: =IF(ISNA(H16),"",IF(ISBLANK(H16),"",TEXT(H16,"#,##0"))) -> 6,552 | I58: =IF(ISNA(I16),"",IF(ISBLANK(I16),"",TEXT(I16,"#,##0"))) -> 7,539 | ... M58: =IF(ISNA(M16),"",IF(ISBLANK(M16),"",TEXT(M16,"#,##0"))) -> 11,456
A59: MAT text | B59: =IF(ISNA(B17),"",IF(ISBLANK(B17),"",TEXT(B17,"#,##0"))) -> 10,288 | C59: =IF(ISNA(C17),"",IF(ISBLANK(C17),"",TEXT(C17,"#,##0"))) -> 10,172 | D59: =IF(ISNA(D17),"",IF(ISBLANK(D17),"",TEXT(D17,"#,##0"))) -> 10,396 | E59: =IF(ISNA(E17),"",IF(ISBLANK(E17),"",TEXT(E17,"#,##0"))) -> 10,090 | F59: =IF(ISNA(F17),"",IF(ISBLANK(F17),"",TEXT(F17,"#,##0"))) -> 10,529 | G59: =IF(ISNA(G17),"",IF(ISBLANK(G17),"",TEXT(G17,"#,##0"))) -> 10,307 | H59: =IF(ISNA(H17),"",IF(ISBLANK(H17),"",TEXT(H17,"#,##0"))) -> 10,251 | I59: =IF(ISNA(I17),"",IF(ISBLANK(I17),"",TEXT(I17,"#,##0"))) -> 10,049 | ... M59: =IF(ISNA(M17),"",IF(ISBLANK(M17),"",TEXT(M17,"#,##0"))) -> 11,456

Sheet C08H
A1: Entity | B1: The Progressive Corporation
A2: Measure | B2: Loss and loss adjustment expense reserves, net
A3: Unit | B3: $m
A4: Period | B4: 2024..2028
A5: Reference | B5: PL
A6: Message | B6: Reserves built +12,301 $m over 10 quarters - losses incurred ran ahead of claims paid in 10 of them. Progressive is running a 66.2 loss ratio where its 96 combined ratio target implies 71.9, so holding the target builds reserves faster rather than slower: 56,535 $m by end 2028
A7: Subject | B7: =B2&IF(B3="",""," in "&B3) -> Loss and loss adjustment expense reserves, net in $m
B9: Q1 | C9: Q2 | D9: Q3 | E9: Q4 | F9: Q1 | G9: Q2 | H9: Q3 | I9: Q4 | J9: Q1 | K9: Q2 | L9: Q3 | M9: Q4 | N9: Q1 | O9: Q2 | P9: Q3 | Q9: Q4 | R9: Q1 | S9: Q2 | T9: Q3 | U9: Q4
B10: 2024 | C10: 2024 | D10: 2024 | E10: 2024 | F10: 2025 | G10: 2025 | H10: 2025 | I10: 2025 | J10: 2026 | K10: 2026 | L10: 2026 | M10: 2026 | N10: 2027 | O10: 2027 | P10: 2027 | Q10: 2027 | R10: 2028 | S10: 2028 | T10: 2028 | U10: 2028
B11: AC | C11: AC | D11: AC | E11: AC | F11: AC | G11: AC | H11: AC | I11: AC | J11: AC | K11: AC | L11: FC | M11: FC | N11: PL | O11: PL | P11: PL | Q11: PL | R11: PL | S11: PL | T11: PL | U11: PL
A12: Increase | B12: 10972 | C12: 12595 | D12: 12510 | E12: 12983 | F12: 12804 | G12: 13605 | H12: 13445 | I12: 14105 | J12: 13827 | K12: 14572 | L12: 15876 | M12: 16240 | N12: 16612 | O12: 16993 | P12: 17382 | Q12: 17781 | R12: 18188 | S12: 18605 | T12: 19032 | U12: 19468
A13: Decrease | B13: 10393 | C13: 10684 | D13: 11084 | E13: 11929 | F13: 11685 | G13: 12040 | H13: 12407 | I13: 12894 | J13: 12701 | K13: 13300 | L13: 14557 | M13: 14891 | N13: 15232 | O13: 15582 | P13: 15938 | Q13: 16304 | R13: 16677 | S13: 17060 | T13: 17451 | U13: 17851
A14: Inventory change | B14: =B12-B13 -> 579 | C14: =C12-C13 -> 1911 | D14: =D12-D13 -> 1426 | E14: =E12-E13 -> 1054 | F14: =F12-F13 -> 1119 | G14: =G12-G13 -> 1565 | H14: =H12-H13 -> 1038 | I14: =I12-I13 -> 1211 | ... U14: =U12-U13 -> 1617
A15: 29600 | B15: =$A$15+SUM(B14:B14) -> 30179 | C15: =$A$15+SUM(B14:C14) -> 32090 | D15: =$A$15+SUM(B14:D14) -> 33516 | E15: =$A$15+SUM(B14:E14) -> 34570 | F15: =$A$15+SUM(B14:F14) -> 35689 | G15: =$A$15+SUM(B14:G14) -> 37254 | H15: =$A$15+SUM(B14:H14) -> 38292 | I15: =$A$15+SUM(B14:I14) -> 39503 | J15: =$A$15+SUM(B14:J14) -> 40629 | K15: =$A$15+SUM(B14:K14) -> 41901 | L15: =$A$15+SUM(B14:L14) -> 43220 | M15: =$A$15+SUM(B14:M14) -> 44569 | N15: =$A$15+SUM(B14:N14) -> 45949 | O15: =$A$15+SUM(B14:O14) -> 47360 | P15: =$A$15+SUM(B14:P14) -> 48804 | Q15: =$A$15+SUM(B14:Q14) -> 50281 | R15: =$A$15+SUM(B14:R14) -> 51792 | S15: =$A$15+SUM(B14:S14) -> 53337 | T15: =$A$15+SUM(B14:T14) -> 54918 | U15: =$A$15+SUM(B14:U14) -> 56535
A16: Inventory AC | B16: =B15 -> 30179 | C16: =C15 -> 32090 | D16: =D15 -> 33516 | E16: =E15 -> 34570 | F16: =F15 -> 35689 | G16: =G15 -> 37254 | H16: =H15 -> 38292 | I16: =I15 -> 39503 | ... L16: =L15 -> 43220 | M16: =NA() -> #N/A | N16: =NA() -> #N/A | O16: =NA() -> #N/A | P16: =NA() -> #N/A | Q16: =NA() -> #N/A | R16: =NA() -> #N/A | S16: =NA() -> #N/A | T16: =NA() -> #N/A | U16: =NA() -> #N/A
A17: Inventory FC | B17: =NA() -> #N/A | C17: =NA() -> #N/A | D17: =NA() -> #N/A | E17: =NA() -> #N/A | F17: =NA() -> #N/A | G17: =NA() -> #N/A | H17: =NA() -> #N/A | I17: =NA() -> #N/A | ... K17: =NA() -> #N/A | L17: =L15 -> 43220 | M17: =M15 -> 44569 | N17: =N15 -> 45949 | O17: =NA() -> #N/A | P17: =NA() -> #N/A | Q17: =NA() -> #N/A | R17: =NA() -> #N/A | S17: =NA() -> #N/A | T17: =NA() -> #N/A | U17: =NA() -> #N/A
A18: Inventory PL | B18: =NA() -> #N/A | C18: =NA() -> #N/A | D18: =NA() -> #N/A | E18: =NA() -> #N/A | F18: =NA() -> #N/A | G18: =NA() -> #N/A | H18: =NA() -> #N/A | I18: =NA() -> #N/A | ... M18: =NA() -> #N/A | N18: =N15 -> 45949 | O18: =O15 -> 47360 | P18: =P15 -> 48804 | Q18: =Q15 -> 50281 | R18: =R15 -> 51792 | S18: =S15 -> 53337 | T18: =T15 -> 54918 | U18: =U15 -> 56535
A19: Decrease (drawn) | B19: =-B13 -> -10393 | C19: =-C13 -> -10684 | D19: =-D13 -> -11084 | E19: =-E13 -> -11929 | F19: =-F13 -> -11685 | G19: =-G13 -> -12040 | H19: =-H13 -> -12407 | I19: =-I13 -> -12894 | ... U19: =-U13 -> -17851
A21: span | B21: =MAX(_xlfn.AGGREGATE(4,6,B16:U16,B17:U17,B18:U18,B12:U12,B19:U19),-_xlfn.AGGREGATE(5,6,B16:U16,B17:U17,B18:U18,B12:U12,B19:U19),0.000000001) -> 56535
A23: FC is not reported by the entity. Progressive publishes no forecast. Earned premium continues the trailing four quarters' growth (+9.5% a year); losses incurred are that premium at 71.9%, the loss ratio a 96 combined ratio implies after the trailing 24.1% expense ratio; claims paid are 91.7% of losses incurred, the trailing rate. Replace these cells with your own figures and every chart on this sheet follows.
A24: PL is not reported by the entity. The same three rules carried through the two plan years. The 96 combined ratio target is Progressive's own and is filed; applying it to a future quarter is this workbook's construction. Replace these cells with your own figures and every chart on this sheet follows.
A35: Increase scaled | B35: =IF(ISNA(B12),NA(),IF(ISBLANK(B12),NA(),B12/$B$21)) -> 0.19407447 | C35: =IF(ISNA(C12),NA(),IF(ISBLANK(C12),NA(),C12/$B$21)) -> 0.22278235 | D35: =IF(ISNA(D12),NA(),IF(ISBLANK(D12),NA(),D12/$B$21)) -> 0.22127885 | E35: =IF(ISNA(E12),NA(),IF(ISBLANK(E12),NA(),E12/$B$21)) -> 0.22964535 | F35: =IF(ISNA(F12),NA(),IF(ISBLANK(F12),NA(),F12/$B$21)) -> 0.22647917 | G35: =IF(ISNA(G12),NA(),IF(ISBLANK(G12),NA(),G12/$B$21)) -> 0.24064739 | H35: =IF(ISNA(H12),NA(),IF(ISBLANK(H12),NA(),H12/$B$21)) -> 0.23781728 | I35: =IF(ISNA(I12),NA(),IF(ISBLANK(I12),NA(),I12/$B$21)) -> 0.24949147 | ... U35: =IF(ISNA(U12),NA(),IF(ISBLANK(U12),NA(),U12/$B$21)) -> 0.34435306
A39: level AC scaled | B39: =IF(ISNA(B16),NA(),IF(ISBLANK(B16),NA(),B16/$B$21)) -> 0.53381091 | C39: =IF(ISNA(C16),NA(),IF(ISBLANK(C16),NA(),C16/$B$21)) -> 0.56761298 | D39: =IF(ISNA(D16),NA(),IF(ISBLANK(D16),NA(),D16/$B$21)) -> 0.5928363 | E39: =IF(ISNA(E16),NA(),IF(ISBLANK(E16),NA(),E16/$B$21)) -> 0.61147961 | F39: =IF(ISNA(F16),NA(),IF(ISBLANK(F16),NA(),F16/$B$21)) -> 0.63127266 | G39: =IF(ISNA(G16),NA(),IF(ISBLANK(G16),NA(),G16/$B$21)) -> 0.65895463 | H39: =IF(ISNA(H16),NA(),IF(ISBLANK(H16),NA(),H16/$B$21)) -> 0.67731494 | I39: =IF(ISNA(I16),NA(),IF(ISBLANK(I16),NA(),I16/$B$21)) -> 0.6987353 | ... U39: =IF(ISNA(U16),NA(),IF(ISBLANK(U16),NA(),U16/$B$21)) -> #N/A
A40: level FC scaled | B40: =IF(ISNA(B17),NA(),IF(ISBLANK(B17),NA(),B17/$B$21)) -> #N/A | C40: =IF(ISNA(C17),NA(),IF(ISBLANK(C17),NA(),C17/$B$21)) -> #N/A | D40: =IF(ISNA(D17),NA(),IF(ISBLANK(D17),NA(),D17/$B$21)) -> #N/A | E40: =IF(ISNA(E17),NA(),IF(ISBLANK(E17),NA(),E17/$B$21)) -> #N/A | F40: =IF(ISNA(F17),NA(),IF(ISBLANK(F17),NA(),F17/$B$21)) -> #N/A | G40: =IF(ISNA(G17),NA(),IF(ISBLANK(G17),NA(),G17/$B$21)) -> #N/A | H40: =IF(ISNA(H17),NA(),IF(ISBLANK(H17),NA(),H17/$B$21)) -> #N/A | I40: =IF(ISNA(I17),NA(),IF(ISBLANK(I17),NA(),I17/$B$21)) -> #N/A | ... U40: =IF(ISNA(U17),NA(),IF(ISBLANK(U17),NA(),U17/$B$21)) -> #N/A
A41: level PL scaled | B41: =IF(ISNA(B18),NA(),IF(ISBLANK(B18),NA(),B18/$B$21)) -> #N/A | C41: =IF(ISNA(C18),NA(),IF(ISBLANK(C18),NA(),C18/$B$21)) -> #N/A | D41: =IF(ISNA(D18),NA(),IF(ISBLANK(D18),NA(),D18/$B$21)) -> #N/A | E41: =IF(ISNA(E18),NA(),IF(ISBLANK(E18),NA(),E18/$B$21)) -> #N/A | F41: =IF(ISNA(F18),NA(),IF(ISBLANK(F18),NA(),F18/$B$21)) -> #N/A | G41: =IF(ISNA(G18),NA(),IF(ISBLANK(G18),NA(),G18/$B$21)) -> #N/A | H41: =IF(ISNA(H18),NA(),IF(ISBLANK(H18),NA(),H18/$B$21)) -> #N/A | I41: =IF(ISNA(I18),NA(),IF(ISBLANK(I18),NA(),I18/$B$21)) -> #N/A | ... U41: =IF(ISNA(U18),NA(),IF(ISBLANK(U18),NA(),U18/$B$21)) -> 1
A42: Decrease drawn scaled | B42: =IF(ISNA(B19),NA(),IF(ISBLANK(B19),NA(),B19/$B$21)) -> -0.18383302 | C42: =IF(ISNA(C19),NA(),IF(ISBLANK(C19),NA(),C19/$B$21)) -> -0.18898028 | D42: =IF(ISNA(D19),NA(),IF(ISBLANK(D19),NA(),D19/$B$21)) -> -0.19605554 | E42: =IF(ISNA(E19),NA(),IF(ISBLANK(E19),NA(),E19/$B$21)) -> -0.21100203 | F42: =IF(ISNA(F19),NA(),IF(ISBLANK(F19),NA(),F19/$B$21)) -> -0.20668612 | G42: =IF(ISNA(G19),NA(),IF(ISBLANK(G19),NA(),G19/$B$21)) -> -0.21296542 | H42: =IF(ISNA(H19),NA(),IF(ISBLANK(H19),NA(),H19/$B$21)) -> -0.21945697 | I42: =IF(ISNA(I19),NA(),IF(ISBLANK(I19),NA(),I19/$B$21)) -> -0.22807111 | ... U42: =IF(ISNA(U19),NA(),IF(ISBLANK(U19),NA(),U19/$B$21)) -> -0.3157513
A58: Increase text | B58: =IF(ISNA(B12),"",IF(ISBLANK(B12),"",TEXT(B12,"0"))) -> 10972 | C58: =IF(ISNA(C12),"",IF(ISBLANK(C12),"",TEXT(C12,"0"))) -> 12595 | D58: =IF(ISNA(D12),"",IF(ISBLANK(D12),"",TEXT(D12,"0"))) -> 12510 | E58: =IF(ISNA(E12),"",IF(ISBLANK(E12),"",TEXT(E12,"0"))) -> 12983 | F58: =IF(ISNA(F12),"",IF(ISBLANK(F12),"",TEXT(F12,"0"))) -> 12804 | G58: =IF(ISNA(G12),"",IF(ISBLANK(G12),"",TEXT(G12,"0"))) -> 13605 | H58: =IF(ISNA(H12),"",IF(ISBLANK(H12),"",TEXT(H12,"0"))) -> 13445 | I58: =IF(ISNA(I12),"",IF(ISBLANK(I12),"",TEXT(I12,"0"))) -> 14105 | ... U58: =IF(ISNA(U12),"",IF(ISBLANK(U12),"",TEXT(U12,"0"))) -> 19468
A65: Decrease drawn text | B65: =IF(ISNA(B19),"",IF(ISBLANK(B19),"",TEXT(B19,"0"))) -> -10393 | C65: =IF(ISNA(C19),"",IF(ISBLANK(C19),"",TEXT(C19,"0"))) -> -10684 | D65: =IF(ISNA(D19),"",IF(ISBLANK(D19),"",TEXT(D19,"0"))) -> -11084 | E65: =IF(ISNA(E19),"",IF(ISBLANK(E19),"",TEXT(E19,"0"))) -> -11929 | F65: =IF(ISNA(F19),"",IF(ISBLANK(F19),"",TEXT(F19,"0"))) -> -11685 | G65: =IF(ISNA(G19),"",IF(ISBLANK(G19),"",TEXT(G19,"0"))) -> -12040 | H65: =IF(ISNA(H19),"",IF(ISBLANK(H19),"",TEXT(H19,"0"))) -> -12407 | I65: =IF(ISNA(I19),"",IF(ISBLANK(I19),"",TEXT(I19,"0"))) -> -12894 | ... U65: =IF(ISNA(U19),"",IF(ISBLANK(U19),"",TEXT(U19,"0"))) -> -17851

Sheet C09C
A1: Entity | B1: The Progressive Corporation
A2: Measure | B2: Net premiums earned
A3: Unit | B3: $m, margin in %
A4: Period | B4: 2024..2025
A5: Reference | B5: PY
A6: Message | B6: 17 of Agency auto's 23 months earned an underwriting result of 300 $m or more; the curves are constant result, so a point's distance beyond one is what its premium and its margin achieved together
A7: Subject | B7: =B2&IF(B3="",""," in "&B3) -> Net premiums earned in $m, margin in %
A10: Agency auto | B10: Underwriting margin in % of earned premium
B11: 14.8 | C11: 1958.7 | D11: Agency auto | E11: =C11*B11/100 -> 289.8876
B12: 15.5 | C12: 1864.1 | D12: Agency auto | E12: =C12*B12/100 -> 288.9355
B13: 18.3 | C13: 2034.9 | D13: Agency auto | E13: =C13*B13/100 -> 372.3867
B14: 14 | C14: 2008.8 | D14: Agency auto | E14: =C14*B14/100 -> 281.232
B15: 8 | C15: 2116.6 | D15: Agency auto | E15: =C15*B15/100 -> 169.328
B16: 16.1 | C16: 2088 | D16: Agency auto | E16: =C16*B16/100 -> 336.168
B17: 14.4 | C17: 2194.4 | D17: Agency auto | E17: =C17*B17/100 -> 315.9936
B18: 17.2 | C18: 2159.8 | D18: Agency auto | E18: =C18*B18/100 -> 371.4856
B19: 8 | C19: 2273.6 | D19: Agency auto | E19: =C19*B19/100 -> 181.888
B20: 7.3 | C20: 2305.2 | D20: Agency auto | E20: =C20*B20/100 -> 168.2796
B21: 16.7 | C21: 2191.1 | D21: Agency auto | E21: =C21*B21/100 -> 365.9137
B22: 17 | C22: 2445 | D22: Agency auto | E22: =C22*B22/100 -> 415.65
... B33: 12.4 | C33: 2559 | D33: Agency auto | E33: =C33*B33/100 -> 317.316
A34: Direct auto
B35: 13.5 | C35: 2327.7 | D35: Direct auto | E35: =C35*B35/100 -> 314.2395
B36: 13.7 | C36: 2231.5 | D36: Direct auto | E36: =C36*B36/100 -> 305.7155
B37: 17.2 | C37: 2461.3 | D37: Direct auto | E37: =C37*B37/100 -> 423.3436
B38: 10.7 | C38: 2446.1 | D38: Direct auto | E38: =C38*B38/100 -> 261.7327
B39: 7.3 | C39: 2588.4 | D39: Direct auto | E39: =C39*B39/100 -> 188.9532
B40: 13 | C40: 2561 | D40: Direct auto | E40: =C40*B40/100 -> 332.93
B41: 9.7 | C41: 2701 | D41: Direct auto | E41: =C41*B41/100 -> 261.997
B42: 9.3 | C42: 2664 | D42: Direct auto | E42: =C42*B42/100 -> 247.752
B43: 5.5 | C43: 2815.2 | D43: Direct auto | E43: =C43*B43/100 -> 154.836
B44: 4.3 | C44: 2867.4 | D44: Direct auto | E44: =C44*B44/100 -> 123.2982
B45: 9.8 | C45: 2731.4 | D45: Direct auto | E45: =C45*B45/100 -> 267.6772
B46: 11.5 | C46: 3063 | D46: Direct auto | E46: =C46*B46/100 -> 352.245
... B57: 8.8 | C57: 3425 | D57: Direct auto | E57: =C57*B57/100 -> 301.4
A58: Commercial
B59: 11.4 | C59: 860.5 | D59: Commercial | E59: =C59*B59/100 -> 98.097
B60: 4 | C60: 807.6 | D60: Commercial | E60: =C60*B60/100 -> 32.304
B61: 8.9 | C61: 889.3 | D61: Commercial | E61: =C61*B61/100 -> 79.1477
B62: 12.5 | C62: 876.1 | D62: Commercial | E62: =C62*B62/100 -> 109.5125
B63: 7.7 | C63: 904.9 | D63: Commercial | E63: =C63*B63/100 -> 69.6773
B64: 14 | C64: 883.5 | D64: Commercial | E64: =C64*B64/100 -> 123.69
B65: 10.1 | C65: 910.1 | D65: Commercial | E65: =C65*B65/100 -> 91.9201
B66: 9.1 | C66: 889.6 | D66: Commercial | E66: =C66*B66/100 -> 80.9536
B67: 14.7 | C67: 927 | D67: Commercial | E67: =C67*B67/100 -> 136.269
B68: 3.1 | C68: 939.8 | D68: Commercial | E68: =C68*B68/100 -> 29.1338
B69: 15.5 | C69: 866.3 | D69: Commercial | E69: =C69*B69/100 -> 134.2765
B70: 15.9 | C70: 952 | D70: Commercial | E70: =C70*B70/100 -> 151.368
... B81: 23.9 | C81: 888 | D81: Commercial | E81: =C81*B81/100 -> 212.232
A83: Agency auto at 300 mUSD or more | E83: =SUMPRODUCT((D11:D81="Agency auto")*(E11:E81>=300)) -> 17
A84: stated in the message | E84: 17
A86: Iso gross profit | B86: Margin | C86: 100 | D86: 200 | E86: 300
B87: 8.5714286 | C87: =IF(100*100/$B87>3500,NA(),100*100/$B87) -> 1166.6667 | D87: =IF(200*100/$B87>3500,NA(),200*100/$B87) -> 2333.3333 | E87: =IF(300*100/$B87>3500,NA(),300*100/$B87) -> 3500
B88: 8.8498789 | C88: =IF(100*100/$B88>3500,NA(),100*100/$B88) -> 1129.959 | D88: =IF(200*100/$B88>3500,NA(),200*100/$B88) -> 2259.9179 | E88: =IF(300*100/$B88>3500,NA(),300*100/$B88) -> 3389.8769
B89: 9.1283293 | C89: =IF(100*100/$B89>3500,NA(),100*100/$B89) -> 1095.4907 | D89: =IF(200*100/$B89>3500,NA(),200*100/$B89) -> 2190.9814 | E89: =IF(300*100/$B89>3500,NA(),300*100/$B89) -> 3286.4721
B90: 9.4067797 | C90: =IF(100*100/$B90>3500,NA(),100*100/$B90) -> 1063.0631 | D90: =IF(200*100/$B90>3500,NA(),200*100/$B90) -> 2126.1261 | E90: =IF(300*100/$B90>3500,NA(),300*100/$B90) -> 3189.1892
B91: 9.68523 | C91: =IF(100*100/$B91>3500,NA(),100*100/$B91) -> 1032.5 | D91: =IF(200*100/$B91>3500,NA(),200*100/$B91) -> 2065 | E91: =IF(300*100/$B91>3500,NA(),300*100/$B91) -> 3097.5
B92: 9.9636804 | C92: =IF(100*100/$B92>3500,NA(),100*100/$B92) -> 1003.6452 | D92: =IF(200*100/$B92>3500,NA(),200*100/$B92) -> 2007.2904 | E92: =IF(300*100/$B92>3500,NA(),300*100/$B92) -> 3010.9356
B93: 10.242131 | C93: =IF(100*100/$B93>3500,NA(),100*100/$B93) -> 976.35934 | D93: =IF(200*100/$B93>3500,NA(),200*100/$B93) -> 1952.7187 | E93: =IF(300*100/$B93>3500,NA(),300*100/$B93) -> 2929.078
B94: 10.520581 | C94: =IF(100*100/$B94>3500,NA(),100*100/$B94) -> 950.51784 | D94: =IF(200*100/$B94>3500,NA(),200*100/$B94) -> 1901.0357 | E94: =IF(300*100/$B94>3500,NA(),300*100/$B94) -> 2851.5535
B95: 10.799031 | C95: =IF(100*100/$B95>3500,NA(),100*100/$B95) -> 926.00897 | D95: =IF(200*100/$B95>3500,NA(),200*100/$B95) -> 1852.0179 | E95: =IF(300*100/$B95>3500,NA(),300*100/$B95) -> 2778.0269
B96: 11.077482 | C96: =IF(100*100/$B96>3500,NA(),100*100/$B96) -> 902.73224 | D96: =IF(200*100/$B96>3500,NA(),200*100/$B96) -> 1805.4645 | E96: =IF(300*100/$B96>3500,NA(),300*100/$B96) -> 2708.1967
B97: 11.355932 | C97: =IF(100*100/$B97>3500,NA(),100*100/$B97) -> 880.59701 | D97: =IF(200*100/$B97>3500,NA(),200*100/$B97) -> 1761.194 | E97: =IF(300*100/$B97>3500,NA(),300*100/$B97) -> 2641.791
B98: 11.634383 | C98: =IF(100*100/$B98>3500,NA(),100*100/$B98) -> 859.52133 | D98: =IF(200*100/$B98>3500,NA(),200*100/$B98) -> 1719.0427 | E98: =IF(300*100/$B98>3500,NA(),300*100/$B98) -> 2578.564
... B146: 25 | C146: =IF(100*100/$B146>3500,NA(),100*100/$B146) -> 400 | D146: =IF(200*100/$B146>3500,NA(),200*100/$B146) -> 800 | E146: =IF(300*100/$B146>3500,NA(),300*100/$B146) -> 1200

Sheet C10D
A1: Entity | B1: The Progressive Corporation
A2: Measure | B2: Underwriting performance by segment
A3: Unit
A4: Period | B4: 2016
A5: Reference | B5: PY
A6: Message | B6: Property carries the highest combined ratio at 96.2 despite the lowest loss ratio in the group at 63.2; its expense ratio of 33.0 is 14 points above the leanest segment
A7: Subject | B7: =B2&IF(B3="",""," in "&B3) -> Underwriting performance by segment
A8: Size | B8: Net premiums earned | C8: $m
A10: PY | B10: Expense ratio in % | C10: Loss and LAE ratio in % | D10: Scenario | E10: =B8&" in "&C8 -> Net premiums earned in $m
A11: Agency auto | B11: 19.6 | C11: 72.6 | D11: PY | E11: 9108.6
A12: Direct auto | B12: 20.1 | C12: 75 | D12: PY | E12: 8185.9
A13: Commercial | B13: 21.7 | C13: 62.4 | D13: PY | E13: 1995.9
A14: AC
A15: Agency auto | B15: 19.7 | C15: 75.3 | D15: AC | E15: 9791.7
A16: Direct auto | B16: 18.8 | C16: 76.8 | D16: AC | E16: 9396.5
A17: Commercial | B17: 21.7 | C17: 71.9 | D17: AC | E17: 2421.3
A18: ACQ
A19: Property | B19: 33.02 | C19: 63.2 | D19: ACQ | E19: 864.5

Sheet C11A
A1: Entity | B1: The Progressive Corporation
A2: Measure | B2: Return on equity
A3: Unit | B3: %
A4: Period | B4: 2019..2025
A5: Reference | B5: PL
A6: Message | B6: Return on equity moved from 24.1% to 33.9% between 2019 and 2025, and the tree says which half did it: premium to equity barely moved (2.65 to 2.69) while the underwriting margin went from 9.1% to 12.6%
A7: Subject | B7: =B2&IF(B3="",""," in "&B3) -> Return on equity in %
A9: Year | B9: 2019 | C9: 2020 | D9: 2021 | E9: 2022 | F9: 2023 | G9: 2024 | H9: 2025
A10: Scenario | B10: AC | C10: AC | D10: AC | E10: AC | F10: AC | G10: AC | H10: AC
A11: Axis scenario | B11: =B10 -> AC | C11: =IF(C10=B10,"",C10) | D11: =IF(D10=C10,"",D10) | E11: =IF(E10=D10,"",E10) | F11: =IF(F10=E10,"",F10) | G11: =IF(G10=F10,"",G10) | H11: =IF(H10=G10,"",H10)
A12: Axis year | B12: =B9 -> 2019 | C12: ="" | D12: ="" | E12: ="" | F12: ="" | G12: ="" | H12: =H9 -> 2025
A13: Underwriting result | B13: 3294 | C13: 4829 | D13: 2085 | E13: 2068 | F13: 2992 | G13: 7929 | H13: 10289
A14: Net premiums earned | B14: 36192 | C14: 39262 | D14: 44369 | E14: 49241 | F14: 58664 | G14: 70799 | H14: 81661
A15: Shareholders' equity | B15: 13673 | C15: 17039 | D15: 18232 | E15: 15891 | F15: 20277 | G15: 25591 | H15: 30323
A16: Underwriting margin | B16: =B13/B14*100 -> 9.1014589 | C16: =C13/C14*100 -> 12.299424 | D16: =D13/D14*100 -> 4.6992269 | E16: =E13/E14*100 -> 4.1997522 | F16: =F13/F14*100 -> 5.1002318 | G16: =G13/G14*100 -> 11.199311 | H16: =H13/H14*100 -> 12.59965
A17: Premium to equity | B17: =B14/B15 -> 2.6469685 | C17: =C14/C15 -> 2.3042432 | D17: =D14/D15 -> 2.4335783 | E17: =E14/E15 -> 3.0986722 | F17: =F14/F15 -> 2.8931301 | G17: =G14/G15 -> 2.7665586 | H17: =H14/H15 -> 2.6930383
A18: Return on equity | B18: =B13/B15*100 -> 24.091275 | C18: =C13/C15*100 -> 28.340865 | D18: =D13/D15*100 -> 11.435937 | E18: =E13/E15*100 -> 13.013656 | F18: =F13/F15*100 -> 14.755634 | G18: =G13/G15*100 -> 30.983549 | H18: =H13/H15*100 -> 33.931339
A20: span percent | B20: =MAX(_xlfn.AGGREGATE(4,6,B18:H18,B16:H16),-_xlfn.AGGREGATE(5,6,B18:H18,B16:H16),0.000000001) -> 33.931339
A21: span turnover | B21: =MAX(_xlfn.AGGREGATE(4,6,B17:H17),-_xlfn.AGGREGATE(5,6,B17:H17),0.000000001) -> 3.0986722
A22: span kEUR | B22: =MAX(_xlfn.AGGREGATE(4,6,B13:H13,B14:H14,B15:H15),-_xlfn.AGGREGATE(5,6,B13:H13,B14:H14,B15:H15),0.000000001) -> 81661
A35: return scaled | B35: =IF(ISNA(B13),NA(),IF(ISBLANK(B13),NA(),B13/$B$22)) -> 0.040337493 | C35: =IF(ISNA(C13),NA(),IF(ISBLANK(C13),NA(),C13/$B$22)) -> 0.059134715 | D35: =IF(ISNA(D13),NA(),IF(ISBLANK(D13),NA(),D13/$B$22)) -> 0.025532384 | E35: =IF(ISNA(E13),NA(),IF(ISBLANK(E13),NA(),E13/$B$22)) -> 0.025324206 | F35: =IF(ISNA(F13),NA(),IF(ISBLANK(F13),NA(),F13/$B$22)) -> 0.036639277 | G35: =IF(ISNA(G13),NA(),IF(ISBLANK(G13),NA(),G13/$B$22)) -> 0.097096533 | H35: =IF(ISNA(H13),NA(),IF(ISBLANK(H13),NA(),H13/$B$22)) -> 0.1259965
A36: net_sales scaled | B36: =IF(ISNA(B14),NA(),IF(ISBLANK(B14),NA(),B14/$B$22)) -> 0.4431981 | C36: =IF(ISNA(C14),NA(),IF(ISBLANK(C14),NA(),C14/$B$22)) -> 0.48079254 | D36: =IF(ISNA(D14),NA(),IF(ISBLANK(D14),NA(),D14/$B$22)) -> 0.54333158 | E36: =IF(ISNA(E14),NA(),IF(ISBLANK(E14),NA(),E14/$B$22)) -> 0.60299286 | F36: =IF(ISNA(F14),NA(),IF(ISBLANK(F14),NA(),F14/$B$22)) -> 0.71838454 | G36: =IF(ISNA(G14),NA(),IF(ISBLANK(G14),NA(),G14/$B$22)) -> 0.86698669 | H36: =IF(ISNA(H14),NA(),IF(ISBLANK(H14),NA(),H14/$B$22)) -> 1
A37: capital scaled | B37: =IF(ISNA(B15),NA(),IF(ISBLANK(B15),NA(),B15/$B$22)) -> 0.16743611 | C37: =IF(ISNA(C15),NA(),IF(ISBLANK(C15),NA(),C15/$B$22)) -> 0.20865529 | D37: =IF(ISNA(D15),NA(),IF(ISBLANK(D15),NA(),D15/$B$22)) -> 0.22326447 | E37: =IF(ISNA(E15),NA(),IF(ISBLANK(E15),NA(),E15/$B$22)) -> 0.19459718 | F37: =IF(ISNA(F15),NA(),IF(ISBLANK(F15),NA(),F15/$B$22)) -> 0.24830703 | G37: =IF(ISNA(G15),NA(),IF(ISBLANK(G15),NA(),G15/$B$22)) -> 0.31338093 | H37: =IF(ISNA(H15),NA(),IF(ISBLANK(H15),NA(),H15/$B$22)) -> 0.37132781
A38: ros scaled | B38: =IF(ISNA(B16),NA(),IF(ISBLANK(B16),NA(),B16/$B$20)) -> 0.26823164 | C38: =IF(ISNA(C16),NA(),IF(ISBLANK(C16),NA(),C16/$B$20)) -> 0.36247978 | D38: =IF(ISNA(D16),NA(),IF(ISBLANK(D16),NA(),D16/$B$20)) -> 0.13849223 | E38: =IF(ISNA(E16),NA(),IF(ISBLANK(E16),NA(),E16/$B$20)) -> 0.12377207 | F38: =IF(ISNA(F16),NA(),IF(ISBLANK(F16),NA(),F16/$B$20)) -> 0.15031036 | G38: =IF(ISNA(G16),NA(),IF(ISBLANK(G16),NA(),G16/$B$20)) -> 0.33005802 | H38: =IF(ISNA(H16),NA(),IF(ISBLANK(H16),NA(),H16/$B$20)) -> 0.37132781
A39: turnover scaled | B39: =IF(ISNA(B17),NA(),IF(ISBLANK(B17),NA(),B17/$B$21)) -> 0.85422668 | C39: =IF(ISNA(C17),NA(),IF(ISBLANK(C17),NA(),C17/$B$21)) -> 0.74362277 | D39: =IF(ISNA(D17),NA(),IF(ISBLANK(D17),NA(),D17/$B$21)) -> 0.78536165 | E39: =IF(ISNA(E17),NA(),IF(ISBLANK(E17),NA(),E17/$B$21)) -> 1 | F39: =IF(ISNA(F17),NA(),IF(ISBLANK(F17),NA(),F17/$B$21)) -> 0.9336677 | G39: =IF(ISNA(G17),NA(),IF(ISBLANK(G17),NA(),G17/$B$21)) -> 0.89282066 | H39: =IF(ISNA(H17),NA(),IF(ISBLANK(H17),NA(),H17/$B$21)) -> 0.86909428
A40: roi scaled | B40: =IF(ISNA(B18),NA(),IF(ISBLANK(B18),NA(),B18/$B$20)) -> 0.7100007 | C40: =IF(ISNA(C18),NA(),IF(ISBLANK(C18),NA(),C18/$B$20)) -> 0.83524157 | D40: =IF(ISNA(D18),NA(),IF(ISBLANK(D18),NA(),D18/$B$20)) -> 0.3370317 | E40: =IF(ISNA(E18),NA(),IF(ISBLANK(E18),NA(),E18/$B$20)) -> 0.38352909 | F40: =IF(ISNA(F18),NA(),IF(ISBLANK(F18),NA(),F18/$B$20)) -> 0.43486743 | G40: =IF(ISNA(G18),NA(),IF(ISBLANK(G18),NA(),G18/$B$20)) -> 0.91312485 | H40: =IF(ISNA(H18),NA(),IF(ISBLANK(H18),NA(),H18/$B$20)) -> 1
A57: return text | B57: =IF(ISNA(B13),"",IF(ISBLANK(B13),"",TEXT(B13,"0.0"))) -> 3294.0 | C57: =IF(ISNA(C13),"",IF(ISBLANK(C13),"",TEXT(C13,"0.0"))) -> 4829.0 | D57: =IF(ISNA(D13),"",IF(ISBLANK(D13),"",TEXT(D13,"0.0"))) -> 2085.0 | E57: =IF(ISNA(E13),"",IF(ISBLANK(E13),"",TEXT(E13,"0.0"))) -> 2068.0 | F57: =IF(ISNA(F13),"",IF(ISBLANK(F13),"",TEXT(F13,"0.0"))) -> 2992.0 | G57: =IF(ISNA(G13),"",IF(ISBLANK(G13),"",TEXT(G13,"0.0"))) -> 7929.0 | H57: =IF(ISNA(H13),"",IF(ISBLANK(H13),"",TEXT(H13,"0.0"))) -> 10289.0
A58: net_sales text | B58: =IF(ISNA(B14),"",IF(ISBLANK(B14),"",TEXT(B14,"0.0"))) -> 36192.0 | C58: =IF(ISNA(C14),"",IF(ISBLANK(C14),"",TEXT(C14,"0.0"))) -> 39262.0 | D58: =IF(ISNA(D14),"",IF(ISBLANK(D14),"",TEXT(D14,"0.0"))) -> 44369.0 | E58: =IF(ISNA(E14),"",IF(ISBLANK(E14),"",TEXT(E14,"0.0"))) -> 49241.0 | F58: =IF(ISNA(F14),"",IF(ISBLANK(F14),"",TEXT(F14,"0.0"))) -> 58664.0 | G58: =IF(ISNA(G14),"",IF(ISBLANK(G14),"",TEXT(G14,"0.0"))) -> 70799.0 | H58: =IF(ISNA(H14),"",IF(ISBLANK(H14),"",TEXT(H14,"0.0"))) -> 81661.0
A59: capital text | B59: =IF(ISNA(B15),"",IF(ISBLANK(B15),"",TEXT(B15,"0.0"))) -> 13673.0 | C59: =IF(ISNA(C15),"",IF(ISBLANK(C15),"",TEXT(C15,"0.0"))) -> 17039.0 | D59: =IF(ISNA(D15),"",IF(ISBLANK(D15),"",TEXT(D15,"0.0"))) -> 18232.0 | E59: =IF(ISNA(E15),"",IF(ISBLANK(E15),"",TEXT(E15,"0.0"))) -> 15891.0 | F59: =IF(ISNA(F15),"",IF(ISBLANK(F15),"",TEXT(F15,"0.0"))) -> 20277.0 | G59: =IF(ISNA(G15),"",IF(ISBLANK(G15),"",TEXT(G15,"0.0"))) -> 25591.0 | H59: =IF(ISNA(H15),"",IF(ISBLANK(H15),"",TEXT(H15,"0.0"))) -> 30323.0
A60: ros text | B60: =IF(ISNA(B16),"",IF(ISBLANK(B16),"",TEXT(B16,"0.0"))) -> 9.1 | C60: =IF(ISNA(C16),"",IF(ISBLANK(C16),"",TEXT(C16,"0.0"))) -> 12.3 | D60: =IF(ISNA(D16),"",IF(ISBLANK(D16),"",TEXT(D16,"0.0"))) -> 4.7 | E60: =IF(ISNA(E16),"",IF(ISBLANK(E16),"",TEXT(E16,"0.0"))) -> 4.2 | F60: =IF(ISNA(F16),"",IF(ISBLANK(F16),"",TEXT(F16,"0.0"))) -> 5.1 | G60: =IF(ISNA(G16),"",IF(ISBLANK(G16),"",TEXT(G16,"0.0"))) -> 11.2 | H60: =IF(ISNA(H16),"",IF(ISBLANK(H16),"",TEXT(H16,"0.0"))) -> 12.6
A61: turnover text | B61: =IF(ISNA(B17),"",IF(ISBLANK(B17),"",TEXT(B17,"0.0"))) -> 2.6 | C61: =IF(ISNA(C17),"",IF(ISBLANK(C17),"",TEXT(C17,"0.0"))) -> 2.3 | D61: =IF(ISNA(D17),"",IF(ISBLANK(D17),"",TEXT(D17,"0.0"))) -> 2.4 | E61: =IF(ISNA(E17),"",IF(ISBLANK(E17),"",TEXT(E17,"0.0"))) -> 3.1 | F61: =IF(ISNA(F17),"",IF(ISBLANK(F17),"",TEXT(F17,"0.0"))) -> 2.9 | G61: =IF(ISNA(G17),"",IF(ISBLANK(G17),"",TEXT(G17,"0.0"))) -> 2.8 | H61: =IF(ISNA(H17),"",IF(ISBLANK(H17),"",TEXT(H17,"0.0"))) -> 2.7
A62: roi text | B62: =IF(ISNA(B18),"",IF(ISBLANK(B18),"",TEXT(B18,"0.0"))) -> 24.1 | C62: =IF(ISNA(C18),"",IF(ISBLANK(C18),"",TEXT(C18,"0.0"))) -> 28.3 | D62: =IF(ISNA(D18),"",IF(ISBLANK(D18),"",TEXT(D18,"0.0"))) -> 11.4 | E62: =IF(ISNA(E18),"",IF(ISBLANK(E18),"",TEXT(E18,"0.0"))) -> 13.0 | F62: =IF(ISNA(F18),"",IF(ISBLANK(F18),"",TEXT(F18,"0.0"))) -> 14.8 | G62: =IF(ISNA(G18),"",IF(ISBLANK(G18),"",TEXT(G18,"0.0"))) -> 31.0 | H62: =IF(ISNA(H18),"",IF(ISBLANK(H18),"",TEXT(H18,"0.0"))) -> 33.9

Sheet C12A
A1: Entity | B1: The Progressive Corporation
A2: Measure | B2: Profit and loss statement
A3: Unit | B3: $m
A4: Period | B4: AC 2023, PY and ΔPY
A5: Reference | B5: PY
A6: Message | B6: Net income rose from 722 to 3,903 $m, +441%, as an underwriting result that had nearly vanished in 2022 recovered; 3 lines move too far to be drawn to scale and carry the overflow marks
A7: Subject | B7: =B2&" in "&B3 -> Profit and loss statement in $m
A9: var_abs caption | B9: ="Δ"&$B$5&" "&$B$3 -> ΔPY $m
A10: var_rel caption | B10: ="Δ"&$B$5&"%" -> ΔPY%
A12: Line | B12: Sign | C12: PY | D12: AC | E12: ΔPY | F12: ΔPY% | G12: PY level | H12: PY from | I12: PY base | J12: PY adds | K12: PY subs | L12: AC level | M12: AC from | N12: AC base | O12: AC adds | P12: AC subs | Q12: ΔPY up ok | R12: ΔPY up bad | S12: ΔPY dn ok | T12: ΔPY dn bad | U12: ΔPY% up ok | V12: ΔPY% up bad | W12: ΔPY% dn ok | X12: ΔPY% dn bad | Y12: span unit | Z12: py_base scaled | AA12: py_add scaled | AB12: py_add text | AC12: py_sub scaled | AD12: py_sub text | AE12: ac_base scaled | AF12: ac_add scaled | AG12: ac_add text | AH12: ac_sub scaled | AI12: ac_sub text | AJ12: var_abs scaled | AK12: var_abs text | AL12: abs_pos_good scaled | AM12: abs_pos_bad scaled | AN12: abs_neg_good scaled | AO12: abs_neg_bad scaled | AP12: var_rel clipped | AQ12: rel_pos_good clipped | AR12: rel_pos_bad clipped | AS12: rel_neg_good clipped | AT12: rel_neg_bad clipped | AU12: ΔPY% text
A13: Premiums earned | B13: 1 | C13: 49241 | D13: 58665 | E13: =D13-C13 -> 9424 | F13: =IF(C13<=0,NA(),(D13-C13)/C13*100) -> 19.138523 | G13: =0+B13*C13 -> 49241 | H13: =0 -> 0 | I13: =MIN(H13,G13) -> 0 | J13: =IF(B13>0,ABS(G13-H13),0) -> 49241 | K13: =IF(B13<0,ABS(G13-H13),0) -> 0 | L13: =0+B13*D13 -> 58665 | M13: =0 -> 0 | N13: =MIN(M13,L13) -> 0 | O13: =IF(B13>0,ABS(L13-M13),0) -> 58665 | P13: =IF(B13<0,ABS(L13-M13),0) -> 0 | Q13: =IF(AND($E13>0,$B13>0),$E13,NA()) -> 9424 | R13: =IF(AND($E13>0,$B13<0),$E13,NA()) -> #N/A | S13: =IF(AND($E13<0,$B13<0),$E13,NA()) -> #N/A | T13: =IF(AND($E13<0,$B13>0),$E13,NA()) -> #N/A | U13: =IF(AND($F13>0,$B13>0),$F13,NA()) -> 19.138523 | V13: =IF(AND($F13>0,$B13<0),$F13,NA()) -> #N/A | W13: =IF(AND($F13<0,$B13<0),$F13,NA()) -> #N/A | X13: =IF(AND($F13<0,$B13>0),$F13,NA()) -> #N/A | Y13: =MAX(_xlfn.AGGREGATE(4,6,I13:I32,J13:J32,K13:K32,N13:N32,O13:O32,P13:P32,E13:E32,Q13:Q32,R13:R32,S13:S32,T13:T32),-_xlfn.AGGREGATE(5,6,I13:I32,J13:J32,K13:K32,N13:N32,O13:O32,P13:P32,E13:E32,Q13:Q32,R13:R32,S13:S32,T13:T32),0.000000001) -> 62109 | Z13: =I13/$Y$13 -> 0 | AA13: =J13/$Y$13 -> 0.79281586 | AB13: =IF(ISNA(J13),"",TEXT(J13,"#,##0")) -> 49,241 | AC13: =K13/$Y$13 -> 0 | AD13: =IF(ISNA(K13),"",TEXT(K13,"#,##0")) -> 0 | AE13: =N13/$Y$13 -> 0 | AF13: =O13/$Y$13 -> 0.9445491 | AG13: =IF(ISNA(O13),"",TEXT(O13,"#,##0")) -> 58,665 | AH13: =P13/$Y$13 -> 0 | AI13: =IF(ISNA(P13),"",TEXT(P13,"#,##0")) -> 0 | AJ13: =E13/$Y$13 -> 0.15173324 | AK13: =IF(ISNA(E13),"",TEXT(E13,"+0;-0")) -> +9424 | AL13: =Q13/$Y$13 -> 0.15173324 | AM13: =R13/$Y$13 -> #N/A | AN13: =S13/$Y$13 -> #N/A | AO13: =T13/$Y$13 -> #N/A | AP13: =IF(ISNA(F13),NA(),MEDIAN(-31.5,F13,238.5)) -> 19.138523 | AQ13: =IF(ISNA(U13),NA(),MEDIAN(-31.5,U13,238.5)) -> 19.138523 | AR13: =IF(ISNA(V13),NA(),MEDIAN(-31.5,V13,238.5)) -> #N/A | AS13: =IF(ISNA(W13),NA(),MEDIAN(-31.5,W13,238.5)) -> #N/A | AT13: =IF(ISNA(X13),NA(),MEDIAN(-31.5,X13,238.5)) -> #N/A | AU13: =IF(ISNA(F13),"",IF(F13>265,TEXT(F13,"+0;-0")&REPT(_xlfn.UNICHAR(9658),MIN(3,MAX(1,INT(F13/265)))),IF(F13<-35,REPT(_xlfn.UNICHAR(9668),MIN(3,MAX(1,INT(-F13/35))))&TEXT(F13,"+0;-0"),TEXT(F13,"+0;-0")))) -> +19
A14: Investment income | B14: 1 | C14: 1236 | D14: 1866 | E14: =D14-C14 -> 630 | F14: =IF(C14<=0,NA(),(D14-C14)/C14*100) -> 50.970874 | G14: =G13+B14*C14 -> 50477 | H14: =G13 -> 49241 | I14: =MIN(H14,G14) -> 49241 | J14: =IF(B14>0,ABS(G14-H14),0) -> 1236 | K14: =IF(B14<0,ABS(G14-H14),0) -> 0 | L14: =L13+B14*D14 -> 60531 | M14: =L13 -> 58665 | N14: =MIN(M14,L14) -> 58665 | O14: =IF(B14>0,ABS(L14-M14),0) -> 1866 | P14: =IF(B14<0,ABS(L14-M14),0) -> 0 | Q14: =IF(AND($E14>0,$B14>0),$E14,NA()) -> 630 | R14: =IF(AND($E14>0,$B14<0),$E14,NA()) -> #N/A | S14: =IF(AND($E14<0,$B14<0),$E14,NA()) -> #N/A | T14: =IF(AND($E14<0,$B14>0),$E14,NA()) -> #N/A | U14: =IF(AND($F14>0,$B14>0),$F14,NA()) -> 50.970874 | V14: =IF(AND($F14>0,$B14<0),$F14,NA()) -> #N/A | W14: =IF(AND($F14<0,$B14<0),$F14,NA()) -> #N/A | X14: =IF(AND($F14<0,$B14>0),$F14,NA()) -> #N/A | Z14: =I14/$Y$13 -> 0.79281586 | AA14: =J14/$Y$13 -> 0.019900498 | AB14: =IF(ISNA(J14),"",TEXT(J14,"#,##0")) -> 1,236 | AC14: =K14/$Y$13 -> 0 | AD14: =IF(ISNA(K14),"",TEXT(K14,"#,##0")) -> 0 | AE14: =N14/$Y$13 -> 0.9445491 | AF14: =O14/$Y$13 -> 0.030043955 | AG14: =IF(ISNA(O14),"",TEXT(O14,"#,##0")) -> 1,866 | AH14: =P14/$Y$13 -> 0 | AI14: =IF(ISNA(P14),"",TEXT(P14,"#,##0")) -> 0 | AJ14: =E14/$Y$13 -> 0.010143457 | AK14: =IF(ISNA(E14),"",TEXT(E14,"+0;-0")) -> +630 | AL14: =Q14/$Y$13 -> 0.010143457 | AM14: =R14/$Y$13 -> #N/A | AN14: =S14/$Y$13 -> #N/A | AO14: =T14/$Y$13 -> #N/A | AP14: =IF(ISNA(F14),NA(),MEDIAN(-31.5,F14,238.5)) -> 50.970874 | AQ14: =IF(ISNA(U14),NA(),MEDIAN(-31.5,U14,238.5)) -> 50.970874 | AR14: =IF(ISNA(V14),NA(),MEDIAN(-31.5,V14,238.5)) -> #N/A | AS14: =IF(ISNA(W14),NA(),MEDIAN(-31.5,W14,238.5)) -> #N/A | AT14: =IF(ISNA(X14),NA(),MEDIAN(-31.5,X14,238.5)) -> #N/A | AU14: =IF(ISNA(F14),"",IF(F14>265,TEXT(F14,"+0;-0")&REPT(_xlfn.UNICHAR(9658),MIN(3,MAX(1,INT(F14/265)))),IF(F14<-35,REPT(_xlfn.UNICHAR(9668),MIN(3,MAX(1,INT(-F14/35))))&TEXT(F14,"+0;-0"),TEXT(F14,"+0;-0")))) -> +51
A15: Other revenues | B15: 1 | C15: -866 | D15: 1578 | E15: =D15-C15 -> 2444 | F15: =IF(C15<=0,NA(),(D15-C15)/C15*100) -> #N/A | G15: =G14+B15*C15 -> 49611 | H15: =G14 -> 50477 | I15: =MIN(H15,G15) -> 49611 | J15: =IF(B15>0,ABS(G15-H15),0) -> 866 | K15: =IF(B15<0,ABS(G15-H15),0) -> 0 | L15: =L14+B15*D15 -> 62109 | M15: =L14 -> 60531 | N15: =MIN(M15,L15) -> 60531 | O15: =IF(B15>0,ABS(L15-M15),0) -> 1578 | P15: =IF(B15<0,ABS(L15-M15),0) -> 0 | Q15: =IF(AND($E15>0,$B15>0),$E15,NA()) -> 2444 | R15: =IF(AND($E15>0,$B15<0),$E15,NA()) -> #N/A | S15: =IF(AND($E15<0,$B15<0),$E15,NA()) -> #N/A | T15: =IF(AND($E15<0,$B15>0),$E15,NA()) -> #N/A | U15: =IF(AND($F15>0,$B15>0),$F15,NA()) -> #N/A | V15: =IF(AND($F15>0,$B15<0),$F15,NA()) -> #N/A | W15: =IF(AND($F15<0,$B15<0),$F15,NA()) -> #N/A | X15: =IF(AND($F15<0,$B15>0),$F15,NA()) -> #N/A | Z15: =I15/$Y$13 -> 0.79877312 | AA15: =J15/$Y$13 -> 0.013943229 | AB15: =IF(ISNA(J15),"",TEXT(J15,"#,##0")) -> 866 | AC15: =K15/$Y$13 -> 0 | AD15: =IF(ISNA(K15),"",TEXT(K15,"#,##0")) -> 0 | AE15: =N15/$Y$13 -> 0.97459305 | AF15: =O15/$Y$13 -> 0.025406946 | AG15: =IF(ISNA(O15),"",TEXT(O15,"#,##0")) -> 1,578 | AH15: =P15/$Y$13 -> 0 | AI15: =IF(ISNA(P15),"",TEXT(P15,"#,##0")) -> 0 | AJ15: =E15/$Y$13 -> 0.039350175 | AK15: =IF(ISNA(E15),"",TEXT(E15,"+0;-0")) -> +2444 | AL15: =Q15/$Y$13 -> 0.039350175 | AM15: =R15/$Y$13 -> #N/A | AN15: =S15/$Y$13 -> #N/A | AO15: =T15/$Y$13 -> #N/A | AP15: =IF(ISNA(F15),NA(),MEDIAN(-31.5,F15,238.5)) -> #N/A | AQ15: =IF(ISNA(U15),NA(),MEDIAN(-31.5,U15,238.5)) -> #N/A | AR15: =IF(ISNA(V15),NA(),MEDIAN(-31.5,V15,238.5)) -> #N/A | AS15: =IF(ISNA(W15),NA(),MEDIAN(-31.5,W15,238.5)) -> #N/A | AT15: =IF(ISNA(X15),NA(),MEDIAN(-31.5,X15,238.5)) -> #N/A | AU15: =IF(ISNA(F15),"",IF(F15>265,TEXT(F15,"+0;-0")&REPT(_xlfn.UNICHAR(9658),MIN(3,MAX(1,INT(F15/265)))),IF(F15<-35,REPT(_xlfn.UNICHAR(9668),MIN(3,MAX(1,INT(-F15/35))))&TEXT(F15,"+0;-0"),TEXT(F15,"+0;-0"))))
A16: Total revenues | B16: 1 | C16: =G15 -> 49611 | D16: =L15 -> 62109 | E16: =D16-C16 -> 12498 | F16: =IF(C16<=0,NA(),(D16-C16)/C16*100) -> 25.191994 | G16: =G15 -> 49611 | H16: =0 -> 0 | I16: =MIN(H16,G16) -> 0 | J16: =IF(B16>0,ABS(G16-H16),0) -> 49611 | K16: =IF(B16<0,ABS(G16-H16),0) -> 0 | L16: =L15 -> 62109 | M16: =0 -> 0 | N16: =MIN(M16,L16) -> 0 | O16: =IF(B16>0,ABS(L16-M16),0) -> 62109 | P16: =IF(B16<0,ABS(L16-M16),0) -> 0 | Q16: =IF(AND($E16>0,$B16>0),$E16,NA()) -> 12498 | R16: =IF(AND($E16>0,$B16<0),$E16,NA()) -> #N/A | S16: =IF(AND($E16<0,$B16<0),$E16,NA()) -> #N/A | T16: =IF(AND($E16<0,$B16>0),$E16,NA()) -> #N/A | U16: =IF(AND($F16>0,$B16>0),$F16,NA()) -> 25.191994 | V16: =IF(AND($F16>0,$B16<0),$F16,NA()) -> #N/A | W16: =IF(AND($F16<0,$B16<0),$F16,NA()) -> #N/A | X16: =IF(AND($F16<0,$B16>0),$F16,NA()) -> #N/A | Z16: =I16/$Y$13 -> 0 | AA16: =J16/$Y$13 -> 0.79877312 | AB16: =IF(ISNA(J16),"",TEXT(J16,"#,##0")) -> 49,611 | AC16: =K16/$Y$13 -> 0 | AD16: =IF(ISNA(K16),"",TEXT(K16,"#,##0")) -> 0 | AE16: =N16/$Y$13 -> 0 | AF16: =O16/$Y$13 -> 1 | AG16: =IF(ISNA(O16),"",TEXT(O16,"#,##0")) -> 62,109 | AH16: =P16/$Y$13 -> 0 | AI16: =IF(ISNA(P16),"",TEXT(P16,"#,##0")) -> 0 | AJ16: =E16/$Y$13 -> 0.20122688 | AK16: =IF(ISNA(E16),"",TEXT(E16,"+0;-0")) -> +12498 | AL16: =Q16/$Y$13 -> 0.20122688 | AM16: =R16/$Y$13 -> #N/A | AN16: =S16/$Y$13 -> #N/A | AO16: =T16/$Y$13 -> #N/A | AP16: =IF(ISNA(F16),NA(),MEDIAN(-31.5,F16,238.5)) -> 25.191994 | AQ16: =IF(ISNA(U16),NA(),MEDIAN(-31.5,U16,238.5)) -> 25.191994 | AR16: =IF(ISNA(V16),NA(),MEDIAN(-31.5,V16,238.5)) -> #N/A | AS16: =IF(ISNA(W16),NA(),MEDIAN(-31.5,W16,238.5)) -> #N/A | AT16: =IF(ISNA(X16),NA(),MEDIAN(-31.5,X16,238.5)) -> #N/A | AU16: =IF(ISNA(F16),"",IF(F16>265,TEXT(F16,"+0;-0")&REPT(_xlfn.UNICHAR(9658),MIN(3,MAX(1,INT(F16/265)))),IF(F16<-35,REPT(_xlfn.UNICHAR(9668),MIN(3,MAX(1,INT(-F16/35))))&TEXT(F16,"+0;-0"),TEXT(F16,"+0;-0")))) -> +25
A17: Losses and LAE | B17: -1 | C17: 38123 | D17: 45655 | E17: =D17-C17 -> 7532 | F17: =IF(C17<=0,NA(),(D17-C17)/C17*100) -> 19.757102 | G17: =G16+B17*C17 -> 11488 | H17: =G16 -> 49611 | I17: =MIN(H17,G17) -> 11488 | J17: =IF(B17>0,ABS(G17-H17),0) -> 0 | K17: =IF(B17<0,ABS(G17-H17),0) -> 38123 | L17: =L16+B17*D17 -> 16454 | M17: =L16 -> 62109 | N17: =MIN(M17,L17) -> 16454 | O17: =IF(B17>0,ABS(L17-M17),0) -> 0 | P17: =IF(B17<0,ABS(L17-M17),0) -> 45655 | Q17: =IF(AND($E17>0,$B17>0),$E17,NA()) -> #N/A | R17: =IF(AND($E17>0,$B17<0),$E17,NA()) -> 7532 | S17: =IF(AND($E17<0,$B17<0),$E17,NA()) -> #N/A | T17: =IF(AND($E17<0,$B17>0),$E17,NA()) -> #N/A | U17: =IF(AND($F17>0,$B17>0),$F17,NA()) -> #N/A | V17: =IF(AND($F17>0,$B17<0),$F17,NA()) -> 19.757102 | W17: =IF(AND($F17<0,$B17<0),$F17,NA()) -> #N/A | X17: =IF(AND($F17<0,$B17>0),$F17,NA()) -> #N/A | Z17: =I17/$Y$13 -> 0.18496514 | AA17: =J17/$Y$13 -> 0 | AB17: =IF(ISNA(J17),"",TEXT(J17,"#,##0")) -> 0 | AC17: =K17/$Y$13 -> 0.61380798 | AD17: =IF(ISNA(K17),"",TEXT(K17,"#,##0")) -> 38,123 | AE17: =N17/$Y$13 -> 0.26492135 | AF17: =O17/$Y$13 -> 0 | AG17: =IF(ISNA(O17),"",TEXT(O17,"#,##0")) -> 0 | AH17: =P17/$Y$13 -> 0.73507865 | AI17: =IF(ISNA(P17),"",TEXT(P17,"#,##0")) -> 45,655 | AJ17: =E17/$Y$13 -> 0.12127067 | AK17: =IF(ISNA(E17),"",TEXT(E17,"+0;-0")) -> +7532 | AL17: =Q17/$Y$13 -> #N/A | AM17: =R17/$Y$13 -> 0.12127067 | AN17: =S17/$Y$13 -> #N/A | AO17: =T17/$Y$13 -> #N/A | AP17: =IF(ISNA(F17),NA(),MEDIAN(-31.5,F17,238.5)) -> 19.757102 | AQ17: =IF(ISNA(U17),NA(),MEDIAN(-31.5,U17,238.5)) -> #N/A | AR17: =IF(ISNA(V17),NA(),MEDIAN(-31.5,V17,238.5)) -> 19.757102 | AS17: =IF(ISNA(W17),NA(),MEDIAN(-31.5,W17,238.5)) -> #N/A | AT17: =IF(ISNA(X17),NA(),MEDIAN(-31.5,X17,238.5)) -> #N/A | AU17: =IF(ISNA(F17),"",IF(F17>265,TEXT(F17,"+0;-0")&REPT(_xlfn.UNICHAR(9658),MIN(3,MAX(1,INT(F17/265)))),IF(F17<-35,REPT(_xlfn.UNICHAR(9668),MIN(3,MAX(1,INT(-F17/35))))&TEXT(F17,"+0;-0"),TEXT(F17,"+0;-0")))) -> +20
A18: Acquisition costs | B18: -1 | C18: 3917 | D18: 4665 | E18: =D18-C18 -> 748 | F18: =IF(C18<=0,NA(),(D18-C18)/C18*100) -> 19.096247 | G18: =G17+B18*C18 -> 7571 | H18: =G17 -> 11488 | I18: =MIN(H18,G18) -> 7571 | J18: =IF(B18>0,ABS(G18-H18),0) -> 0 | K18: =IF(B18<0,ABS(G18-H18),0) -> 3917 | L18: =L17+B18*D18 -> 11789 | M18: =L17 -> 16454 | N18: =MIN(M18,L18) -> 11789 | O18: =IF(B18>0,ABS(L18-M18),0) -> 0 | P18: =IF(B18<0,ABS(L18-M18),0) -> 4665 | Q18: =IF(AND($E18>0,$B18>0),$E18,NA()) -> #N/A | R18: =IF(AND($E18>0,$B18<0),$E18,NA()) -> 748 | S18: =IF(AND($E18<0,$B18<0),$E18,NA()) -> #N/A | T18: =IF(AND($E18<0,$B18>0),$E18,NA()) -> #N/A | U18: =IF(AND($F18>0,$B18>0),$F18,NA()) -> #N/A | V18: =IF(AND($F18>0,$B18<0),$F18,NA()) -> 19.096247 | W18: =IF(AND($F18<0,$B18<0),$F18,NA()) -> #N/A | X18: =IF(AND($F18<0,$B18>0),$F18,NA()) -> #N/A | Z18: =I18/$Y$13 -> 0.1218986 | AA18: =J18/$Y$13 -> 0 | AB18: =IF(ISNA(J18),"",TEXT(J18,"#,##0")) -> 0 | AC18: =K18/$Y$13 -> 0.063066544 | AD18: =IF(ISNA(K18),"",TEXT(K18,"#,##0")) -> 3,917 | AE18: =N18/$Y$13 -> 0.18981146 | AF18: =O18/$Y$13 -> 0 | AG18: =IF(ISNA(O18),"",TEXT(O18,"#,##0")) -> 0 | AH18: =P18/$Y$13 -> 0.075109887 | AI18: =IF(ISNA(P18),"",TEXT(P18,"#,##0")) -> 4,665 | AJ18: =E18/$Y$13 -> 0.012043343 | AK18: =IF(ISNA(E18),"",TEXT(E18,"+0;-0")) -> +748 | AL18: =Q18/$Y$13 -> #N/A | AM18: =R18/$Y$13 -> 0.012043343 | AN18: =S18/$Y$13 -> #N/A | AO18: =T18/$Y$13 -> #N/A | AP18: =IF(ISNA(F18),NA(),MEDIAN(-31.5,F18,238.5)) -> 19.096247 | AQ18: =IF(ISNA(U18),NA(),MEDIAN(-31.5,U18,238.5)) -> #N/A | AR18: =IF(ISNA(V18),NA(),MEDIAN(-31.5,V18,238.5)) -> 19.096247 | AS18: =IF(ISNA(W18),NA(),MEDIAN(-31.5,W18,238.5)) -> #N/A | AT18: =IF(ISNA(X18),NA(),MEDIAN(-31.5,X18,238.5)) -> #N/A | AU18: =IF(ISNA(F18),"",IF(F18>265,TEXT(F18,"+0;-0")&REPT(_xlfn.UNICHAR(9658),MIN(3,MAX(1,INT(F18/265)))),IF(F18<-35,REPT(_xlfn.UNICHAR(9668),MIN(3,MAX(1,INT(-F18/35))))&TEXT(F18,"+0;-0"),TEXT(F18,"+0;-0")))) -> +19
A19: Other expenses | B19: -1 | C19: 6649 | D19: 6885 | E19: =D19-C19 -> 236 | F19: =IF(C19<=0,NA(),(D19-C19)/C19*100) -> 3.5494059 | G19: =G18+B19*C19 -> 922 | H19: =G18 -> 7571 | I19: =MIN(H19,G19) -> 922 | J19: =IF(B19>0,ABS(G19-H19),0) -> 0 | K19: =IF(B19<0,ABS(G19-H19),0) -> 6649 | L19: =L18+B19*D19 -> 4904 | M19: =L18 -> 11789 | N19: =MIN(M19,L19) -> 4904 | O19: =IF(B19>0,ABS(L19-M19),0) -> 0 | P19: =IF(B19<0,ABS(L19-M19),0) -> 6885 | Q19: =IF(AND($E19>0,$B19>0),$E19,NA()) -> #N/A | R19: =IF(AND($E19>0,$B19<0),$E19,NA()) -> 236 | S19: =IF(AND($E19<0,$B19<0),$E19,NA()) -> #N/A | T19: =IF(AND($E19<0,$B19>0),$E19,NA()) -> #N/A | U19: =IF(AND($F19>0,$B19>0),$F19,NA()) -> #N/A | V19: =IF(AND($F19>0,$B19<0),$F19,NA()) -> 3.5494059 | W19: =IF(AND($F19<0,$B19<0),$F19,NA()) -> #N/A | X19: =IF(AND($F19<0,$B19>0),$F19,NA()) -> #N/A | Z19: =I19/$Y$13 -> 0.01484487 | AA19: =J19/$Y$13 -> 0 | AB19: =IF(ISNA(J19),"",TEXT(J19,"#,##0")) -> 0 | AC19: =K19/$Y$13 -> 0.10705373 | AD19: =IF(ISNA(K19),"",TEXT(K19,"#,##0")) -> 6,649 | AE19: =N19/$Y$13 -> 0.078957961 | AF19: =O19/$Y$13 -> 0 | AG19: =IF(ISNA(O19),"",TEXT(O19,"#,##0")) -> 0 | AH19: =P19/$Y$13 -> 0.1108535 | AI19: =IF(ISNA(P19),"",TEXT(P19,"#,##0")) -> 6,885 | AJ19: =E19/$Y$13 -> 0.0037997714 | AK19: =IF(ISNA(E19),"",TEXT(E19,"+0;-0")) -> +236 | AL19: =Q19/$Y$13 -> #N/A | AM19: =R19/$Y$13 -> 0.0037997714 | AN19: =S19/$Y$13 -> #N/A | AO19: =T19/$Y$13 -> #N/A | AP19: =IF(ISNA(F19),NA(),MEDIAN(-31.5,F19,238.5)) -> 3.5494059 | AQ19: =IF(ISNA(U19),NA(),MEDIAN(-31.5,U19,238.5)) -> #N/A | AR19: =IF(ISNA(V19),NA(),MEDIAN(-31.5,V19,238.5)) -> 3.5494059 | AS19: =IF(ISNA(W19),NA(),MEDIAN(-31.5,W19,238.5)) -> #N/A | AT19: =IF(ISNA(X19),NA(),MEDIAN(-31.5,X19,238.5)) -> #N/A | AU19: =IF(ISNA(F19),"",IF(F19>265,TEXT(F19,"+0;-0")&REPT(_xlfn.UNICHAR(9658),MIN(3,MAX(1,INT(F19/265)))),IF(F19<-35,REPT(_xlfn.UNICHAR(9668),MIN(3,MAX(1,INT(-F19/35))))&TEXT(F19,"+0;-0"),TEXT(F19,"+0;-0")))) -> +4
A20: Pretax income | B20: 1 | C20: =G19 -> 922 | D20: =L19 -> 4904 | E20: =D20-C20 -> 3982 | F20: =IF(C20<=0,NA(),(D20-C20)/C20*100) -> 431.8872 | G20: =G19 -> 922 | H20: =0 -> 0 | I20: =MIN(H20,G20) -> 0 | J20: =IF(B20>0,ABS(G20-H20),0) -> 922 | K20: =IF(B20<0,ABS(G20-H20),0) -> 0 | L20: =L19 -> 4904 | M20: =0 -> 0 | N20: =MIN(M20,L20) -> 0 | O20: =IF(B20>0,ABS(L20-M20),0) -> 4904 | P20: =IF(B20<0,ABS(L20-M20),0) -> 0 | Q20: =IF(AND($E20>0,$B20>0),$E20,NA()) -> 3982 | R20: =IF(AND($E20>0,$B20<0),$E20,NA()) -> #N/A | S20: =IF(AND($E20<0,$B20<0),$E20,NA()) -> #N/A | T20: =IF(AND($E20<0,$B20>0),$E20,NA()) -> #N/A | U20: =IF(AND($F20>0,$B20>0),$F20,NA()) -> 431.8872 | V20: =IF(AND($F20>0,$B20<0),$F20,NA()) -> #N/A | W20: =IF(AND($F20<0,$B20<0),$F20,NA()) -> #N/A | X20: =IF(AND($F20<0,$B20>0),$F20,NA()) -> #N/A | Z20: =I20/$Y$13 -> 0 | AA20: =J20/$Y$13 -> 0.01484487 | AB20: =IF(ISNA(J20),"",TEXT(J20,"#,##0")) -> 922 | AC20: =K20/$Y$13 -> 0 | AD20: =IF(ISNA(K20),"",TEXT(K20,"#,##0")) -> 0 | AE20: =N20/$Y$13 -> 0 | AF20: =O20/$Y$13 -> 0.078957961 | AG20: =IF(ISNA(O20),"",TEXT(O20,"#,##0")) -> 4,904 | AH20: =P20/$Y$13 -> 0 | AI20: =IF(ISNA(P20),"",TEXT(P20,"#,##0")) -> 0 | AJ20: =E20/$Y$13 -> 0.064113092 | AK20: =IF(ISNA(E20),"",TEXT(E20,"+0;-0")) -> +3982 | AL20: =Q20/$Y$13 -> 0.064113092 | AM20: =R20/$Y$13 -> #N/A | AN20: =S20/$Y$13 -> #N/A | AO20: =T20/$Y$13 -> #N/A | AP20: =IF(ISNA(F20),NA(),MEDIAN(-31.5,F20,238.5)) -> 238.5 | AQ20: =IF(ISNA(U20),NA(),MEDIAN(-31.5,U20,238.5)) -> 238.5 | AR20: =IF(ISNA(V20),NA(),MEDIAN(-31.5,V20,238.5)) -> #N/A | AS20: =IF(ISNA(W20),NA(),MEDIAN(-31.5,W20,238.5)) -> #N/A | AT20: =IF(ISNA(X20),NA(),MEDIAN(-31.5,X20,238.5)) -> #N/A | AU20: =IF(ISNA(F20),"",IF(F20>265,TEXT(F20,"+0;-0")&REPT(_xlfn.UNICHAR(9658),MIN(3,MAX(1,INT(F20/265)))),IF(F20<-35,REPT(_xlfn.UNICHAR(9668),MIN(3,MAX(1,INT(-F20/35))))&TEXT(F20,"+0;-0"),TEXT(F20,"+0;-0")))) -> +432►
A21: Income taxes | B21: -1 | C21: 200 | D21: 1001 | E21: =D21-C21 -> 801 | F21: =IF(C21<=0,NA(),(D21-C21)/C21*100) -> 400.5 | G21: =G20+B21*C21 -> 722 | H21: =G20 -> 922 | I21: =MIN(H21,G21) -> 722 | J21: =IF(B21>0,ABS(G21-H21),0) -> 0 | K21: =IF(B21<0,ABS(G21-H21),0) -> 200 | L21: =L20+B21*D21 -> 3903 | M21: =L20 -> 4904 | N21: =MIN(M21,L21) -> 3903 | O21: =IF(B21>0,ABS(L21-M21),0) -> 0 | P21: =IF(B21<0,ABS(L21-M21),0) -> 1001 | Q21: =IF(AND($E21>0,$B21>0),$E21,NA()) -> #N/A | R21: =IF(AND($E21>0,$B21<0),$E21,NA()) -> 801 | S21: =IF(AND($E21<0,$B21<0),$E21,NA()) -> #N/A | T21: =IF(AND($E21<0,$B21>0),$E21,NA()) -> #N/A | U21: =IF(AND($F21>0,$B21>0),$F21,NA()) -> #N/A | V21: =IF(AND($F21>0,$B21<0),$F21,NA()) -> 400.5 | W21: =IF(AND($F21<0,$B21<0),$F21,NA()) -> #N/A | X21: =IF(AND($F21<0,$B21>0),$F21,NA()) -> #N/A | Z21: =I21/$Y$13 -> 0.011624724 | AA21: =J21/$Y$13 -> 0 | AB21: =IF(ISNA(J21),"",TEXT(J21,"#,##0")) -> 0 | AC21: =K21/$Y$13 -> 0.0032201452 | AD21: =IF(ISNA(K21),"",TEXT(K21,"#,##0")) -> 200 | AE21: =N21/$Y$13 -> 0.062841134 | AF21: =O21/$Y$13 -> 0 | AG21: =IF(ISNA(O21),"",TEXT(O21,"#,##0")) -> 0 | AH21: =P21/$Y$13 -> 0.016116827 | AI21: =IF(ISNA(P21),"",TEXT(P21,"#,##0")) -> 1,001 | AJ21: =E21/$Y$13 -> 0.012896682 | AK21: =IF(ISNA(E21),"",TEXT(E21,"+0;-0")) -> +801 | AL21: =Q21/$Y$13 -> #N/A | AM21: =R21/$Y$13 -> 0.012896682 | AN21: =S21/$Y$13 -> #N/A | AO21: =T21/$Y$13 -> #N/A | AP21: =IF(ISNA(F21),NA(),MEDIAN(-31.5,F21,238.5)) -> 238.5 | AQ21: =IF(ISNA(U21),NA(),MEDIAN(-31.5,U21,238.5)) -> #N/A | AR21: =IF(ISNA(V21),NA(),MEDIAN(-31.5,V21,238.5)) -> 238.5 | AS21: =IF(ISNA(W21),NA(),MEDIAN(-31.5,W21,238.5)) -> #N/A | AT21: =IF(ISNA(X21),NA(),MEDIAN(-31.5,X21,238.5)) -> #N/A | AU21: =IF(ISNA(F21),"",IF(F21>265,TEXT(F21,"+0;-0")&REPT(_xlfn.UNICHAR(9658),MIN(3,MAX(1,INT(F21/265)))),IF(F21<-35,REPT(_xlfn.UNICHAR(9668),MIN(3,MAX(1,INT(-F21/35))))&TEXT(F21,"+0;-0"),TEXT(F21,"+0;-0")))) -> +401►
A22: Net income | B22: 1 | C22: =G21 -> 722 | D22: =L21 -> 3903 | E22: =D22-C22 -> 3181 | F22: =IF(C22<=0,NA(),(D22-C22)/C22*100) -> 440.58172 | G22: =G21 -> 722 | H22: =0 -> 0 | I22: =MIN(H22,G22) -> 0 | J22: =IF(B22>0,ABS(G22-H22),0) -> 722 | K22: =IF(B22<0,ABS(G22-H22),0) -> 0 | L22: =L21 -> 3903 | M22: =0 -> 0 | N22: =MIN(M22,L22) -> 0 | O22: =IF(B22>0,ABS(L22-M22),0) -> 3903 | P22: =IF(B22<0,ABS(L22-M22),0) -> 0 | Q22: =IF(AND($E22>0,$B22>0),$E22,NA()) -> 3181 | R22: =IF(AND($E22>0,$B22<0),$E22,NA()) -> #N/A | S22: =IF(AND($E22<0,$B22<0),$E22,NA()) -> #N/A | T22: =IF(AND($E22<0,$B22>0),$E22,NA()) -> #N/A | U22: =IF(AND($F22>0,$B22>0),$F22,NA()) -> 440.58172 | V22: =IF(AND($F22>0,$B22<0),$F22,NA()) -> #N/A | W22: =IF(AND($F22<0,$B22<0),$F22,NA()) -> #N/A | X22: =IF(AND($F22<0,$B22>0),$F22,NA()) -> #N/A | Z22: =I22/$Y$13 -> 0 | AA22: =J22/$Y$13 -> 0.011624724 | AB22: =IF(ISNA(J22),"",TEXT(J22,"#,##0")) -> 722 | AC22: =K22/$Y$13 -> 0 | AD22: =IF(ISNA(K22),"",TEXT(K22,"#,##0")) -> 0 | AE22: =N22/$Y$13 -> 0 | AF22: =O22/$Y$13 -> 0.062841134 | AG22: =IF(ISNA(O22),"",TEXT(O22,"#,##0")) -> 3,903 | AH22: =P22/$Y$13 -> 0 | AI22: =IF(ISNA(P22),"",TEXT(P22,"#,##0")) -> 0 | AJ22: =E22/$Y$13 -> 0.05121641 | AK22: =IF(ISNA(E22),"",TEXT(E22,"+0;-0")) -> +3181 | AL22: =Q22/$Y$13 -> 0.05121641 | AM22: =R22/$Y$13 -> #N/A | AN22: =S22/$Y$13 -> #N/A | AO22: =T22/$Y$13 -> #N/A | AP22: =IF(ISNA(F22),NA(),MEDIAN(-31.5,F22,238.5)) -> 238.5 | AQ22: =IF(ISNA(U22),NA(),MEDIAN(-31.5,U22,238.5)) -> 238.5 | AR22: =IF(ISNA(V22),NA(),MEDIAN(-31.5,V22,238.5)) -> #N/A | AS22: =IF(ISNA(W22),NA(),MEDIAN(-31.5,W22,238.5)) -> #N/A | AT22: =IF(ISNA(X22),NA(),MEDIAN(-31.5,X22,238.5)) -> #N/A | AU22: =IF(ISNA(F22),"",IF(F22>265,TEXT(F22,"+0;-0")&REPT(_xlfn.UNICHAR(9658),MIN(3,MAX(1,INT(F22/265)))),IF(F22<-35,REPT(_xlfn.UNICHAR(9668),MIN(3,MAX(1,INT(-F22/35))))&TEXT(F22,"+0;-0"),TEXT(F22,"+0;-0")))) -> +441►

Sheet C13D
A1: Entity | B1: The Progressive Corporation
A2: Measure | B2: Net premiums written
A3: Unit | B3: $m, relative variance in % from the monthly average
A4: Period | B4: 2011..2025
A5: Reference | B5: AVG
A6: Message | B6: Every month of 2025 sits above the fifteen-year average, Mar by +179%; the book has grown 5.5x since 2011, so the grid reads as a climb from below the line to well above it
A7: Subject | B7: =B2&IF(B3="",""," in "&B3) -> Net premiums written in $m, relative variance in % from the monthly average
A9: Location | B9: Jan | C9: Feb | D9: Mar | E9: Apr | F9: May | G9: Jun | H9: Jul | I9: Aug | J9: Sep | K9: Oct | L9: Nov | M9: Dec
A10: Scenario | B10: AC | C10: AC | D10: AC | E10: AC | F10: AC | G10: AC | H10: AC | I10: AC | J10: AC | K10: AC | L10: AC | M10: AC
A11: 2011 | B11: 1375 | C11: 1302.9 | D11: 1222.1 | E11: 1540.4 | F11: 1134.6 | G11: 1162 | H11: 1496.1 | I11: 1206.4 | J11: 1169 | K11: 1454.7 | L11: 1071.9 | M11: 1011.5
A12: 2012 | B12: 1458.3 | C12: 1379.2 | D12: 1325 | E12: 1672 | F12: 1217.4 | G12: 1239.7 | H12: 1648 | I12: 1285.5 | J12: 1308.3 | K12: 1571.9 | L12: 1129.9 | M12: 1137.5
A13: 2013 | B13: 1537.8 | C13: 1492.6 | D13: 1419 | E13: 1782 | F13: 1281.6 | G13: 1323.5 | H13: 1732.2 | I13: 1368.1 | J13: 1354.3 | K13: 1659.8 | L13: 1194.8 | M13: 1194
A14: 2014 | B14: 1578.4 | C14: 1538.7 | D14: 1563.9 | E14: 1877.2 | F14: 1372 | G14: 1378.5 | H14: 1809.7 | I14: 1499.4 | J14: 1423.2 | K14: 1745.8 | L14: 1298.9 | M14: 1568.9
A15: 2015 | B15: 1773.6 | C15: 1686.9 | D15: 1606.3 | E15: 2062.7 | F15: 1581.4 | G15: 1602 | H15: 2011.5 | I15: 1678.1 | J15: 1723 | K15: 1946 | L15: 1500.1 | M15: 1392.4
A16: 2016 | B16: 2025.8 | C16: 1933.5 | D16: 1859.1 | E16: 2325.7 | F16: 1748.3 | G16: 1860.6 | H16: 2276.4 | I16: 1910.7 | J16: 1861.9 | K16: 2259.2 | L16: 1683.3 | M16: 1609
A17: 2017 | B17: 2241.9 | C17: 2201.3 | D17: 2047.8 | E17: 2704 | F17: 2013.2 | G17: 2028.9 | H17: 2708.7 | I17: 2211.8 | J17: 2221.9 | K17: 2758.2 | L17: 2022.1 | M17: 1972.3
A18: 2018 | B18: 2729.2 | C18: 2700.9 | D18: 2538.7 | E18: 3226.9 | F18: 2412.8 | G18: 2455.6 | H18: 3285.8 | I18: 2591.3 | J18: 2726.9 | K18: 3251.4 | L18: 2328 | M18: 2362.4
A19: 2019 | B19: 3173.2 | C19: 3107 | D19: 2959.7 | E19: 3669.8 | F19: 2662.7 | G19: 2794 | H19: 3675.6 | I19: 2921.3 | J19: 3024.3 | K19: 3655.7 | L19: 2596.1 | M19: 3338.5
A20: 2020 | B20: 3606.3 | C20: 3404.2 | D20: 2860.8 | E20: 3764.2 | F20: 3174.2 | G20: 3201.6 | H20: 4109.3 | I20: 3437.7 | J20: 3468.1 | K20: 3795.3 | L20: 2957.9 | M20: 2789.1
A21: 2021 | B21: 4104.2 | C21: 3852.4 | D21: 3772.5 | E21: 4450.6 | F21: 3402.4 | G21: 3627.3 | H21: 4551.6 | I21: 3890.9 | J21: 4004 | K21: 4346.6 | L21: 3289.4 | M21: 3113.3
A22: 2022 | B22: 4585.2 | C22: 4625.7 | D22: 3970.1 | E22: 4820.7 | F22: 3724.3 | G22: 3877.1 | H22: 4929.4 | I22: 4081.1 | J22: 4007.3 | K22: 5187.1 | L22: 3699.1 | M22: 3574
... A25: 2025 | B25: 6481 | C25: 6684 | D25: 9041 | E25: 6837 | F25: 6634 | G25: 6605 | H25: 7057 | I25: 7199 | J25: 7128 | K25: 7002 | L25: 6193 | M25: 6313
A26: average 15 years | B26: =AVERAGE(B11:B25) -> 3166.5133 | C26: =AVERAGE(C11:C25) -> 3179.1733 | D26: =AVERAGE(D11:D25) -> 3243.4533 | E26: =AVERAGE(E11:E25) -> 3532.44 | F26: =AVERAGE(F11:F25) -> 2843.6933 | G26: =AVERAGE(G11:G25) -> 2881.6267 | H26: =AVERAGE(H11:H25) -> 3574.6867 | I26: =AVERAGE(I11:I25) -> 3102.1467 | ... M26: =AVERAGE(M11:M25) -> 2814.3867
P31: ENGINE - do not edit
P32: grid rows | Q32: 4
B33: ΔØ % | P33: grid cols | Q33: 4
A34: Panel | B34: Jan | C34: Feb | D34: Mar | E34: Apr | F34: May | G34: Jun | H34: Jul | I34: Aug | J34: Sep | K34: Oct | L34: Nov | M34: Dec | P34: periods | Q34: 12
A35: 2011 | B35: =(B11-B26)/B26*100 -> -56.576845 | C35: =(C11-C26)/C26*100 -> -59.017648 | D35: =(D11-D26)/D26*100 -> -62.321024 | E35: =(E11-E26)/E26*100 -> -56.392748 | F35: =(F11-F26)/F26*100 -> -60.101183 | G35: =(G11-G26)/G26*100 -> -59.675554 | H35: =(H11-H26)/H26*100 -> -58.147381 | I35: =(I11-I26)/I26*100 -> -61.110801 | ... M35: =(M11-M26)/M26*100 -> -64.059665 | P35: elements | Q35: 1
A36: 2012 | B36: =(B12-B26)/B26*100 -> -53.946191 | C36: =(C12-C26)/C26*100 -> -56.617653 | D36: =(D12-D26)/D26*100 -> -59.14848 | E36: =(E12-E26)/E26*100 -> -52.667278 | F36: =(F12-F26)/F26*100 -> -57.189477 | G36: =(G12-G26)/G26*100 -> -56.97916 | H36: =(H12-H26)/H26*100 -> -53.898057 | I36: =(I12-I26)/I26*100 -> -58.560953 | ... M36: =(M12-M26)/M26*100 -> -59.582668 | P36: blocks | Q36: 4
A37: 2013 | B37: =(B13-B26)/B26*100 -> -51.435543 | C37: =(C13-C26)/C26*100 -> -53.050688 | D37: =(D13-D26)/D26*100 -> -56.250334 | E37: =(E13-E26)/E26*100 -> -49.553283 | F37: =(F13-F26)/F26*100 -> -54.931849 | G37: =(G13-G26)/G26*100 -> -54.07108 | H37: =(H13-H26)/H26*100 -> -51.542606 | I37: =(I13-I26)/I26*100 -> -55.898281 | ... M37: =(M13-M26)/M26*100 -> -57.575126 | P37: bands | Q37: 4
A38: 2014 | B38: =(B14-B26)/B26*100 -> -50.153376 | C38: =(C14-C26)/C26*100 -> -51.600626 | D38: =(D14-D26)/D26*100 -> -51.782873 | E38: =(E14-E26)/E26*100 -> -46.858262 | F38: =(F14-F26)/F26*100 -> -51.752885 | G38: =(G14-G26)/G26*100 -> -52.162436 | H38: =(H14-H26)/H26*100 -> -49.374584 | I38: =(I14-I26)/I26*100 -> -51.665728 | ... M38: =(M14-M26)/M26*100 -> -44.254284 | P38: sub-slots | Q38: 1
A39: 2015 | B39: =(B15-B26)/B26*100 -> -43.988867 | C39: =(C15-C26)/C26*100 -> -46.939037 | D39: =(D15-D26)/D26*100 -> -50.475625 | E39: =(E15-E26)/E26*100 -> -41.606935 | F39: =(F15-F26)/F26*100 -> -44.389222 | G39: =(G15-G26)/G26*100 -> -44.4064 | H39: =(H15-H26)/H26*100 -> -43.729334 | I39: =(I15-I26)/I26*100 -> -45.905201 | ... M39: =(M15-M26)/M26*100 -> -50.525633 | P39: block slots | Q39: 12
A40: 2016 | B40: =(B16-B26)/B26*100 -> -36.024271 | C40: =(C16-C26)/C26*100 -> -39.182303 | D40: =(D16-D26)/D26*100 -> -42.681463 | E40: =(E16-E26)/E26*100 -> -34.161656 | F40: =(F16-F26)/F26*100 -> -38.520094 | G40: =(G16-G26)/G26*100 -> -35.432302 | H40: =(H16-H26)/H26*100 -> -36.318894 | I40: =(I16-I26)/I26*100 -> -38.407168 | ... M40: =(M16-M26)/M26*100 -> -42.829462 | P40: spacers | Q40: 1
A41: 2017 | B41: =(B17-B26)/B26*100 -> -29.19973 | C41: =(C17-C26)/C26*100 -> -30.75873 | D41: =(D17-D26)/D26*100 -> -36.86359 | E41: =(E17-E26)/E26*100 -> -23.452345 | F41: =(F17-F26)/F26*100 -> -29.204743 | G41: =(G17-G26)/G26*100 -> -29.591851 | H41: =(H17-H26)/H26*100 -> -24.225527 | I41: =(I17-I26)/I26*100 -> -28.700986 | ... M41: =(M17-M26)/M26*100 -> -29.920788 | P41: lead | Q41: 3
A42: 2018 | B42: =(B18-B26)/B26*100 -> -13.810563 | C42: =(C18-C26)/C26*100 -> -15.043953 | D42: =(D18-D26)/D26*100 -> -21.728487 | E42: =(E18-E26)/E26*100 -> -8.6495454 | F42: =(F18-F26)/F26*100 -> -15.152595 | G42: =(G18-G26)/G26*100 -> -14.784242 | H42: =(H18-H26)/H26*100 -> -8.0814542 | I42: =(I18-I26)/I26*100 -> -16.467521 | ... M42: =(M18-M26)/M26*100 -> -16.059864 | P42: band frac | Q42: 0.82
A43: 2019 | B43: =(B19-B26)/B26*100 -> 0.21116812 | C43: =(C19-C26)/C26*100 -> -2.2701918 | D43: =(D19-D26)/D26*100 -> -8.7484944 | E43: =(E19-E26)/E26*100 -> 3.8885303 | F43: =(F19-F26)/F26*100 -> -6.3647276 | G43: =(G19-G26)/G26*100 -> -3.0408751 | H43: =(H19-H26)/H26*100 -> 2.822998 | I43: =(I19-I26)/I26*100 -> -5.8297265 | ... M43: =(M19-M26)/M26*100 -> 18.622648 | P43: min raw | Q43: =MIN(0,MIN($B$35:$M$50)) -> -64.059665
A44: 2020 | B44: =(B20-B26)/B26*100 -> 13.888673 | C44: =(C20-C26)/C26*100 -> 7.0781503 | D44: =(D20-D26)/D26*100 -> -11.797714 | E44: =(E20-E26)/E26*100 -> 6.5609041 | F44: =(F20-F26)/F26*100 -> 11.622444 | G44: =(G20-G26)/G26*100 -> 11.103914 | H44: =(H20-H26)/H26*100 -> 14.95553 | I44: =(I20-I26)/I26*100 -> 10.816811 | ... M44: =(M20-M26)/M26*100 -> -0.89847877 | P44: max raw | Q44: =MAX($B$35:$M$50) -> 178.74611
A45: 2021 | B45: =(B21-B26)/B26*100 -> 29.612592 | C45: =(C21-C26)/C26*100 -> 21.176155 | D45: =(D21-D26)/D26*100 -> 16.311216 | E45: =(E21-E26)/E26*100 -> 25.992232 | F45: =(F21-F26)/F26*100 -> 19.647219 | G45: =(G21-G26)/G26*100 -> 25.87682 | H45: =(H21-H26)/H26*100 -> 27.328642 | I45: =(I21-I26)/I26*100 -> 25.426049 | ... M45: =(M21-M26)/M26*100 -> 10.620905 | P45: step | Q45: =10^INT(LOG10(MAX(0.000000001,$Q$44-$Q$43)))/2 -> 50
A46: 2022 | B46: =(B22-B26)/B26*100 -> 44.802801 | C46: =(C22-C26)/C26*100 -> 45.500088 | D46: =(D22-D26)/D26*100 -> 22.403488 | E46: =(E22-E26)/E26*100 -> 36.469409 | F46: =(F22-F26)/F26*100 -> 30.967005 | G46: =(G22-G26)/G26*100 -> 34.545534 | H46: =(H22-H26)/H26*100 -> 37.897401 | I46: =(I22-I26)/I26*100 -> 31.557287 | ... M46: =(M22-M26)/M26*100 -> 26.990369 | P46: vmin | Q46: =FLOOR($Q$43-($Q$44-$Q$43)*0.1,$Q$45) -> -100
A47: 2023 | B47: =(B23-B26)/B26*100 -> 68.390259 | C47: =(C23-C26)/C26*100 -> 90.546389 | D47: =(D23-D26)/D26*100 -> 45.51774 | E47: =(E23-E26)/E26*100 -> 71.988767 | F47: =(F23-F26)/F26*100 -> 51.964347 | G47: =(G23-G26)/G26*100 -> 49.918796 | H47: =(H23-H26)/H26*100 -> 66.462142 | I47: =(I23-I26)/I26*100 -> 52.919914 | ... M47: =(M23-M26)/M26*100 -> 73.249115 | P47: vmax | Q47: =CEILING($Q$44+($Q$44-$Q$43)*0.1,$Q$45) -> 250
A48: 2024 | B48: =(B24-B26)/B26*100 -> 73.556825 | C48: =(C24-C26)/C26*100 -> 79.936713 | D48: =(D24-D26)/D26*100 -> 138.81953 | E48: =(E24-E26)/E26*100 -> 74.893275 | F48: =(F24-F26)/F26*100 -> 110.11759 | G48: =(G24-G26)/G26*100 -> 99.488021 | H48: =(H24-H26)/H26*100 -> 78.435219 | I48: =(I24-I26)/I26*100 -> 109.7612 | ... M48: =(M24-M26)/M26*100 -> 111.91118 | P48: span | Q48: =MAX(0.000000001,$Q$47-$Q$46) -> 350
A49: 2025 | B49: =(B25-B26)/B26*100 -> 104.67307 | C49: =(C25-C26)/C26*100 -> 110.24333 | D49: =(D25-D26)/D26*100 -> 178.74611 | E49: =(E25-E26)/E26*100 -> 93.548935 | F49: =(F25-F26)/F26*100 -> 133.28817 | G49: =(G25-G26)/G26*100 -> 129.21082 | H49: =(H25-H26)/H26*100 -> 97.415904 | I49: =(I25-I26)/I26*100 -> 132.06511 | ... M49: =(M25-M26)/M26*100 -> 124.31175 | P49: zero offset | Q49: =(0-$Q$46)/$Q$48*$Q$42 -> 0.23428571
P52: x | Q52: pos | R52: blk | S52: sub | T52: k | U52: e | V52: sep | W52: kx | X52: blkx | Y52: cat | Z52: ΔØ % b0 + | AA52: ΔØ % b0 - | AB52: ΔØ % b1 + | AC52: ΔØ % b1 - | AD52: ΔØ % b2 + | AE52: ΔØ % b2 - | AF52: ΔØ % b3 + | AG52: ΔØ % b3 - | AI52: stem ΔØ % b0 + | AJ52: stem ΔØ % b0 - | AK52: stem ΔØ % b1 + | AL52: stem ΔØ % b1 - | AM52: stem ΔØ % b2 + | AN52: stem ΔØ % b2 - | AO52: stem ΔØ % b3 + | AP52: stem ΔØ % b3 - | AR52: label ΔØ % b0 + | AS52: label ΔØ % b0 - | AT52: label ΔØ % b1 + | AU52: label ΔØ % b1 - | AV52: label ΔØ % b2 + | AW52: label ΔØ % b2 - | AX52: label ΔØ % b3 + | AY52: label ΔØ % b3 - | BA52: divider | BD52: bandrule | BG52: baseline | BJ52: ptitle | BN52: ytick
P53: 1 | Q53: =P53-$Q$41 -> -2 | R53: =IF(Q53<=0,-1,INT((Q53-1)/($Q$39+$Q$40))) -> -1 | S53: =IF(Q53<=0,-1,MOD(Q53-1,($Q$39+$Q$40))) -> -1 | T53: =IF(OR(S53<0,S53>=$Q$39),-1,INT(S53/$Q$38)) -> -1 | U53: =IF(OR(S53<0,S53>=$Q$39),-1,MOD(S53,$Q$38)) -> -1 | V53: =IF(OR(Q53<=0,S53<0,S53>=$Q$39,R53>=$Q$36),1,0) -> 1 | W53: =IF(V53=1,-1,T53) -> -1 | X53: =IF(V53=1,-1,R53) -> -1 | Y53: =IF(V53=1,"",IF(AND(MOD(W53,3)=0,U53=INT(($Q$38-1)/2)),INDEX($B$34:$M$34,W53+1),"")) | Z53: =IF(V53=1,NA(),IF(INDEX($B$35:$M$50,($Q$32-1-0)*$Q$33+X53+1,0*$Q$34+W53+1)="",NA(),IF(INDEX($B$35:$M$50,($Q$32-1-0)*$Q$33+X53+1,0*$Q$34+W53+1)>=0,0+(INDEX($B$35:$M$50,($Q$32-1-0)*$Q$33+X53+1,0*$Q$34+W53+1)-$Q$46)/$Q$48*$Q$42,NA()))) -> #N/A | AA53: =IF(V53=1,NA(),IF(INDEX($B$35:$M$50,($Q$32-1-0)*$Q$33+X53+1,0*$Q$34+W53+1)="",NA(),IF(INDEX($B$35:$M$50,($Q$32-1-0)*$Q$33+X53+1,0*$Q$34+W53+1)<0,0+(INDEX($B$35:$M$50,($Q$32-1-0)*$Q$33+X53+1,0*$Q$34+W53+1)-$Q$46)/$Q$48*$Q$42,NA()))) -> #N/A | AB53: =IF(V53=1,NA(),IF(INDEX($B$35:$M$50,($Q$32-1-1)*$Q$33+X53+1,0*$Q$34+W53+1)="",NA(),IF(INDEX($B$35:$M$50,($Q$32-1-1)*$Q$33+X53+1,0*$Q$34+W53+1)>=0,1+(INDEX($B$35:$M$50,($Q$32-1-1)*$Q$33+X53+1,0*$Q$34+W53+1)-$Q$46)/$Q$48*$Q$42,NA()))) -> #N/A | AC53: =IF(V53=1,NA(),IF(INDEX($B$35:$M$50,($Q$32-1-1)*$Q$33+X53+1,0*$Q$34+W53+1)="",NA(),IF(INDEX($B$35:$M$50,($Q$32-1-1)*$Q$33+X53+1,0*$Q$34+W53+1)<0,1+(INDEX($B$35:$M$50,($Q$32-1-1)*$Q$33+X53+1,0*$Q$34+W53+1)-$Q$46)/$Q$48*$Q$42,NA()))) -> #N/A | AD53: =IF(V53=1,NA(),IF(INDEX($B$35:$M$50,($Q$32-1-2)*$Q$33+X53+1,0*$Q$34+W53+1)="",NA(),IF(INDEX($B$35:$M$50,($Q$32-1-2)*$Q$33+X53+1,0*$Q$34+W53+1)>=0,2+(INDEX($B$35:$M$50,($Q$32-1-2)*$Q$33+X53+1,0*$Q$34+W53+1)-$Q$46)/$Q$48*$Q$42,NA()))) -> #N/A | AE53: =IF(V53=1,NA(),IF(INDEX($B$35:$M$50,($Q$32-1-2)*$Q$33+X53+1,0*$Q$34+W53+1)="",NA(),IF(INDEX($B$35:$M$50,($Q$32-1-2)*$Q$33+X53+1,0*$Q$34+W53+1)<0,2+(INDEX($B$35:$M$50,($Q$32-1-2)*$Q$33+X53+1,0*$Q$34+W53+1)-$Q$46)/$Q$48*$Q$42,NA()))) -> #N/A | AF53: =IF(V53=1,NA(),IF(INDEX($B$35:$M$50,($Q$32-1-3)*$Q$33+X53+1,0*$Q$34+W53+1)="",NA(),IF(INDEX($B$35:$M$50,($Q$32-1-3)*$Q$33+X53+1,0*$Q$34+W53+1)>=0,3+(INDEX($B$35:$M$50,($Q$32-1-3)*$Q$33+X53+1,0*$Q$34+W53+1)-$Q$46)/$Q$48*$Q$42,NA()))) -> #N/A | AG53: =IF(V53=1,NA(),IF(INDEX($B$35:$M$50,($Q$32-1-3)*$Q$33+X53+1,0*$Q$34+W53+1)="",NA(),IF(INDEX($B$35:$M$50,($Q$32-1-3)*$Q$33+X53+1,0*$Q$34+W53+1)<0,3+(INDEX($B$35:$M$50,($Q$32-1-3)*$Q$33+X53+1,0*$Q$34+W53+1)-$Q$46)/$Q$48*$Q$42,NA()))) -> #N/A | AI53: =IF(V53=1,0,IF(INDEX($B$35:$M$50,($Q$32-1-0)*$Q$33+X53+1,0*$Q$34+W53+1)="",0,IF(INDEX($B$35:$M$50,($Q$32-1-0)*$Q$33+X53+1,0*$Q$34+W53+1)>=0,ABS(INDEX($B$35:$M$50,($Q$32-1-0)*$Q$33+X53+1,0*$Q$34+W53+1))/$Q$48*$Q$42,0))) -> 0 | AJ53: =IF(V53=1,0,IF(INDEX($B$35:$M$50,($Q$32-1-0)*$Q$33+X53+1,0*$Q$34+W53+1)="",0,IF(INDEX($B$35:$M$50,($Q$32-1-0)*$Q$33+X53+1,0*$Q$34+W53+1)<0,ABS(INDEX($B$35:$M$50,($Q$32-1-0)*$Q$33+X53+1,0*$Q$34+W53+1))/$Q$48*$Q$42,0))) -> 0 | AK53: =IF(V53=1,0,IF(INDEX($B$35:$M$50,($Q$32-1-1)*$Q$33+X53+1,0*$Q$34+W53+1)="",0,IF(INDEX($B$35:$M$50,($Q$32-1-1)*$Q$33+X53+1,0*$Q$34+W53+1)>=0,ABS(INDEX($B$35:$M$50,($Q$32-1-1)*$Q$33+X53+1,0*$Q$34+W53+1))/$Q$48*$Q$42,0))) -> 0 | AL53: =IF(V53=1,0,IF(INDEX($B$35:$M$50,($Q$32-1-1)*$Q$33+X53+1,0*$Q$34+W53+1)="",0,IF(INDEX($B$35:$M$50,($Q$32-1-1)*$Q$33+X53+1,0*$Q$34+W53+1)<0,ABS(INDEX($B$35:$M$50,($Q$32-1-1)*$Q$33+X53+1,0*$Q$34+W53+1))/$Q$48*$Q$42,0))) -> 0 | AM53: =IF(V53=1,0,IF(INDEX($B$35:$M$50,($Q$32-1-2)*$Q$33+X53+1,0*$Q$34+W53+1)="",0,IF(INDEX($B$35:$M$50,($Q$32-1-2)*$Q$33+X53+1,0*$Q$34+W53+1)>=0,ABS(INDEX($B$35:$M$50,($Q$32-1-2)*$Q$33+X53+1,0*$Q$34+W53+1))/$Q$48*$Q$42,0))) -> 0 | AN53: =IF(V53=1,0,IF(INDEX($B$35:$M$50,($Q$32-1-2)*$Q$33+X53+1,0*$Q$34+W53+1)="",0,IF(INDEX($B$35:$M$50,($Q$32-1-2)*$Q$33+X53+1,0*$Q$34+W53+1)<0,ABS(INDEX($B$35:$M$50,($Q$32-1-2)*$Q$33+X53+1,0*$Q$34+W53+1))/$Q$48*$Q$42,0))) -> 0 | AO53: =IF(V53=1,0,IF(INDEX($B$35:$M$50,($Q$32-1-3)*$Q$33+X53+1,0*$Q$34+W53+1)="",0,IF(INDEX($B$35:$M$50,($Q$32-1-3)*$Q$33+X53+1,0*$Q$34+W53+1)>=0,ABS(INDEX($B$35:$M$50,($Q$32-1-3)*$Q$33+X53+1,0*$Q$34+W53+1))/$Q$48*$Q$42,0))) -> 0 | AP53: =IF(V53=1,0,IF(INDEX($B$35:$M$50,($Q$32-1-3)*$Q$33+X53+1,0*$Q$34+W53+1)="",0,IF(INDEX($B$35:$M$50,($Q$32-1-3)*$Q$33+X53+1,0*$Q$34+W53+1)<0,ABS(INDEX($B$35:$M$50,($Q$32-1-3)*$Q$33+X53+1,0*$Q$34+W53+1))/$Q$48*$Q$42,0))) -> 0 | AR53: =IF(V53=1,"",IF(INDEX($B$35:$M$50,($Q$32-1-0)*$Q$33+X53+1,0*$Q$34+W53+1)="","",IF(INDEX($B$35:$M$50,($Q$32-1-0)*$Q$33+X53+1,0*$Q$34+W53+1)>=0,TEXT(INDEX($B$35:$M$50,($Q$32-1-0)*$Q$33+X53+1,0*$Q$34+W53+1),"+0;-0;0"),""))) | AS53: =IF(V53=1,"",IF(INDEX($B$35:$M$50,($Q$32-1-0)*$Q$33+X53+1,0*$Q$34+W53+1)="","",IF(INDEX($B$35:$M$50,($Q$32-1-0)*$Q$33+X53+1,0*$Q$34+W53+1)<0,TEXT(INDEX($B$35:$M$50,($Q$32-1-0)*$Q$33+X53+1,0*$Q$34+W53+1),"+0;-0;0"),""))) | AT53: =IF(V53=1,"",IF(INDEX($B$35:$M$50,($Q$32-1-1)*$Q$33+X53+1,0*$Q$34+W53+1)="","",IF(INDEX($B$35:$M$50,($Q$32-1-1)*$Q$33+X53+1,0*$Q$34+W53+1)>=0,TEXT(INDEX($B$35:$M$50,($Q$32-1-1)*$Q$33+X53+1,0*$Q$34+W53+1),"+0;-0;0"),""))) | AU53: =IF(V53=1,"",IF(INDEX($B$35:$M$50,($Q$32-1-1)*$Q$33+X53+1,0*$Q$34+W53+1)="","",IF(INDEX($B$35:$M$50,($Q$32-1-1)*$Q$33+X53+1,0*$Q$34+W53+1)<0,TEXT(INDEX($B$35:$M$50,($Q$32-1-1)*$Q$33+X53+1,0*$Q$34+W53+1),"+0;-0;0"),""))) | AV53: =IF(V53=1,"",IF(INDEX($B$35:$M$50,($Q$32-1-2)*$Q$33+X53+1,0*$Q$34+W53+1)="","",IF(INDEX($B$35:$M$50,($Q$32-1-2)*$Q$33+X53+1,0*$Q$34+W53+1)>=0,TEXT(INDEX($B$35:$M$50,($Q$32-1-2)*$Q$33+X53+1,0*$Q$34+W53+1),"+0;-0;0"),""))) | AW53: =IF(V53=1,"",IF(INDEX($B$35:$M$50,($Q$32-1-2)*$Q$33+X53+1,0*$Q$34+W53+1)="","",IF(INDEX($B$35:$M$50,($Q$32-1-2)*$Q$33+X53+1,0*$Q$34+W53+1)<0,TEXT(INDEX($B$35:$M$50,($Q$32-1-2)*$Q$33+X53+1,0*$Q$34+W53+1),"+0;-0;0"),""))) | AX53: =IF(V53=1,"",IF(INDEX($B$35:$M$50,($Q$32-1-3)*$Q$33+X53+1,0*$Q$34+W53+1)="","",IF(INDEX($B$35:$M$50,($Q$32-1-3)*$Q$33+X53+1,0*$Q$34+W53+1)>=0,TEXT(INDEX($B$35:$M$50,($Q$32-1-3)*$Q$33+X53+1,0*$Q$34+W53+1),"+0;-0;0"),""))) | AY53: =IF(V53=1,"",IF(INDEX($B$35:$M$50,($Q$32-1-3)*$Q$33+X53+1,0*$Q$34+W53+1)="","",IF(INDEX($B$35:$M$50,($Q$32-1-3)*$Q$33+X53+1,0*$Q$34+W53+1)<0,TEXT(INDEX($B$35:$M$50,($Q$32-1-3)*$Q$33+X53+1,0*$Q$34+W53+1),"+0;-0;0"),""))) | BA53: 16 | BB53: 0 | BD53: 0.5 | BE53: 0.91 | BG53: 3.5 | BH53: =IF(OR($Q$46>0,$Q$47<0),NA(),0+$Q$49) -> 0.23428571 | BJ53: 4 | BK53: =3+$Q$42+0.03 -> 3.85 | BL53: ='C13D'!$A$35 -> 2011 | BN53: 3.35 | BO53: =0+0*$Q$42 -> 0 | BP53: =TEXT($Q$46+($Q$47-$Q$46)*0,"#,##0") -> -100
P54: 2 | Q54: =P54-$Q$41 -> -1 | R54: =IF(Q54<=0,-1,INT((Q54-1)/($Q$39+$Q$40))) -> -1 | S54: =IF(Q54<=0,-1,MOD(Q54-1,($Q$39+$Q$40))) -> -1 | T54: =IF(OR(S54<0,S54>=$Q$39),-1,INT(S54/$Q$38)) -> -1 | U54: =IF(OR(S54<0,S54>=$Q$39),-1,MOD(S54,$Q$38)) -> -1 | V54: =IF(OR(Q54<=0,S54<0,S54>=$Q$39,R54>=$Q$36),1,0) -> 1 | W54: =IF(V54=1,-1,T54) -> -1 | X54: =IF(V54=1,-1,R54) -> -1 | Y54: =IF(V54=1,"",IF(AND(MOD(W54,3)=0,U54=INT(($Q$38-1)/2)),INDEX($B$34:$M$34,W54+1),"")) | Z54: =IF(V54=1,NA(),IF(INDEX($B$35:$M$50,($Q$32-1-0)*$Q$33+X54+1,0*$Q$34+W54+1)="",NA(),IF(INDEX($B$35:$M$50,($Q$32-1-0)*$Q$33+X54+1,0*$Q$34+W54+1)>=0,0+(INDEX($B$35:$M$50,($Q$32-1-0)*$Q$33+X54+1,0*$Q$34+W54+1)-$Q$46)/$Q$48*$Q$42,NA()))) -> #N/A | AA54: =IF(V54=1,NA(),IF(INDEX($B$35:$M$50,($Q$32-1-0)*$Q$33+X54+1,0*$Q$34+W54+1)="",NA(),IF(INDEX($B$35:$M$50,($Q$32-1-0)*$Q$33+X54+1,0*$Q$34+W54+1)<0,0+(INDEX($B$35:$M$50,($Q$32-1-0)*$Q$33+X54+1,0*$Q$34+W54+1)-$Q$46)/$Q$48*$Q$42,NA()))) -> #N/A | AB54: =IF(V54=1,NA(),IF(INDEX($B$35:$M$50,($Q$32-1-1)*$Q$33+X54+1,0*$Q$34+W54+1)="",NA(),IF(INDEX($B$35:$M$50,($Q$32-1-1)*$Q$33+X54+1,0*$Q$34+W54+1)>=0,1+(INDEX($B$35:$M$50,($Q$32-1-1)*$Q$33+X54+1,0*$Q$34+W54+1)-$Q$46)/$Q$48*$Q$42,NA()))) -> #N/A | AC54: =IF(V54=1,NA(),IF(INDEX($B$35:$M$50,($Q$32-1-1)*$Q$33+X54+1,0*$Q$34+W54+1)="",NA(),IF(INDEX($B$35:$M$50,($Q$32-1-1)*$Q$33+X54+1,0*$Q$34+W54+1)<0,1+(INDEX($B$35:$M$50,($Q$32-1-1)*$Q$33+X54+1,0*$Q$34+W54+1)-$Q$46)/$Q$48*$Q$42,NA()))) -> #N/A | AD54: =IF(V54=1,NA(),IF(INDEX($B$35:$M$50,($Q$32-1-2)*$Q$33+X54+1,0*$Q$34+W54+1)="",NA(),IF(INDEX($B$35:$M$50,($Q$32-1-2)*$Q$33+X54+1,0*$Q$34+W54+1)>=0,2+(INDEX($B$35:$M$50,($Q$32-1-2)*$Q$33+X54+1,0*$Q$34+W54+1)-$Q$46)/$Q$48*$Q$42,NA()))) -> #N/A | AE54: =IF(V54=1,NA(),IF(INDEX($B$35:$M$50,($Q$32-1-2)*$Q$33+X54+1,0*$Q$34+W54+1)="",NA(),IF(INDEX($B$35:$M$50,($Q$32-1-2)*$Q$33+X54+1,0*$Q$34+W54+1)<0,2+(INDEX($B$35:$M$50,($Q$32-1-2)*$Q$33+X54+1,0*$Q$34+W54+1)-$Q$46)/$Q$48*$Q$42,NA()))) -> #N/A | AF54: =IF(V54=1,NA(),IF(INDEX($B$35:$M$50,($Q$32-1-3)*$Q$33+X54+1,0*$Q$34+W54+1)="",NA(),IF(INDEX($B$35:$M$50,($Q$32-1-3)*$Q$33+X54+1,0*$Q$34+W54+1)>=0,3+(INDEX($B$35:$M$50,($Q$32-1-3)*$Q$33+X54+1,0*$Q$34+W54+1)-$Q$46)/$Q$48*$Q$42,NA()))) -> #N/A | AG54: =IF(V54=1,NA(),IF(INDEX($B$35:$M$50,($Q$32-1-3)*$Q$33+X54+1,0*$Q$34+W54+1)="",NA(),IF(INDEX($B$35:$M$50,($Q$32-1-3)*$Q$33+X54+1,0*$Q$34+W54+1)<0,3+(INDEX($B$35:$M$50,($Q$32-1-3)*$Q$33+X54+1,0*$Q$34+W54+1)-$Q$46)/$Q$48*$Q$42,NA()))) -> #N/A | AI54: =IF(V54=1,0,IF(INDEX($B$35:$M$50,($Q$32-1-0)*$Q$33+X54+1,0*$Q$34+W54+1)="",0,IF(INDEX($B$35:$M$50,($Q$32-1-0)*$Q$33+X54+1,0*$Q$34+W54+1)>=0,ABS(INDEX($B$35:$M$50,($Q$32-1-0)*$Q$33+X54+1,0*$Q$34+W54+1))/$Q$48*$Q$42,0))) -> 0 | AJ54: =IF(V54=1,0,IF(INDEX($B$35:$M$50,($Q$32-1-0)*$Q$33+X54+1,0*$Q$34+W54+1)="",0,IF(INDEX($B$35:$M$50,($Q$32-1-0)*$Q$33+X54+1,0*$Q$34+W54+1)<0,ABS(INDEX($B$35:$M$50,($Q$32-1-0)*$Q$33+X54+1,0*$Q$34+W54+1))/$Q$48*$Q$42,0))) -> 0 | AK54: =IF(V54=1,0,IF(INDEX($B$35:$M$50,($Q$32-1-1)*$Q$33+X54+1,0*$Q$34+W54+1)="",0,IF(INDEX($B$35:$M$50,($Q$32-1-1)*$Q$33+X54+1,0*$Q$34+W54+1)>=0,ABS(INDEX($B$35:$M$50,($Q$32-1-1)*$Q$33+X54+1,0*$Q$34+W54+1))/$Q$48*$Q$42,0))) -> 0 | AL54: =IF(V54=1,0,IF(INDEX($B$35:$M$50,($Q$32-1-1)*$Q$33+X54+1,0*$Q$34+W54+1)="",0,IF(INDEX($B$35:$M$50,($Q$32-1-1)*$Q$33+X54+1,0*$Q$34+W54+1)<0,ABS(INDEX($B$35:$M$50,($Q$32-1-1)*$Q$33+X54+1,0*$Q$34+W54+1))/$Q$48*$Q$42,0))) -> 0 | AM54: =IF(V54=1,0,IF(INDEX($B$35:$M$50,($Q$32-1-2)*$Q$33+X54+1,0*$Q$34+W54+1)="",0,IF(INDEX($B$35:$M$50,($Q$32-1-2)*$Q$33+X54+1,0*$Q$34+W54+1)>=0,ABS(INDEX($B$35:$M$50,($Q$32-1-2)*$Q$33+X54+1,0*$Q$34+W54+1))/$Q$48*$Q$42,0))) -> 0 | AN54: =IF(V54=1,0,IF(INDEX($B$35:$M$50,($Q$32-1-2)*$Q$33+X54+1,0*$Q$34+W54+1)="",0,IF(INDEX($B$35:$M$50,($Q$32-1-2)*$Q$33+X54+1,0*$Q$34+W54+1)<0,ABS(INDEX($B$35:$M$50,($Q$32-1-2)*$Q$33+X54+1,0*$Q$34+W54+1))/$Q$48*$Q$42,0))) -> 0 | AO54: =IF(V54=1,0,IF(INDEX($B$35:$M$50,($Q$32-1-3)*$Q$33+X54+1,0*$Q$34+W54+1)="",0,IF(INDEX($B$35:$M$50,($Q$32-1-3)*$Q$33+X54+1,0*$Q$34+W54+1)>=0,ABS(INDEX($B$35:$M$50,($Q$32-1-3)*$Q$33+X54+1,0*$Q$34+W54+1))/$Q$48*$Q$42,0))) -> 0 | AP54: =IF(V54=1,0,IF(INDEX($B$35:$M$50,($Q$32-1-3)*$Q$33+X54+1,0*$Q$34+W54+1)="",0,IF(INDEX($B$35:$M$50,($Q$32-1-3)*$Q$33+X54+1,0*$Q$34+W54+1)<0,ABS(INDEX($B$35:$M$50,($Q$32-1-3)*$Q$33+X54+1,0*$Q$34+W54+1))/$Q$48*$Q$42,0))) -> 0 | AR54: =IF(V54=1,"",IF(INDEX($B$35:$M$50,($Q$32-1-0)*$Q$33+X54+1,0*$Q$34+W54+1)="","",IF(INDEX($B$35:$M$50,($Q$32-1-0)*$Q$33+X54+1,0*$Q$34+W54+1)>=0,TEXT(INDEX($B$35:$M$50,($Q$32-1-0)*$Q$33+X54+1,0*$Q$34+W54+1),"+0;-0;0"),""))) | AS54: =IF(V54=1,"",IF(INDEX($B$35:$M$50,($Q$32-1-0)*$Q$33+X54+1,0*$Q$34+W54+1)="","",IF(INDEX($B$35:$M$50,($Q$32-1-0)*$Q$33+X54+1,0*$Q$34+W54+1)<0,TEXT(INDEX($B$35:$M$50,($Q$32-1-0)*$Q$33+X54+1,0*$Q$34+W54+1),"+0;-0;0"),""))) | AT54: =IF(V54=1,"",IF(INDEX($B$35:$M$50,($Q$32-1-1)*$Q$33+X54+1,0*$Q$34+W54+1)="","",IF(INDEX($B$35:$M$50,($Q$32-1-1)*$Q$33+X54+1,0*$Q$34+W54+1)>=0,TEXT(INDEX($B$35:$M$50,($Q$32-1-1)*$Q$33+X54+1,0*$Q$34+W54+1),"+0;-0;0"),""))) | AU54: =IF(V54=1,"",IF(INDEX($B$35:$M$50,($Q$32-1-1)*$Q$33+X54+1,0*$Q$34+W54+1)="","",IF(INDEX($B$35:$M$50,($Q$32-1-1)*$Q$33+X54+1,0*$Q$34+W54+1)<0,TEXT(INDEX($B$35:$M$50,($Q$32-1-1)*$Q$33+X54+1,0*$Q$34+W54+1),"+0;-0;0"),""))) | AV54: =IF(V54=1,"",IF(INDEX($B$35:$M$50,($Q$32-1-2)*$Q$33+X54+1,0*$Q$34+W54+1)="","",IF(INDEX($B$35:$M$50,($Q$32-1-2)*$Q$33+X54+1,0*$Q$34+W54+1)>=0,TEXT(INDEX($B$35:$M$50,($Q$32-1-2)*$Q$33+X54+1,0*$Q$34+W54+1),"+0;-0;0"),""))) | AW54: =IF(V54=1,"",IF(INDEX($B$35:$M$50,($Q$32-1-2)*$Q$33+X54+1,0*$Q$34+W54+1)="","",IF(INDEX($B$35:$M$50,($Q$32-1-2)*$Q$33+X54+1,0*$Q$34+W54+1)<0,TEXT(INDEX($B$35:$M$50,($Q$32-1-2)*$Q$33+X54+1,0*$Q$34+W54+1),"+0;-0;0"),""))) | AX54: =IF(V54=1,"",IF(INDEX($B$35:$M$50,($Q$32-1-3)*$Q$33+X54+1,0*$Q$34+W54+1)="","",IF(INDEX($B$35:$M$50,($Q$32-1-3)*$Q$33+X54+1,0*$Q$34+W54+1)>=0,TEXT(INDEX($B$35:$M$50,($Q$32-1-3)*$Q$33+X54+1,0*$Q$34+W54+1),"+0;-0;0"),""))) | AY54: =IF(V54=1,"",IF(INDEX($B$35:$M$50,($Q$32-1-3)*$Q$33+X54+1,0*$Q$34+W54+1)="","",IF(INDEX($B$35:$M$50,($Q$32-1-3)*$Q$33+X54+1,0*$Q$34+W54+1)<0,TEXT(INDEX($B$35:$M$50,($Q$32-1-3)*$Q$33+X54+1,0*$Q$34+W54+1),"+0;-0;0"),""))) | BA54: 16 | BB54: 4 | BD54: 54.5 | BE54: 0.91 | BG54: 15.5 | BH54: =IF(OR($Q$46>0,$Q$47<0),NA(),0+$Q$49) -> 0.23428571 | BJ54: 17 | BK54: =3+$Q$42+0.03 -> 3.85 | BL54: ='C13D'!$A$36 -> 2012 | BN54: 3.35 | BO54: =0+0.5*$Q$42 -> 0.41 | BP54: =TEXT($Q$46+($Q$47-$Q$46)*0.5,"#,##0") -> 75
P55: 3 | Q55: =P55-$Q$41 -> 0 | R55: =IF(Q55<=0,-1,INT((Q55-1)/($Q$39+$Q$40))) -> -1 | S55: =IF(Q55<=0,-1,MOD(Q55-1,($Q$39+$Q$40))) -> -1 | T55: =IF(OR(S55<0,S55>=$Q$39),-1,INT(S55/$Q$38)) -> -1 | U55: =IF(OR(S55<0,S55>=$Q$39),-1,MOD(S55,$Q$38)) -> -1 | V55: =IF(OR(Q55<=0,S55<0,S55>=$Q$39,R55>=$Q$36),1,0) -> 1 | W55: =IF(V55=1,-1,T55) -> -1 | X55: =IF(V55=1,-1,R55) -> -1 | Y55: =IF(V55=1,"",IF(AND(MOD(W55,3)=0,U55=INT(($Q$38-1)/2)),INDEX($B$34:$M$34,W55+1),"")) | Z55: =IF(V55=1,NA(),IF(INDEX($B$35:$M$50,($Q$32-1-0)*$Q$33+X55+1,0*$Q$34+W55+1)="",NA(),IF(INDEX($B$35:$M$50,($Q$32-1-0)*$Q$33+X55+1,0*$Q$34+W55+1)>=0,0+(INDEX($B$35:$M$50,($Q$32-1-0)*$Q$33+X55+1,0*$Q$34+W55+1)-$Q$46)/$Q$48*$Q$42,NA()))) -> #N/A | AA55: =IF(V55=1,NA(),IF(INDEX($B$35:$M$50,($Q$32-1-0)*$Q$33+X55+1,0*$Q$34+W55+1)="",NA(),IF(INDEX($B$35:$M$50,($Q$32-1-0)*$Q$33+X55+1,0*$Q$34+W55+1)<0,0+(INDEX($B$35:$M$50,($Q$32-1-0)*$Q$33+X55+1,0*$Q$34+W55+1)-$Q$46)/$Q$48*$Q$42,NA()))) -> #N/A | AB55: =IF(V55=1,NA(),IF(INDEX($B$35:$M$50,($Q$32-1-1)*$Q$33+X55+1,0*$Q$34+W55+1)="",NA(),IF(INDEX($B$35:$M$50,($Q$32-1-1)*$Q$33+X55+1,0*$Q$34+W55+1)>=0,1+(INDEX($B$35:$M$50,($Q$32-1-1)*$Q$33+X55+1,0*$Q$34+W55+1)-$Q$46)/$Q$48*$Q$42,NA()))) -> #N/A | AC55: =IF(V55=1,NA(),IF(INDEX($B$35:$M$50,($Q$32-1-1)*$Q$33+X55+1,0*$Q$34+W55+1)="",NA(),IF(INDEX($B$35:$M$50,($Q$32-1-1)*$Q$33+X55+1,0*$Q$34+W55+1)<0,1+(INDEX($B$35:$M$50,($Q$32-1-1)*$Q$33+X55+1,0*$Q$34+W55+1)-$Q$46)/$Q$48*$Q$42,NA()))) -> #N/A | AD55: =IF(V55=1,NA(),IF(INDEX($B$35:$M$50,($Q$32-1-2)*$Q$33+X55+1,0*$Q$34+W55+1)="",NA(),IF(INDEX($B$35:$M$50,($Q$32-1-2)*$Q$33+X55+1,0*$Q$34+W55+1)>=0,2+(INDEX($B$35:$M$50,($Q$32-1-2)*$Q$33+X55+1,0*$Q$34+W55+1)-$Q$46)/$Q$48*$Q$42,NA()))) -> #N/A | AE55: =IF(V55=1,NA(),IF(INDEX($B$35:$M$50,($Q$32-1-2)*$Q$33+X55+1,0*$Q$34+W55+1)="",NA(),IF(INDEX($B$35:$M$50,($Q$32-1-2)*$Q$33+X55+1,0*$Q$34+W55+1)<0,2+(INDEX($B$35:$M$50,($Q$32-1-2)*$Q$33+X55+1,0*$Q$34+W55+1)-$Q$46)/$Q$48*$Q$42,NA()))) -> #N/A | AF55: =IF(V55=1,NA(),IF(INDEX($B$35:$M$50,($Q$32-1-3)*$Q$33+X55+1,0*$Q$34+W55+1)="",NA(),IF(INDEX($B$35:$M$50,($Q$32-1-3)*$Q$33+X55+1,0*$Q$34+W55+1)>=0,3+(INDEX($B$35:$M$50,($Q$32-1-3)*$Q$33+X55+1,0*$Q$34+W55+1)-$Q$46)/$Q$48*$Q$42,NA()))) -> #N/A | AG55: =IF(V55=1,NA(),IF(INDEX($B$35:$M$50,($Q$32-1-3)*$Q$33+X55+1,0*$Q$34+W55+1)="",NA(),IF(INDEX($B$35:$M$50,($Q$32-1-3)*$Q$33+X55+1,0*$Q$34+W55+1)<0,3+(INDEX($B$35:$M$50,($Q$32-1-3)*$Q$33+X55+1,0*$Q$34+W55+1)-$Q$46)/$Q$48*$Q$42,NA()))) -> #N/A | AI55: =IF(V55=1,0,IF(INDEX($B$35:$M$50,($Q$32-1-0)*$Q$33+X55+1,0*$Q$34+W55+1)="",0,IF(INDEX($B$35:$M$50,($Q$32-1-0)*$Q$33+X55+1,0*$Q$34+W55+1)>=0,ABS(INDEX($B$35:$M$50,($Q$32-1-0)*$Q$33+X55+1,0*$Q$34+W55+1))/$Q$48*$Q$42,0))) -> 0 | AJ55: =IF(V55=1,0,IF(INDEX($B$35:$M$50,($Q$32-1-0)*$Q$33+X55+1,0*$Q$34+W55+1)="",0,IF(INDEX($B$35:$M$50,($Q$32-1-0)*$Q$33+X55+1,0*$Q$34+W55+1)<0,ABS(INDEX($B$35:$M$50,($Q$32-1-0)*$Q$33+X55+1,0*$Q$34+W55+1))/$Q$48*$Q$42,0))) -> 0 | AK55: =IF(V55=1,0,IF(INDEX($B$35:$M$50,($Q$32-1-1)*$Q$33+X55+1,0*$Q$34+W55+1)="",0,IF(INDEX($B$35:$M$50,($Q$32-1-1)*$Q$33+X55+1,0*$Q$34+W55+1)>=0,ABS(INDEX($B$35:$M$50,($Q$32-1-1)*$Q$33+X55+1,0*$Q$34+W55+1))/$Q$48*$Q$42,0))) -> 0 | AL55: =IF(V55=1,0,IF(INDEX($B$35:$M$50,($Q$32-1-1)*$Q$33+X55+1,0*$Q$34+W55+1)="",0,IF(INDEX($B$35:$M$50,($Q$32-1-1)*$Q$33+X55+1,0*$Q$34+W55+1)<0,ABS(INDEX($B$35:$M$50,($Q$32-1-1)*$Q$33+X55+1,0*$Q$34+W55+1))/$Q$48*$Q$42,0))) -> 0 | AM55: =IF(V55=1,0,IF(INDEX($B$35:$M$50,($Q$32-1-2)*$Q$33+X55+1,0*$Q$34+W55+1)="",0,IF(INDEX($B$35:$M$50,($Q$32-1-2)*$Q$33+X55+1,0*$Q$34+W55+1)>=0,ABS(INDEX($B$35:$M$50,($Q$32-1-2)*$Q$33+X55+1,0*$Q$34+W55+1))/$Q$48*$Q$42,0))) -> 0 | AN55: =IF(V55=1,0,IF(INDEX($B$35:$M$50,($Q$32-1-2)*$Q$33+X55+1,0*$Q$34+W55+1)="",0,IF(INDEX($B$35:$M$50,($Q$32-1-2)*$Q$33+X55+1,0*$Q$34+W55+1)<0,ABS(INDEX($B$35:$M$50,($Q$32-1-2)*$Q$33+X55+1,0*$Q$34+W55+1))/$Q$48*$Q$42,0))) -> 0 | AO55: =IF(V55=1,0,IF(INDEX($B$35:$M$50,($Q$32-1-3)*$Q$33+X55+1,0*$Q$34+W55+1)="",0,IF(INDEX($B$35:$M$50,($Q$32-1-3)*$Q$33+X55+1,0*$Q$34+W55+1)>=0,ABS(INDEX($B$35:$M$50,($Q$32-1-3)*$Q$33+X55+1,0*$Q$34+W55+1))/$Q$48*$Q$42,0))) -> 0 | AP55: =IF(V55=1,0,IF(INDEX($B$35:$M$50,($Q$32-1-3)*$Q$33+X55+1,0*$Q$34+W55+1)="",0,IF(INDEX($B$35:$M$50,($Q$32-1-3)*$Q$33+X55+1,0*$Q$34+W55+1)<0,ABS(INDEX($B$35:$M$50,($Q$32-1-3)*$Q$33+X55+1,0*$Q$34+W55+1))/$Q$48*$Q$42,0))) -> 0 | AR55: =IF(V55=1,"",IF(INDEX($B$35:$M$50,($Q$32-1-0)*$Q$33+X55+1,0*$Q$34+W55+1)="","",IF(INDEX($B$35:$M$50,($Q$32-1-0)*$Q$33+X55+1,0*$Q$34+W55+1)>=0,TEXT(INDEX($B$35:$M$50,($Q$32-1-0)*$Q$33+X55+1,0*$Q$34+W55+1),"+0;-0;0"),""))) | AS55: =IF(V55=1,"",IF(INDEX($B$35:$M$50,($Q$32-1-0)*$Q$33+X55+1,0*$Q$34+W55+1)="","",IF(INDEX($B$35:$M$50,($Q$32-1-0)*$Q$33+X55+1,0*$Q$34+W55+1)<0,TEXT(INDEX($B$35:$M$50,($Q$32-1-0)*$Q$33+X55+1,0*$Q$34+W55+1),"+0;-0;0"),""))) | AT55: =IF(V55=1,"",IF(INDEX($B$35:$M$50,($Q$32-1-1)*$Q$33+X55+1,0*$Q$34+W55+1)="","",IF(INDEX($B$35:$M$50,($Q$32-1-1)*$Q$33+X55+1,0*$Q$34+W55+1)>=0,TEXT(INDEX($B$35:$M$50,($Q$32-1-1)*$Q$33+X55+1,0*$Q$34+W55+1),"+0;-0;0"),""))) | AU55: =IF(V55=1,"",IF(INDEX($B$35:$M$50,($Q$32-1-1)*$Q$33+X55+1,0*$Q$34+W55+1)="","",IF(INDEX($B$35:$M$50,($Q$32-1-1)*$Q$33+X55+1,0*$Q$34+W55+1)<0,TEXT(INDEX($B$35:$M$50,($Q$32-1-1)*$Q$33+X55+1,0*$Q$34+W55+1),"+0;-0;0"),""))) | AV55: =IF(V55=1,"",IF(INDEX($B$35:$M$50,($Q$32-1-2)*$Q$33+X55+1,0*$Q$34+W55+1)="","",IF(INDEX($B$35:$M$50,($Q$32-1-2)*$Q$33+X55+1,0*$Q$34+W55+1)>=0,TEXT(INDEX($B$35:$M$50,($Q$32-1-2)*$Q$33+X55+1,0*$Q$34+W55+1),"+0;-0;0"),""))) | AW55: =IF(V55=1,"",IF(INDEX($B$35:$M$50,($Q$32-1-2)*$Q$33+X55+1,0*$Q$34+W55+1)="","",IF(INDEX($B$35:$M$50,($Q$32-1-2)*$Q$33+X55+1,0*$Q$34+W55+1)<0,TEXT(INDEX($B$35:$M$50,($Q$32-1-2)*$Q$33+X55+1,0*$Q$34+W55+1),"+0;-0;0"),""))) | AX55: =IF(V55=1,"",IF(INDEX($B$35:$M$50,($Q$32-1-3)*$Q$33+X55+1,0*$Q$34+W55+1)="","",IF(INDEX($B$35:$M$50,($Q$32-1-3)*$Q$33+X55+1,0*$Q$34+W55+1)>=0,TEXT(INDEX($B$35:$M$50,($Q$32-1-3)*$Q$33+X55+1,0*$Q$34+W55+1),"+0;-0;0"),""))) | AY55: =IF(V55=1,"",IF(INDEX($B$35:$M$50,($Q$32-1-3)*$Q$33+X55+1,0*$Q$34+W55+1)="","",IF(INDEX($B$35:$M$50,($Q$32-1-3)*$Q$33+X55+1,0*$Q$34+W55+1)<0,TEXT(INDEX($B$35:$M$50,($Q$32-1-3)*$Q$33+X55+1,0*$Q$34+W55+1),"+0;-0;0"),""))) | BA55: 16 | BB55: =NA() -> #N/A | BD55: 54.5 | BE55: =NA() -> #N/A | BG55: 15.5 | BH55: =NA() -> #N/A | BJ55: 30 | BK55: =3+$Q$42+0.03 -> 3.85 | BL55: ='C13D'!$A$37 -> 2013 | BN55: 3.35 | BO55: =0+1*$Q$42 -> 0.82 | BP55: =TEXT($Q$46+($Q$47-$Q$46)*1,"#,##0") -> 250
P56: 4 | Q56: =P56-$Q$41 -> 1 | R56: =IF(Q56<=0,-1,INT((Q56-1)/($Q$39+$Q$40))) -> 0 | S56: =IF(Q56<=0,-1,MOD(Q56-1,($Q$39+$Q$40))) -> 0 | T56: =IF(OR(S56<0,S56>=$Q$39),-1,INT(S56/$Q$38)) -> 0 | U56: =IF(OR(S56<0,S56>=$Q$39),-1,MOD(S56,$Q$38)) -> 0 | V56: =IF(OR(Q56<=0,S56<0,S56>=$Q$39,R56>=$Q$36),1,0) -> 0 | W56: =IF(V56=1,-1,T56) -> 0 | X56: =IF(V56=1,-1,R56) -> 0 | Y56: =IF(V56=1,"",IF(AND(MOD(W56,3)=0,U56=INT(($Q$38-1)/2)),INDEX($B$34:$M$34,W56+1),"")) -> Jan | Z56: =IF(V56=1,NA(),IF(INDEX($B$35:$M$50,($Q$32-1-0)*$Q$33+X56+1,0*$Q$34+W56+1)="",NA(),IF(INDEX($B$35:$M$50,($Q$32-1-0)*$Q$33+X56+1,0*$Q$34+W56+1)>=0,0+(INDEX($B$35:$M$50,($Q$32-1-0)*$Q$33+X56+1,0*$Q$34+W56+1)-$Q$46)/$Q$48*$Q$42,NA()))) -> 0.39451432 | AA56: =IF(V56=1,NA(),IF(INDEX($B$35:$M$50,($Q$32-1-0)*$Q$33+X56+1,0*$Q$34+W56+1)="",NA(),IF(INDEX($B$35:$M$50,($Q$32-1-0)*$Q$33+X56+1,0*$Q$34+W56+1)<0,0+(INDEX($B$35:$M$50,($Q$32-1-0)*$Q$33+X56+1,0*$Q$34+W56+1)-$Q$46)/$Q$48*$Q$42,NA()))) -> #N/A | AB56: =IF(V56=1,NA(),IF(INDEX($B$35:$M$50,($Q$32-1-1)*$Q$33+X56+1,0*$Q$34+W56+1)="",NA(),IF(INDEX($B$35:$M$50,($Q$32-1-1)*$Q$33+X56+1,0*$Q$34+W56+1)>=0,1+(INDEX($B$35:$M$50,($Q$32-1-1)*$Q$33+X56+1,0*$Q$34+W56+1)-$Q$46)/$Q$48*$Q$42,NA()))) -> 1.2347805 | AC56: =IF(V56=1,NA(),IF(INDEX($B$35:$M$50,($Q$32-1-1)*$Q$33+X56+1,0*$Q$34+W56+1)="",NA(),IF(INDEX($B$35:$M$50,($Q$32-1-1)*$Q$33+X56+1,0*$Q$34+W56+1)<0,1+(INDEX($B$35:$M$50,($Q$32-1-1)*$Q$33+X56+1,0*$Q$34+W56+1)-$Q$46)/$Q$48*$Q$42,NA()))) -> #N/A | AD56: =IF(V56=1,NA(),IF(INDEX($B$35:$M$50,($Q$32-1-2)*$Q$33+X56+1,0*$Q$34+W56+1)="",NA(),IF(INDEX($B$35:$M$50,($Q$32-1-2)*$Q$33+X56+1,0*$Q$34+W56+1)>=0,2+(INDEX($B$35:$M$50,($Q$32-1-2)*$Q$33+X56+1,0*$Q$34+W56+1)-$Q$46)/$Q$48*$Q$42,NA()))) -> #N/A | AE56: =IF(V56=1,NA(),IF(INDEX($B$35:$M$50,($Q$32-1-2)*$Q$33+X56+1,0*$Q$34+W56+1)="",NA(),IF(INDEX($B$35:$M$50,($Q$32-1-2)*$Q$33+X56+1,0*$Q$34+W56+1)<0,2+(INDEX($B$35:$M$50,($Q$32-1-2)*$Q$33+X56+1,0*$Q$34+W56+1)-$Q$46)/$Q$48*$Q$42,NA()))) -> 2.1312261 | AF56: =IF(V56=1,NA(),IF(INDEX($B$35:$M$50,($Q$32-1-3)*$Q$33+X56+1,0*$Q$34+W56+1)="",NA(),IF(INDEX($B$35:$M$50,($Q$32-1-3)*$Q$33+X56+1,0*$Q$34+W56+1)>=0,3+(INDEX($B$35:$M$50,($Q$32-1-3)*$Q$33+X56+1,0*$Q$34+W56+1)-$Q$46)/$Q$48*$Q$42,NA()))) -> #N/A | AG56: =IF(V56=1,NA(),IF(INDEX($B$35:$M$50,($Q$32-1-3)*$Q$33+X56+1,0*$Q$34+W56+1)="",NA(),IF(INDEX($B$35:$M$50,($Q$32-1-3)*$Q$33+X56+1,0*$Q$34+W56+1)<0,3+(INDEX($B$35:$M$50,($Q$32-1-3)*$Q$33+X56+1,0*$Q$34+W56+1)-$Q$46)/$Q$48*$Q$42,NA()))) -> 3.1017342 | AI56: =IF(V56=1,0,IF(INDEX($B$35:$M$50,($Q$32-1-0)*$Q$33+X56+1,0*$Q$34+W56+1)="",0,IF(INDEX($B$35:$M$50,($Q$32-1-0)*$Q$33+X56+1,0*$Q$34+W56+1)>=0,ABS(INDEX($B$35:$M$50,($Q$32-1-0)*$Q$33+X56+1,0*$Q$34+W56+1))/$Q$48*$Q$42,0))) -> 0.16022861 | AJ56: =IF(V56=1,0,IF(INDEX($B$35:$M$50,($Q$32-1-0)*$Q$33+X56+1,0*$Q$34+W56+1)="",0,IF(INDEX($B$35:$M$50,($Q$32-1-0)*$Q$33+X56+1,0*$Q$34+W56+1)<0,ABS(INDEX($B$35:$M$50,($Q$32-1-0)*$Q$33+X56+1,0*$Q$34+W56+1))/$Q$48*$Q$42,0))) -> 0 | AK56: =IF(V56=1,0,IF(INDEX($B$35:$M$50,($Q$32-1-1)*$Q$33+X56+1,0*$Q$34+W56+1)="",0,IF(INDEX($B$35:$M$50,($Q$32-1-1)*$Q$33+X56+1,0*$Q$34+W56+1)>=0,ABS(INDEX($B$35:$M$50,($Q$32-1-1)*$Q$33+X56+1,0*$Q$34+W56+1))/$Q$48*$Q$42,0))) -> 0.00049473674 | AL56: =IF(V56=1,0,IF(INDEX($B$35:$M$50,($Q$32-1-1)*$Q$33+X56+1,0*$Q$34+W56+1)="",0,IF(INDEX($B$35:$M$50,($Q$32-1-1)*$Q$33+X56+1,0*$Q$34+W56+1)<0,ABS(INDEX($B$35:$M$50,($Q$32-1-1)*$Q$33+X56+1,0*$Q$34+W56+1))/$Q$48*$Q$42,0))) -> 0 | AM56: =IF(V56=1,0,IF(INDEX($B$35:$M$50,($Q$32-1-2)*$Q$33+X56+1,0*$Q$34+W56+1)="",0,IF(INDEX($B$35:$M$50,($Q$32-1-2)*$Q$33+X56+1,0*$Q$34+W56+1)>=0,ABS(INDEX($B$35:$M$50,($Q$32-1-2)*$Q$33+X56+1,0*$Q$34+W56+1))/$Q$48*$Q$42,0))) -> 0 | AN56: =IF(V56=1,0,IF(INDEX($B$35:$M$50,($Q$32-1-2)*$Q$33+X56+1,0*$Q$34+W56+1)="",0,IF(INDEX($B$35:$M$50,($Q$32-1-2)*$Q$33+X56+1,0*$Q$34+W56+1)<0,ABS(INDEX($B$35:$M$50,($Q$32-1-2)*$Q$33+X56+1,0*$Q$34+W56+1))/$Q$48*$Q$42,0))) -> 0.10305963 | AO56: =IF(V56=1,0,IF(INDEX($B$35:$M$50,($Q$32-1-3)*$Q$33+X56+1,0*$Q$34+W56+1)="",0,IF(INDEX($B$35:$M$50,($Q$32-1-3)*$Q$33+X56+1,0*$Q$34+W56+1)>=0,ABS(INDEX($B$35:$M$50,($Q$32-1-3)*$Q$33+X56+1,0*$Q$34+W56+1))/$Q$48*$Q$42,0))) -> 0 | AP56: =IF(V56=1,0,IF(INDEX($B$35:$M$50,($Q$32-1-3)*$Q$33+X56+1,0*$Q$34+W56+1)="",0,IF(INDEX($B$35:$M$50,($Q$32-1-3)*$Q$33+X56+1,0*$Q$34+W56+1)<0,ABS(INDEX($B$35:$M$50,($Q$32-1-3)*$Q$33+X56+1,0*$Q$34+W56+1))/$Q$48*$Q$42,0))) -> 0.13255146 | AR56: =IF(V56=1,"",IF(INDEX($B$35:$M$50,($Q$32-1-0)*$Q$33+X56+1,0*$Q$34+W56+1)="","",IF(INDEX($B$35:$M$50,($Q$32-1-0)*$Q$33+X56+1,0*$Q$34+W56+1)>=0,TEXT(INDEX($B$35:$M$50,($Q$32-1-0)*$Q$33+X56+1,0*$Q$34+W56+1),"+0;-0;0"),""))) -> +68 | AS56: =IF(V56=1,"",IF(INDEX($B$35:$M$50,($Q$32-1-0)*$Q$33+X56+1,0*$Q$34+W56+1)="","",IF(INDEX($B$35:$M$50,($Q$32-1-0)*$Q$33+X56+1,0*$Q$34+W56+1)<0,TEXT(INDEX($B$35:$M$50,($Q$32-1-0)*$Q$33+X56+1,0*$Q$34+W56+1),"+0;-0;0"),""))) | AT56: =IF(V56=1,"",IF(INDEX($B$35:$M$50,($Q$32-1-1)*$Q$33+X56+1,0*$Q$34+W56+1)="","",IF(INDEX($B$35:$M$50,($Q$32-1-1)*$Q$33+X56+1,0*$Q$34+W56+1)>=0,TEXT(INDEX($B$35:$M$50,($Q$32-1-1)*$Q$33+X56+1,0*$Q$34+W56+1),"+0;-0;0"),""))) -> +0 | AU56: =IF(V56=1,"",IF(INDEX($B$35:$M$50,($Q$32-1-1)*$Q$33+X56+1,0*$Q$34+W56+1)="","",IF(INDEX($B$35:$M$50,($Q$32-1-1)*$Q$33+X56+1,0*$Q$34+W56+1)<0,TEXT(INDEX($B$35:$M$50,($Q$32-1-1)*$Q$33+X56+1,0*$Q$34+W56+1),"+0;-0;0"),""))) | AV56: =IF(V56=1,"",IF(INDEX($B$35:$M$50,($Q$32-1-2)*$Q$33+X56+1,0*$Q$34+W56+1)="","",IF(INDEX($B$35:$M$50,($Q$32-1-2)*$Q$33+X56+1,0*$Q$34+W56+1)>=0,TEXT(INDEX($B$35:$M$50,($Q$32-1-2)*$Q$33+X56+1,0*$Q$34+W56+1),"+0;-0;0"),""))) | AW56: =IF(V56=1,"",IF(INDEX($B$35:$M$50,($Q$32-1-2)*$Q$33+X56+1,0*$Q$34+W56+1)="","",IF(INDEX($B$35:$M$50,($Q$32-1-2)*$Q$33+X56+1,0*$Q$34+W56+1)<0,TEXT(INDEX($B$35:$M$50,($Q$32-1-2)*$Q$33+X56+1,0*$Q$34+W56+1),"+0;-0;0"),""))) -> -44 | AX56: =IF(V56=1,"",IF(INDEX($B$35:$M$50,($Q$32-1-3)*$Q$33+X56+1,0*$Q$34+W56+1)="","",IF(INDEX($B$35:$M$50,($Q$32-1-3)*$Q$33+X56+1,0*$Q$34+W56+1)>=0,TEXT(INDEX($B$35:$M$50,($Q$32-1-3)*$Q$33+X56+1,0*$Q$34+W56+1),"+0;-0;0"),""))) | AY56: =IF(V56=1,"",IF(INDEX($B$35:$M$50,($Q$32-1-3)*$Q$33+X56+1,0*$Q$34+W56+1)="","",IF(INDEX($B$35:$M$50,($Q$32-1-3)*$Q$33+X56+1,0*$Q$34+W56+1)<0,TEXT(INDEX($B$35:$M$50,($Q$32-1-3)*$Q$33+X56+1,0*$Q$34+W56+1),"+0;-0;0"),""))) -> -57 | BA56: 29 | BB56: 0 | BD56: 0.5 | BE56: 1.91 | BG56: 16.5 | BH56: =IF(OR($Q$46>0,$Q$47<0),NA(),0+$Q$49) -> 0.23428571 | BJ56: 43 | BK56: =3+$Q$42+0.03 -> 3.85 | BL56: ='C13D'!$A$38 -> 2014 | BN56: 3.35 | BO56: =1+0*$Q$42 -> 1 | BP56: =TEXT($Q$46+($Q$47-$Q$46)*0,"#,##0") -> -100
P57: 5 | Q57: =P57-$Q$41 -> 2 | R57: =IF(Q57<=0,-1,INT((Q57-1)/($Q$39+$Q$40))) -> 0 | S57: =IF(Q57<=0,-1,MOD(Q57-1,($Q$39+$Q$40))) -> 1 | T57: =IF(OR(S57<0,S57>=$Q$39),-1,INT(S57/$Q$38)) -> 1 | U57: =IF(OR(S57<0,S57>=$Q$39),-1,MOD(S57,$Q$38)) -> 0 | V57: =IF(OR(Q57<=0,S57<0,S57>=$Q$39,R57>=$Q$36),1,0) -> 0 | W57: =IF(V57=1,-1,T57) -> 1 | X57: =IF(V57=1,-1,R57) -> 0 | Y57: =IF(V57=1,"",IF(AND(MOD(W57,3)=0,U57=INT(($Q$38-1)/2)),INDEX($B$34:$M$34,W57+1),"")) | Z57: =IF(V57=1,NA(),IF(INDEX($B$35:$M$50,($Q$32-1-0)*$Q$33+X57+1,0*$Q$34+W57+1)="",NA(),IF(INDEX($B$35:$M$50,($Q$32-1-0)*$Q$33+X57+1,0*$Q$34+W57+1)>=0,0+(INDEX($B$35:$M$50,($Q$32-1-0)*$Q$33+X57+1,0*$Q$34+W57+1)-$Q$46)/$Q$48*$Q$42,NA()))) -> 0.44642297 | AA57: =IF(V57=1,NA(),IF(INDEX($B$35:$M$50,($Q$32-1-0)*$Q$33+X57+1,0*$Q$34+W57+1)="",NA(),IF(INDEX($B$35:$M$50,($Q$32-1-0)*$Q$33+X57+1,0*$Q$34+W57+1)<0,0+(INDEX($B$35:$M$50,($Q$32-1-0)*$Q$33+X57+1,0*$Q$34+W57+1)-$Q$46)/$Q$48*$Q$42,NA()))) -> #N/A | AB57: =IF(V57=1,NA(),IF(INDEX($B$35:$M$50,($Q$32-1-1)*$Q$33+X57+1,0*$Q$34+W57+1)="",NA(),IF(INDEX($B$35:$M$50,($Q$32-1-1)*$Q$33+X57+1,0*$Q$34+W57+1)>=0,1+(INDEX($B$35:$M$50,($Q$32-1-1)*$Q$33+X57+1,0*$Q$34+W57+1)-$Q$46)/$Q$48*$Q$42,NA()))) -> #N/A | AC57: =IF(V57=1,NA(),IF(INDEX($B$35:$M$50,($Q$32-1-1)*$Q$33+X57+1,0*$Q$34+W57+1)="",NA(),IF(INDEX($B$35:$M$50,($Q$32-1-1)*$Q$33+X57+1,0*$Q$34+W57+1)<0,1+(INDEX($B$35:$M$50,($Q$32-1-1)*$Q$33+X57+1,0*$Q$34+W57+1)-$Q$46)/$Q$48*$Q$42,NA()))) -> 1.228967 | AD57: =IF(V57=1,NA(),IF(INDEX($B$35:$M$50,($Q$32-1-2)*$Q$33+X57+1,0*$Q$34+W57+1)="",NA(),IF(INDEX($B$35:$M$50,($Q$32-1-2)*$Q$33+X57+1,0*$Q$34+W57+1)>=0,2+(INDEX($B$35:$M$50,($Q$32-1-2)*$Q$33+X57+1,0*$Q$34+W57+1)-$Q$46)/$Q$48*$Q$42,NA()))) -> #N/A | AE57: =IF(V57=1,NA(),IF(INDEX($B$35:$M$50,($Q$32-1-2)*$Q$33+X57+1,0*$Q$34+W57+1)="",NA(),IF(INDEX($B$35:$M$50,($Q$32-1-2)*$Q$33+X57+1,0*$Q$34+W57+1)<0,2+(INDEX($B$35:$M$50,($Q$32-1-2)*$Q$33+X57+1,0*$Q$34+W57+1)-$Q$46)/$Q$48*$Q$42,NA()))) -> 2.1243143 | AF57: =IF(V57=1,NA(),IF(INDEX($B$35:$M$50,($Q$32-1-3)*$Q$33+X57+1,0*$Q$34+W57+1)="",NA(),IF(INDEX($B$35:$M$50,($Q$32-1-3)*$Q$33+X57+1,0*$Q$34+W57+1)>=0,3+(INDEX($B$35:$M$50,($Q$32-1-3)*$Q$33+X57+1,0*$Q$34+W57+1)-$Q$46)/$Q$48*$Q$42,NA()))) -> #N/A | AG57: =IF(V57=1,NA(),IF(INDEX($B$35:$M$50,($Q$32-1-3)*$Q$33+X57+1,0*$Q$34+W57+1)="",NA(),IF(INDEX($B$35:$M$50,($Q$32-1-3)*$Q$33+X57+1,0*$Q$34+W57+1)<0,3+(INDEX($B$35:$M$50,($Q$32-1-3)*$Q$33+X57+1,0*$Q$34+W57+1)-$Q$46)/$Q$48*$Q$42,NA()))) -> 3.0960158 | AI57: =IF(V57=1,0,IF(INDEX($B$35:$M$50,($Q$32-1-0)*$Q$33+X57+1,0*$Q$34+W57+1)="",0,IF(INDEX($B$35:$M$50,($Q$32-1-0)*$Q$33+X57+1,0*$Q$34+W57+1)>=0,ABS(INDEX($B$35:$M$50,($Q$32-1-0)*$Q$33+X57+1,0*$Q$34+W57+1))/$Q$48*$Q$42,0))) -> 0.21213726 | AJ57: =IF(V57=1,0,IF(INDEX($B$35:$M$50,($Q$32-1-0)*$Q$33+X57+1,0*$Q$34+W57+1)="",0,IF(INDEX($B$35:$M$50,($Q$32-1-0)*$Q$33+X57+1,0*$Q$34+W57+1)<0,ABS(INDEX($B$35:$M$50,($Q$32-1-0)*$Q$33+X57+1,0*$Q$34+W57+1))/$Q$48*$Q$42,0))) -> 0 | AK57: =IF(V57=1,0,IF(INDEX($B$35:$M$50,($Q$32-1-1)*$Q$33+X57+1,0*$Q$34+W57+1)="",0,IF(INDEX($B$35:$M$50,($Q$32-1-1)*$Q$33+X57+1,0*$Q$34+W57+1)>=0,ABS(INDEX($B$35:$M$50,($Q$32-1-1)*$Q$33+X57+1,0*$Q$34+W57+1))/$Q$48*$Q$42,0))) -> 0 | AL57: =IF(V57=1,0,IF(INDEX($B$35:$M$50,($Q$32-1-1)*$Q$33+X57+1,0*$Q$34+W57+1)="",0,IF(INDEX($B$35:$M$50,($Q$32-1-1)*$Q$33+X57+1,0*$Q$34+W57+1)<0,ABS(INDEX($B$35:$M$50,($Q$32-1-1)*$Q$33+X57+1,0*$Q$34+W57+1))/$Q$48*$Q$42,0))) -> 0.0053187351 | AM57: =IF(V57=1,0,IF(INDEX($B$35:$M$50,($Q$32-1-2)*$Q$33+X57+1,0*$Q$34+W57+1)="",0,IF(INDEX($B$35:$M$50,($Q$32-1-2)*$Q$33+X57+1,0*$Q$34+W57+1)>=0,ABS(INDEX($B$35:$M$50,($Q$32-1-2)*$Q$33+X57+1,0*$Q$34+W57+1))/$Q$48*$Q$42,0))) -> 0 | AN57: =IF(V57=1,0,IF(INDEX($B$35:$M$50,($Q$32-1-2)*$Q$33+X57+1,0*$Q$34+W57+1)="",0,IF(INDEX($B$35:$M$50,($Q$32-1-2)*$Q$33+X57+1,0*$Q$34+W57+1)<0,ABS(INDEX($B$35:$M$50,($Q$32-1-2)*$Q$33+X57+1,0*$Q$34+W57+1))/$Q$48*$Q$42,0))) -> 0.10997146 | AO57: =IF(V57=1,0,IF(INDEX($B$35:$M$50,($Q$32-1-3)*$Q$33+X57+1,0*$Q$34+W57+1)="",0,IF(INDEX($B$35:$M$50,($Q$32-1-3)*$Q$33+X57+1,0*$Q$34+W57+1)>=0,ABS(INDEX($B$35:$M$50,($Q$32-1-3)*$Q$33+X57+1,0*$Q$34+W57+1))/$Q$48*$Q$42,0))) -> 0 | AP57: =IF(V57=1,0,IF(INDEX($B$35:$M$50,($Q$32-1-3)*$Q$33+X57+1,0*$Q$34+W57+1)="",0,IF(INDEX($B$35:$M$50,($Q$32-1-3)*$Q$33+X57+1,0*$Q$34+W57+1)<0,ABS(INDEX($B$35:$M$50,($Q$32-1-3)*$Q$33+X57+1,0*$Q$34+W57+1))/$Q$48*$Q$42,0))) -> 0.13826992 | AR57: =IF(V57=1,"",IF(INDEX($B$35:$M$50,($Q$32-1-0)*$Q$33+X57+1,0*$Q$34+W57+1)="","",IF(INDEX($B$35:$M$50,($Q$32-1-0)*$Q$33+X57+1,0*$Q$34+W57+1)>=0,TEXT(INDEX($B$35:$M$50,($Q$32-1-0)*$Q$33+X57+1,0*$Q$34+W57+1),"+0;-0;0"),""))) -> +91 | AS57: =IF(V57=1,"",IF(INDEX($B$35:$M$50,($Q$32-1-0)*$Q$33+X57+1,0*$Q$34+W57+1)="","",IF(INDEX($B$35:$M$50,($Q$32-1-0)*$Q$33+X57+1,0*$Q$34+W57+1)<0,TEXT(INDEX($B$35:$M$50,($Q$32-1-0)*$Q$33+X57+1,0*$Q$34+W57+1),"+0;-0;0"),""))) | AT57: =IF(V57=1,"",IF(INDEX($B$35:$M$50,($Q$32-1-1)*$Q$33+X57+1,0*$Q$34+W57+1)="","",IF(INDEX($B$35:$M$50,($Q$32-1-1)*$Q$33+X57+1,0*$Q$34+W57+1)>=0,TEXT(INDEX($B$35:$M$50,($Q$32-1-1)*$Q$33+X57+1,0*$Q$34+W57+1),"+0;-0;0"),""))) | AU57: =IF(V57=1,"",IF(INDEX($B$35:$M$50,($Q$32-1-1)*$Q$33+X57+1,0*$Q$34+W57+1)="","",IF(INDEX($B$35:$M$50,($Q$32-1-1)*$Q$33+X57+1,0*$Q$34+W57+1)<0,TEXT(INDEX($B$35:$M$50,($Q$32-1-1)*$Q$33+X57+1,0*$Q$34+W57+1),"+0;-0;0"),""))) -> -2 | AV57: =IF(V57=1,"",IF(INDEX($B$35:$M$50,($Q$32-1-2)*$Q$33+X57+1,0*$Q$34+W57+1)="","",IF(INDEX($B$35:$M$50,($Q$32-1-2)*$Q$33+X57+1,0*$Q$34+W57+1)>=0,TEXT(INDEX($B$35:$M$50,($Q$32-1-2)*$Q$33+X57+1,0*$Q$34+W57+1),"+0;-0;0"),""))) | AW57: =IF(V57=1,"",IF(INDEX($B$35:$M$50,($Q$32-1-2)*$Q$33+X57+1,0*$Q$34+W57+1)="","",IF(INDEX($B$35:$M$50,($Q$32-1-2)*$Q$33+X57+1,0*$Q$34+W57+1)<0,TEXT(INDEX($B$35:$M$50,($Q$32-1-2)*$Q$33+X57+1,0*$Q$34+W57+1),"+0;-0;0"),""))) -> -47 | AX57: =IF(V57=1,"",IF(INDEX($B$35:$M$50,($Q$32-1-3)*$Q$33+X57+1,0*$Q$34+W57+1)="","",IF(INDEX($B$35:$M$50,($Q$32-1-3)*$Q$33+X57+1,0*$Q$34+W57+1)>=0,TEXT(INDEX($B$35:$M$50,($Q$32-1-3)*$Q$33+X57+1,0*$Q$34+W57+1),"+0;-0;0"),""))) | AY57: =IF(V57=1,"",IF(INDEX($B$35:$M$50,($Q$32-1-3)*$Q$33+X57+1,0*$Q$34+W57+1)="","",IF(INDEX($B$35:$M$50,($Q$32-1-3)*$Q$33+X57+1,0*$Q$34+W57+1)<0,TEXT(INDEX($B$35:$M$50,($Q$32-1-3)*$Q$33+X57+1,0*$Q$34+W57+1),"+0;-0;0"),""))) -> -59 | BA57: 29 | BB57: 4 | BD57: 54.5 | BE57: 1.91 | BG57: 28.5 | BH57: =IF(OR($Q$46>0,$Q$47<0),NA(),0+$Q$49) -> 0.23428571 | BJ57: 4 | BK57: =2+$Q$42+0.03 -> 2.85 | BL57: ='C13D'!$A$39 -> 2015 | BN57: 3.35 | BO57: =1+0.5*$Q$42 -> 1.41 | BP57: =TEXT($Q$46+($Q$47-$Q$46)*0.5,"#,##0") -> 75
P58: 6 | Q58: =P58-$Q$41 -> 3 | R58: =IF(Q58<=0,-1,INT((Q58-1)/($Q$39+$Q$40))) -> 0 | S58: =IF(Q58<=0,-1,MOD(Q58-1,($Q$39+$Q$40))) -> 2 | T58: =IF(OR(S58<0,S58>=$Q$39),-1,INT(S58/$Q$38)) -> 2 | U58: =IF(OR(S58<0,S58>=$Q$39),-1,MOD(S58,$Q$38)) -> 0 | V58: =IF(OR(Q58<=0,S58<0,S58>=$Q$39,R58>=$Q$36),1,0) -> 0 | W58: =IF(V58=1,-1,T58) -> 2 | X58: =IF(V58=1,-1,R58) -> 0 | Y58: =IF(V58=1,"",IF(AND(MOD(W58,3)=0,U58=INT(($Q$38-1)/2)),INDEX($B$34:$M$34,W58+1),"")) | Z58: =IF(V58=1,NA(),IF(INDEX($B$35:$M$50,($Q$32-1-0)*$Q$33+X58+1,0*$Q$34+W58+1)="",NA(),IF(INDEX($B$35:$M$50,($Q$32-1-0)*$Q$33+X58+1,0*$Q$34+W58+1)>=0,0+(INDEX($B$35:$M$50,($Q$32-1-0)*$Q$33+X58+1,0*$Q$34+W58+1)-$Q$46)/$Q$48*$Q$42,NA()))) -> 0.34092728 | AA58: =IF(V58=1,NA(),IF(INDEX($B$35:$M$50,($Q$32-1-0)*$Q$33+X58+1,0*$Q$34+W58+1)="",NA(),IF(INDEX($B$35:$M$50,($Q$32-1-0)*$Q$33+X58+1,0*$Q$34+W58+1)<0,0+(INDEX($B$35:$M$50,($Q$32-1-0)*$Q$33+X58+1,0*$Q$34+W58+1)-$Q$46)/$Q$48*$Q$42,NA()))) -> #N/A | AB58: =IF(V58=1,NA(),IF(INDEX($B$35:$M$50,($Q$32-1-1)*$Q$33+X58+1,0*$Q$34+W58+1)="",NA(),IF(INDEX($B$35:$M$50,($Q$32-1-1)*$Q$33+X58+1,0*$Q$34+W58+1)>=0,1+(INDEX($B$35:$M$50,($Q$32-1-1)*$Q$33+X58+1,0*$Q$34+W58+1)-$Q$46)/$Q$48*$Q$42,NA()))) -> #N/A | AC58: =IF(V58=1,NA(),IF(INDEX($B$35:$M$50,($Q$32-1-1)*$Q$33+X58+1,0*$Q$34+W58+1)="",NA(),IF(INDEX($B$35:$M$50,($Q$32-1-1)*$Q$33+X58+1,0*$Q$34+W58+1)<0,1+(INDEX($B$35:$M$50,($Q$32-1-1)*$Q$33+X58+1,0*$Q$34+W58+1)-$Q$46)/$Q$48*$Q$42,NA()))) -> 1.2137892 | AD58: =IF(V58=1,NA(),IF(INDEX($B$35:$M$50,($Q$32-1-2)*$Q$33+X58+1,0*$Q$34+W58+1)="",NA(),IF(INDEX($B$35:$M$50,($Q$32-1-2)*$Q$33+X58+1,0*$Q$34+W58+1)>=0,2+(INDEX($B$35:$M$50,($Q$32-1-2)*$Q$33+X58+1,0*$Q$34+W58+1)-$Q$46)/$Q$48*$Q$42,NA()))) -> #N/A | AE58: =IF(V58=1,NA(),IF(INDEX($B$35:$M$50,($Q$32-1-2)*$Q$33+X58+1,0*$Q$34+W58+1)="",NA(),IF(INDEX($B$35:$M$50,($Q$32-1-2)*$Q$33+X58+1,0*$Q$34+W58+1)<0,2+(INDEX($B$35:$M$50,($Q$32-1-2)*$Q$33+X58+1,0*$Q$34+W58+1)-$Q$46)/$Q$48*$Q$42,NA()))) -> 2.1160285 | AF58: =IF(V58=1,NA(),IF(INDEX($B$35:$M$50,($Q$32-1-3)*$Q$33+X58+1,0*$Q$34+W58+1)="",NA(),IF(INDEX($B$35:$M$50,($Q$32-1-3)*$Q$33+X58+1,0*$Q$34+W58+1)>=0,3+(INDEX($B$35:$M$50,($Q$32-1-3)*$Q$33+X58+1,0*$Q$34+W58+1)-$Q$46)/$Q$48*$Q$42,NA()))) -> #N/A | AG58: =IF(V58=1,NA(),IF(INDEX($B$35:$M$50,($Q$32-1-3)*$Q$33+X58+1,0*$Q$34+W58+1)="",NA(),IF(INDEX($B$35:$M$50,($Q$32-1-3)*$Q$33+X58+1,0*$Q$34+W58+1)<0,3+(INDEX($B$35:$M$50,($Q$32-1-3)*$Q$33+X58+1,0*$Q$34+W58+1)-$Q$46)/$Q$48*$Q$42,NA()))) -> 3.0882765 | AI58: =IF(V58=1,0,IF(INDEX($B$35:$M$50,($Q$32-1-0)*$Q$33+X58+1,0*$Q$34+W58+1)="",0,IF(INDEX($B$35:$M$50,($Q$32-1-0)*$Q$33+X58+1,0*$Q$34+W58+1)>=0,ABS(INDEX($B$35:$M$50,($Q$32-1-0)*$Q$33+X58+1,0*$Q$34+W58+1))/$Q$48*$Q$42,0))) -> 0.10664156 | AJ58: =IF(V58=1,0,IF(INDEX($B$35:$M$50,($Q$32-1-0)*$Q$33+X58+1,0*$Q$34+W58+1)="",0,IF(INDEX($B$35:$M$50,($Q$32-1-0)*$Q$33+X58+1,0*$Q$34+W58+1)<0,ABS(INDEX($B$35:$M$50,($Q$32-1-0)*$Q$33+X58+1,0*$Q$34+W58+1))/$Q$48*$Q$42,0))) -> 0 | AK58: =IF(V58=1,0,IF(INDEX($B$35:$M$50,($Q$32-1-1)*$Q$33+X58+1,0*$Q$34+W58+1)="",0,IF(INDEX($B$35:$M$50,($Q$32-1-1)*$Q$33+X58+1,0*$Q$34+W58+1)>=0,ABS(INDEX($B$35:$M$50,($Q$32-1-1)*$Q$33+X58+1,0*$Q$34+W58+1))/$Q$48*$Q$42,0))) -> 0 | AL58: =IF(V58=1,0,IF(INDEX($B$35:$M$50,($Q$32-1-1)*$Q$33+X58+1,0*$Q$34+W58+1)="",0,IF(INDEX($B$35:$M$50,($Q$32-1-1)*$Q$33+X58+1,0*$Q$34+W58+1)<0,ABS(INDEX($B$35:$M$50,($Q$32-1-1)*$Q$33+X58+1,0*$Q$34+W58+1))/$Q$48*$Q$42,0))) -> 0.020496473 | AM58: =IF(V58=1,0,IF(INDEX($B$35:$M$50,($Q$32-1-2)*$Q$33+X58+1,0*$Q$34+W58+1)="",0,IF(INDEX($B$35:$M$50,($Q$32-1-2)*$Q$33+X58+1,0*$Q$34+W58+1)>=0,ABS(INDEX($B$35:$M$50,($Q$32-1-2)*$Q$33+X58+1,0*$Q$34+W58+1))/$Q$48*$Q$42,0))) -> 0 | AN58: =IF(V58=1,0,IF(INDEX($B$35:$M$50,($Q$32-1-2)*$Q$33+X58+1,0*$Q$34+W58+1)="",0,IF(INDEX($B$35:$M$50,($Q$32-1-2)*$Q$33+X58+1,0*$Q$34+W58+1)<0,ABS(INDEX($B$35:$M$50,($Q$32-1-2)*$Q$33+X58+1,0*$Q$34+W58+1))/$Q$48*$Q$42,0))) -> 0.11825718 | AO58: =IF(V58=1,0,IF(INDEX($B$35:$M$50,($Q$32-1-3)*$Q$33+X58+1,0*$Q$34+W58+1)="",0,IF(INDEX($B$35:$M$50,($Q$32-1-3)*$Q$33+X58+1,0*$Q$34+W58+1)>=0,ABS(INDEX($B$35:$M$50,($Q$32-1-3)*$Q$33+X58+1,0*$Q$34+W58+1))/$Q$48*$Q$42,0))) -> 0 | AP58: =IF(V58=1,0,IF(INDEX($B$35:$M$50,($Q$32-1-3)*$Q$33+X58+1,0*$Q$34+W58+1)="",0,IF(INDEX($B$35:$M$50,($Q$32-1-3)*$Q$33+X58+1,0*$Q$34+W58+1)<0,ABS(INDEX($B$35:$M$50,($Q$32-1-3)*$Q$33+X58+1,0*$Q$34+W58+1))/$Q$48*$Q$42,0))) -> 0.14600926 | AR58: =IF(V58=1,"",IF(INDEX($B$35:$M$50,($Q$32-1-0)*$Q$33+X58+1,0*$Q$34+W58+1)="","",IF(INDEX($B$35:$M$50,($Q$32-1-0)*$Q$33+X58+1,0*$Q$34+W58+1)>=0,TEXT(INDEX($B$35:$M$50,($Q$32-1-0)*$Q$33+X58+1,0*$Q$34+W58+1),"+0;-0;0"),""))) -> +46 | AS58: =IF(V58=1,"",IF(INDEX($B$35:$M$50,($Q$32-1-0)*$Q$33+X58+1,0*$Q$34+W58+1)="","",IF(INDEX($B$35:$M$50,($Q$32-1-0)*$Q$33+X58+1,0*$Q$34+W58+1)<0,TEXT(INDEX($B$35:$M$50,($Q$32-1-0)*$Q$33+X58+1,0*$Q$34+W58+1),"+0;-0;0"),""))) | AT58: =IF(V58=1,"",IF(INDEX($B$35:$M$50,($Q$32-1-1)*$Q$33+X58+1,0*$Q$34+W58+1)="","",IF(INDEX($B$35:$M$50,($Q$32-1-1)*$Q$33+X58+1,0*$Q$34+W58+1)>=0,TEXT(INDEX($B$35:$M$50,($Q$32-1-1)*$Q$33+X58+1,0*$Q$34+W58+1),"+0;-0;0"),""))) | AU58: =IF(V58=1,"",IF(INDEX($B$35:$M$50,($Q$32-1-1)*$Q$33+X58+1,0*$Q$34+W58+1)="","",IF(INDEX($B$35:$M$50,($Q$32-1-1)*$Q$33+X58+1,0*$Q$34+W58+1)<0,TEXT(INDEX($B$35:$M$50,($Q$32-1-1)*$Q$33+X58+1,0*$Q$34+W58+1),"+0;-0;0"),""))) -> -9 | AV58: =IF(V58=1,"",IF(INDEX($B$35:$M$50,($Q$32-1-2)*$Q$33+X58+1,0*$Q$34+W58+1)="","",IF(INDEX($B$35:$M$50,($Q$32-1-2)*$Q$33+X58+1,0*$Q$34+W58+1)>=0,TEXT(INDEX($B$35:$M$50,($Q$32-1-2)*$Q$33+X58+1,0*$Q$34+W58+1),"+0;-0;0"),""))) | AW58: =IF(V58=1,"",IF(INDEX($B$35:$M$50,($Q$32-1-2)*$Q$33+X58+1,0*$Q$34+W58+1)="","",IF(INDEX($B$35:$M$50,($Q$32-1-2)*$Q$33+X58+1,0*$Q$34+W58+1)<0,TEXT(INDEX($B$35:$M$50,($Q$32-1-2)*$Q$33+X58+1,0*$Q$34+W58+1),"+0;-0;0"),""))) -> -50 | AX58: =IF(V58=1,"",IF(INDEX($B$35:$M$50,($Q$32-1-3)*$Q$33+X58+1,0*$Q$34+W58+1)="","",IF(INDEX($B$35:$M$50,($Q$32-1-3)*$Q$33+X58+1,0*$Q$34+W58+1)>=0,TEXT(INDEX($B$35:$M$50,($Q$32-1-3)*$Q$33+X58+1,0*$Q$34+W58+1),"+0;-0;0"),""))) | AY58: =IF(V58=1,"",IF(INDEX($B$35:$M$50,($Q$32-1-3)*$Q$33+X58+1,0*$Q$34+W58+1)="","",IF(INDEX($B$35:$M$50,($Q$32-1-3)*$Q$33+X58+1,0*$Q$34+W58+1)<0,TEXT(INDEX($B$35:$M$50,($Q$32-1-3)*$Q$33+X58+1,0*$Q$34+W58+1),"+0;-0;0"),""))) -> -62 | BA58: 29 | BB58: =NA() -> #N/A | BD58: 54.5 | BE58: =NA() -> #N/A | BG58: 28.5 | BH58: =NA() -> #N/A | BJ58: 17 | BK58: =2+$Q$42+0.03 -> 2.85 | BL58: ='C13D'!$A$40 -> 2016 | BN58: 3.35 | BO58: =1+1*$Q$42 -> 1.82 | BP58: =TEXT($Q$46+($Q$47-$Q$46)*1,"#,##0") -> 250
P59: 7 | Q59: =P59-$Q$41 -> 4 | R59: =IF(Q59<=0,-1,INT((Q59-1)/($Q$39+$Q$40))) -> 0 | S59: =IF(Q59<=0,-1,MOD(Q59-1,($Q$39+$Q$40))) -> 3 | T59: =IF(OR(S59<0,S59>=$Q$39),-1,INT(S59/$Q$38)) -> 3 | U59: =IF(OR(S59<0,S59>=$Q$39),-1,MOD(S59,$Q$38)) -> 0 | V59: =IF(OR(Q59<=0,S59<0,S59>=$Q$39,R59>=$Q$36),1,0) -> 0 | W59: =IF(V59=1,-1,T59) -> 3 | X59: =IF(V59=1,-1,R59) -> 0 | Y59: =IF(V59=1,"",IF(AND(MOD(W59,3)=0,U59=INT(($Q$38-1)/2)),INDEX($B$34:$M$34,W59+1),"")) -> Apr | Z59: =IF(V59=1,NA(),IF(INDEX($B$35:$M$50,($Q$32-1-0)*$Q$33+X59+1,0*$Q$34+W59+1)="",NA(),IF(INDEX($B$35:$M$50,($Q$32-1-0)*$Q$33+X59+1,0*$Q$34+W59+1)>=0,0+(INDEX($B$35:$M$50,($Q$32-1-0)*$Q$33+X59+1,0*$Q$34+W59+1)-$Q$46)/$Q$48*$Q$42,NA()))) -> 0.40294511 | AA59: =IF(V59=1,NA(),IF(INDEX($B$35:$M$50,($Q$32-1-0)*$Q$33+X59+1,0*$Q$34+W59+1)="",NA(),IF(INDEX($B$35:$M$50,($Q$32-1-0)*$Q$33+X59+1,0*$Q$34+W59+1)<0,0+(INDEX($B$35:$M$50,($Q$32-1-0)*$Q$33+X59+1,0*$Q$34+W59+1)-$Q$46)/$Q$48*$Q$42,NA()))) -> #N/A | AB59: =IF(V59=1,NA(),IF(INDEX($B$35:$M$50,($Q$32-1-1)*$Q$33+X59+1,0*$Q$34+W59+1)="",NA(),IF(INDEX($B$35:$M$50,($Q$32-1-1)*$Q$33+X59+1,0*$Q$34+W59+1)>=0,1+(INDEX($B$35:$M$50,($Q$32-1-1)*$Q$33+X59+1,0*$Q$34+W59+1)-$Q$46)/$Q$48*$Q$42,NA()))) -> 1.243396 | AC59: =IF(V59=1,NA(),IF(INDEX($B$35:$M$50,($Q$32-1-1)*$Q$33+X59+1,0*$Q$34+W59+1)="",NA(),IF(INDEX($B$35:$M$50,($Q$32-1-1)*$Q$33+X59+1,0*$Q$34+W59+1)<0,1+(INDEX($B$35:$M$50,($Q$32-1-1)*$Q$33+X59+1,0*$Q$34+W59+1)-$Q$46)/$Q$48*$Q$42,NA()))) -> #N/A | AD59: =IF(V59=1,NA(),IF(INDEX($B$35:$M$50,($Q$32-1-2)*$Q$33+X59+1,0*$Q$34+W59+1)="",NA(),IF(INDEX($B$35:$M$50,($Q$32-1-2)*$Q$33+X59+1,0*$Q$34+W59+1)>=0,2+(INDEX($B$35:$M$50,($Q$32-1-2)*$Q$33+X59+1,0*$Q$34+W59+1)-$Q$46)/$Q$48*$Q$42,NA()))) -> #N/A | AE59: =IF(V59=1,NA(),IF(INDEX($B$35:$M$50,($Q$32-1-2)*$Q$33+X59+1,0*$Q$34+W59+1)="",NA(),IF(INDEX($B$35:$M$50,($Q$32-1-2)*$Q$33+X59+1,0*$Q$34+W59+1)<0,2+(INDEX($B$35:$M$50,($Q$32-1-2)*$Q$33+X59+1,0*$Q$34+W59+1)-$Q$46)/$Q$48*$Q$42,NA()))) -> 2.1368066 | AF59: =IF(V59=1,NA(),IF(INDEX($B$35:$M$50,($Q$32-1-3)*$Q$33+X59+1,0*$Q$34+W59+1)="",NA(),IF(INDEX($B$35:$M$50,($Q$32-1-3)*$Q$33+X59+1,0*$Q$34+W59+1)>=0,3+(INDEX($B$35:$M$50,($Q$32-1-3)*$Q$33+X59+1,0*$Q$34+W59+1)-$Q$46)/$Q$48*$Q$42,NA()))) -> #N/A | AG59: =IF(V59=1,NA(),IF(INDEX($B$35:$M$50,($Q$32-1-3)*$Q$33+X59+1,0*$Q$34+W59+1)="",NA(),IF(INDEX($B$35:$M$50,($Q$32-1-3)*$Q$33+X59+1,0*$Q$34+W59+1)<0,3+(INDEX($B$35:$M$50,($Q$32-1-3)*$Q$33+X59+1,0*$Q$34+W59+1)-$Q$46)/$Q$48*$Q$42,NA()))) -> 3.1021656 | AI59: =IF(V59=1,0,IF(INDEX($B$35:$M$50,($Q$32-1-0)*$Q$33+X59+1,0*$Q$34+W59+1)="",0,IF(INDEX($B$35:$M$50,($Q$32-1-0)*$Q$33+X59+1,0*$Q$34+W59+1)>=0,ABS(INDEX($B$35:$M$50,($Q$32-1-0)*$Q$33+X59+1,0*$Q$34+W59+1))/$Q$48*$Q$42,0))) -> 0.1686594 | AJ59: =IF(V59=1,0,IF(INDEX($B$35:$M$50,($Q$32-1-0)*$Q$33+X59+1,0*$Q$34+W59+1)="",0,IF(INDEX($B$35:$M$50,($Q$32-1-0)*$Q$33+X59+1,0*$Q$34+W59+1)<0,ABS(INDEX($B$35:$M$50,($Q$32-1-0)*$Q$33+X59+1,0*$Q$34+W59+1))/$Q$48*$Q$42,0))) -> 0 | AK59: =IF(V59=1,0,IF(INDEX($B$35:$M$50,($Q$32-1-1)*$Q$33+X59+1,0*$Q$34+W59+1)="",0,IF(INDEX($B$35:$M$50,($Q$32-1-1)*$Q$33+X59+1,0*$Q$34+W59+1)>=0,ABS(INDEX($B$35:$M$50,($Q$32-1-1)*$Q$33+X59+1,0*$Q$34+W59+1))/$Q$48*$Q$42,0))) -> 0.009110271 | AL59: =IF(V59=1,0,IF(INDEX($B$35:$M$50,($Q$32-1-1)*$Q$33+X59+1,0*$Q$34+W59+1)="",0,IF(INDEX($B$35:$M$50,($Q$32-1-1)*$Q$33+X59+1,0*$Q$34+W59+1)<0,ABS(INDEX($B$35:$M$50,($Q$32-1-1)*$Q$33+X59+1,0*$Q$34+W59+1))/$Q$48*$Q$42,0))) -> 0 | AM59: =IF(V59=1,0,IF(INDEX($B$35:$M$50,($Q$32-1-2)*$Q$33+X59+1,0*$Q$34+W59+1)="",0,IF(INDEX($B$35:$M$50,($Q$32-1-2)*$Q$33+X59+1,0*$Q$34+W59+1)>=0,ABS(INDEX($B$35:$M$50,($Q$32-1-2)*$Q$33+X59+1,0*$Q$34+W59+1))/$Q$48*$Q$42,0))) -> 0 | AN59: =IF(V59=1,0,IF(INDEX($B$35:$M$50,($Q$32-1-2)*$Q$33+X59+1,0*$Q$34+W59+1)="",0,IF(INDEX($B$35:$M$50,($Q$32-1-2)*$Q$33+X59+1,0*$Q$34+W59+1)<0,ABS(INDEX($B$35:$M$50,($Q$32-1-2)*$Q$33+X59+1,0*$Q$34+W59+1))/$Q$48*$Q$42,0))) -> 0.097479104 | AO59: =IF(V59=1,0,IF(INDEX($B$35:$M$50,($Q$32-1-3)*$Q$33+X59+1,0*$Q$34+W59+1)="",0,IF(INDEX($B$35:$M$50,($Q$32-1-3)*$Q$33+X59+1,0*$Q$34+W59+1)>=0,ABS(INDEX($B$35:$M$50,($Q$32-1-3)*$Q$33+X59+1,0*$Q$34+W59+1))/$Q$48*$Q$42,0))) -> 0 | AP59: =IF(V59=1,0,IF(INDEX($B$35:$M$50,($Q$32-1-3)*$Q$33+X59+1,0*$Q$34+W59+1)="",0,IF(INDEX($B$35:$M$50,($Q$32-1-3)*$Q$33+X59+1,0*$Q$34+W59+1)<0,ABS(INDEX($B$35:$M$50,($Q$32-1-3)*$Q$33+X59+1,0*$Q$34+W59+1))/$Q$48*$Q$42,0))) -> 0.13212015 | AR59: =IF(V59=1,"",IF(INDEX($B$35:$M$50,($Q$32-1-0)*$Q$33+X59+1,0*$Q$34+W59+1)="","",IF(INDEX($B$35:$M$50,($Q$32-1-0)*$Q$33+X59+1,0*$Q$34+W59+1)>=0,TEXT(INDEX($B$35:$M$50,($Q$32-1-0)*$Q$33+X59+1,0*$Q$34+W59+1),"+0;-0;0"),""))) -> +72 | AS59: =IF(V59=1,"",IF(INDEX($B$35:$M$50,($Q$32-1-0)*$Q$33+X59+1,0*$Q$34+W59+1)="","",IF(INDEX($B$35:$M$50,($Q$32-1-0)*$Q$33+X59+1,0*$Q$34+W59+1)<0,TEXT(INDEX($B$35:$M$50,($Q$32-1-0)*$Q$33+X59+1,0*$Q$34+W59+1),"+0;-0;0"),""))) | AT59: =IF(V59=1,"",IF(INDEX($B$35:$M$50,($Q$32-1-1)*$Q$33+X59+1,0*$Q$34+W59+1)="","",IF(INDEX($B$35:$M$50,($Q$32-1-1)*$Q$33+X59+1,0*$Q$34+W59+1)>=0,TEXT(INDEX($B$35:$M$50,($Q$32-1-1)*$Q$33+X59+1,0*$Q$34+W59+1),"+0;-0;0"),""))) -> +4 | AU59: =IF(V59=1,"",IF(INDEX($B$35:$M$50,($Q$32-1-1)*$Q$33+X59+1,0*$Q$34+W59+1)="","",IF(INDEX($B$35:$M$50,($Q$32-1-1)*$Q$33+X59+1,0*$Q$34+W59+1)<0,TEXT(INDEX($B$35:$M$50,($Q$32-1-1)*$Q$33+X59+1,0*$Q$34+W59+1),"+0;-0;0"),""))) | AV59: =IF(V59=1,"",IF(INDEX($B$35:$M$50,($Q$32-1-2)*$Q$33+X59+1,0*$Q$34+W59+1)="","",IF(INDEX($B$35:$M$50,($Q$32-1-2)*$Q$33+X59+1,0*$Q$34+W59+1)>=0,TEXT(INDEX($B$35:$M$50,($Q$32-1-2)*$Q$33+X59+1,0*$Q$34+W59+1),"+0;-0;0"),""))) | AW59: =IF(V59=1,"",IF(INDEX($B$35:$M$50,($Q$32-1-2)*$Q$33+X59+1,0*$Q$34+W59+1)="","",IF(INDEX($B$35:$M$50,($Q$32-1-2)*$Q$33+X59+1,0*$Q$34+W59+1)<0,TEXT(INDEX($B$35:$M$50,($Q$32-1-2)*$Q$33+X59+1,0*$Q$34+W59+1),"+0;-0;0"),""))) -> -42 | AX59: =IF(V59=1,"",IF(INDEX($B$35:$M$50,($Q$32-1-3)*$Q$33+X59+1,0*$Q$34+W59+1)="","",IF(INDEX($B$35:$M$50,($Q$32-1-3)*$Q$33+X59+1,0*$Q$34+W59+1)>=0,TEXT(INDEX($B$35:$M$50,($Q$32-1-3)*$Q$33+X59+1,0*$Q$34+W59+1),"+0;-0;0"),""))) | AY59: =IF(V59=1,"",IF(INDEX($B$35:$M$50,($Q$32-1-3)*$Q$33+X59+1,0*$Q$34+W59+1)="","",IF(INDEX($B$35:$M$50,($Q$32-1-3)*$Q$33+X59+1,0*$Q$34+W59+1)<0,TEXT(INDEX($B$35:$M$50,($Q$32-1-3)*$Q$33+X59+1,0*$Q$34+W59+1),"+0;-0;0"),""))) -> -56 | BA59: 42 | BB59: 0 | BD59: 0.5 | BE59: 2.91 | BG59: 29.5 | BH59: =IF(OR($Q$46>0,$Q$47<0),NA(),0+$Q$49) -> 0.23428571 | BJ59: 30 | BK59: =2+$Q$42+0.03 -> 2.85 | BL59: ='C13D'!$A$41 -> 2017 | BN59: 3.35 | BO59: =2+0*$Q$42 -> 2 | BP59: =TEXT($Q$46+($Q$47-$Q$46)*0,"#,##0") -> -100
